Workbook
Name Beginning_Reserve_Balance_Date: 'Property Info'!$B$15
Name City_State: Expenditures!$N$6
Name City_State: 'Funding Plan'!$C$6
Name Client_City: 'Property Info'!$B$3
Name Client_Long: 'Property Info'!$B$2
Name Client_State: 'Property Info'!$B$4
Name contributions_year0: 'Funding Plan'!$E$8
Name contributions_year1: 'Funding Plan'!$F$8
Name contributions_year10: 'Funding Plan'!$O$8
Name contributions_year11: 'Funding Plan'!$P$8
Name contributions_year12: 'Funding Plan'!$Q$8
Name contributions_year13: 'Funding Plan'!$R$8
Name contributions_year14: 'Funding Plan'!$S$8
Name contributions_year15: 'Funding Plan'!$T$8
Name contributions_year16: 'Funding Plan'!$F$29
Name contributions_year17: 'Funding Plan'!$G$29
Name contributions_year18: 'Funding Plan'!$H$29
Name contributions_year19: 'Funding Plan'!$I$29
Name contributions_year2: 'Funding Plan'!$G$8
Name contributions_year20: 'Funding Plan'!$J$29
Name contributions_year21: 'Funding Plan'!$K$29
Name contributions_year22: 'Funding Plan'!$L$29
Name contributions_year23: 'Funding Plan'!$M$29
Name contributions_year24: 'Funding Plan'!$N$29
Name contributions_year25: 'Funding Plan'!$O$29
Name contributions_year26: 'Funding Plan'!$P$29
Name contributions_year27: 'Funding Plan'!$Q$29
Name contributions_year28: 'Funding Plan'!$R$29
Name contributions_year29: 'Funding Plan'!$S$29
Name contributions_year3: 'Funding Plan'!$H$8
Name contributions_year30: 'Funding Plan'!$T$29
Name contributions_year4: 'Funding Plan'!$I$8
Name contributions_year5: 'Funding Plan'!$J$8
Name contributions_year6: 'Funding Plan'!$K$8
Name contributions_year7: 'Funding Plan'!$L$8
Name contributions_year8: 'Funding Plan'!$M$8
Name contributions_year9: 'Funding Plan'!$N$8
Name Currency_Symbol: 'Property Info'!$B$22
Name Current_Fiscal_Year: 'Property Info'!$B$10
Name Date_of_Inspection: 'Property Info'!$B$9
Name expenditures0: Expenditures!$X$22
Name expenditures0: #REF!
Name expenditures1: Expenditures!$Y$22
Name expenditures1: #REF!
Name expenditures10: Expenditures!$AH$22
Name expenditures10: #REF!
Name expenditures11: Expenditures!$AI$22
Name expenditures11: #REF!
Name expenditures12: Expenditures!$AJ$22
Name expenditures12: #REF!
Name expenditures13: Expenditures!$AK$22
Name expenditures13: #REF!
Name expenditures14: Expenditures!$AL$22
Name expenditures14: #REF!
Name expenditures15: Expenditures!$AM$22
Name expenditures15: #REF!
Name expenditures16: Expenditures!$AN$22
Name expenditures16: #REF!
Name expenditures17: Expenditures!$AO$22
Name expenditures17: #REF!

Sheet Property Info
A1: Version: | B1: v7.0
A2: Association Name: | B2: The Villas at Amarra Drive Condominium Community, Inc.
A3: City: | B3: Austin
A4: State: | B4: Texas
A5: Reference Number: | B5: 253212
A6: Length of Study (Years): | B6: 30
A7: Number of Units: | B7: 20
A8: Number of Buildings: | B8: 1
A9: Date of Inspection: | B9: 46042
A10: Current Fiscal Year: | B10: 2026
A11: Fiscal Year Beginning: | B11: 46023
A12: First Year of Recommendation: | B12: 2027
A13: Remaining Budgeted Intervals: | B13: 11
A14: Remaining Budgeted Months of Interest: | B14: 11
A15: Beginning Reserve Balance Date: | B15: 46053
A16: Reserve Balance Projected: | B16: No
A17: Near Term Inflation: | B17: 0.032
A18: Last Year of Near Term Inflation: | B18: 2067
A19: Remaining Study Inflation: | B19: 0.032
A20: Interest: | B20: 0.02
A21: Frequency of Contributions: | B21: 12
A22: Currency Symbol: | B22: $
A23: Rounded_by: | B23: 100
A24: Operating_Budget: | B24: 156000
A25: Property_Type: | B25: homeowners association
B26: ="©"&Current_Fiscal_Year&" Reserve Advisors LLC. All rights reserved. Any unauthorized copying, alteration, distribution, transmission, display or other use of this spreadsheet and its contents, "&"data or formula are strictly prohibited."&" This spreadsheet is licensed to you pursuant to (and is subject in all respects to the terms and conditions of) your agreement with Reserve Advisors LLC. "&"Reserve Advisors LLC does not make, and expressly disclaims, any representations or warranties (express or implied), including, "&"without limitation, as to the accuracy or timeliness of information prepared by you or any third parties, whether linked to this spreadsheet or incorporated herein."&" We encourage you to contact us at www.reserveadvisors.com with any questions." -> ©2026 Reserve Advisors LLC. All rights reserved. Any unauthorized copying, alteration, distribution, transmission, display or other use of this spreadsheet and its contents, data or formula are strictly prohibited. This spreadsheet is licensed to you pursuant to (and is subject in all respects to the terms and conditions of) your agreement with Reserve Advisors LLC. Reserve Advisors LLC does not make, and expressly disclaims, any representations or warranties (express or implied), including, without limitation, as to the accuracy or timeliness of information prepared by you or any third parties, whether linked to this spreadsheet or incorporated herein. We encourage you to contact us at www.reserveadvisors.com with any questions.

Sheet Use Instructions
A7: Expenditure Sheet Controls:
A8: Column Range Address | B8: Column Name | C8: Description
A9: Column C | B9: Frequency of Events | C9: If an event is phased using Column E, the user can control the years in between each phase of the component.
A10: Column E | B10: Events Per Phase | C10: This value can be edited to phase an event. Ex: The user wants to include three phases of an event. The user would change the value in Column E to a value of "3".
A11: Column F | B11: Next Full Replacement | C11: This value can be edited to change the first year occurrence of an event.
A12: Column G | B12: Useful Life | C12: This value can be edited to change how often the event will occur after the initial event. Ex: The user wants to change the frequency of a replacement event from 20 years to 15 years. The user would change the value in Column G to a value of "15".
A13: Column R | B13: Costs $ (Unit) | C13: This value can be edited to update the per unit cost for a component. Ex: The user wants to update the unit cost for a component from $800.00 to $1,200.00. The user would change the value in Column R to a value of "1,200.00".
A14: Column S | B14: Costs, $ (Percentage Ownership) | C14: IF APPLICABLE to your study, this column includes the percentage of ownership that the entity is responsible to pay.
A15: Columns X through BB | B15: Years of Expenditures | C15: To apply an additional inflated expense in any year within these columns, Copy and Paste the Formula from cell Y5 onto the Line Item and in the year you would like to show the inflated cost.
A17: Funding Sheet Controls
A18: Range Address | B18: Column Name | C18: Description
A19: Cell L21 | B19: Single Increase | C19: A dollar amount entered in this cell will show up in the Funding Plan as a Single Year increase in the first non-budgeted year.
A20: Cells N21 and N22 | B20: Phased Increase | C20: A dollar amount (N21) and number of years (N22) entered in these cells will increase Reserve Contributions by the amount specified beginning in the first non-budgeted year and concluding in the number of years entered]
A21: Cells P21, P22 and P23 | B21: Stable | C21: A dollar amount (P21), beginning year (P22) and ending year (P23) will stabilize Reserve Contributions over the specified year range
A22: Cells R21 and R22 | B22: Decrease | C22: A dollar amount (R21), and a year (R22) will decrease the contributions to the specified amount in the specified year
A23: Cells T21 and T22 | B23: 2nd Decrease | C23: A dollar amount (T21), and a year (T22) will decrease the contributions to the specified amount in the specified year

Sheet Expenditures
Y1: Explanatory Notes: | AJ1: =IF(COUNTIFS($J$10:J21,"<>0",$W$10:W21,"=0"),BB9 & "+","")
N2: RESERVE EXPENDITURES | X2: 1) | Y2: =IF(Inflation=secondaryInflation,Inflation,secondaryInflation) -> 0.032 | Z2: =IF(Inflation=secondaryInflation,"is the estimated Inflation Rate for estimating Future Replacement Costs.","is the estimated Inflation Rate through "&secondaryInflationYear&".") -> is the estimated Inflation Rate for estimating Future Replacement Costs.
X3: 2) | Y3: FY2026 | Z3: is Fiscal Year beginning January 1, 2026 and ending December 31, 2026.
N4: The Villas at Amarra Drive | X4: =IF(Y4<>"","3)","") | Y4: =IF(COUNTIFS($J$10:J21,"<>0",$W$10:W21,"=0"),BB9+1 & "+","") | Z4: =IF($Y$4<>"","indicates a component which is considered long-lived","")
N5: Condominium Community, Inc. | X5: =IF(X4="","","4)") | Y5: =IF($L5="","Formula",IF(secondaryInflationYear- Current_Fiscal_Year >=Y$8,ROUND($L5* $R5*$S5*((1 + Y$7)^Y$8),1),ROUND($L5* $R5*$S5*(((1+secondaryInflation)^(secondaryInflationYear-Current_Fiscal_Year)) * ((1+Y$7)^(Y$8-(secondaryInflationYear - Current_Fiscal_Year)))),1))) -> Formula | Z5: < Copy Formula to a blank cell to show an Inflated Cost outside the regular timing intervals defined by columns B through G
N6: Austin, TX
O7: Estimated | P7: Life Analysis, | R7: Costs, $ | W7: Percentage | X7: =IF(secondaryInflationYear>=X$9,secondaryInflation,Inflation) -> 0.032 | Y7: =IF(secondaryInflationYear>=Y$9,secondaryInflation,Inflation) -> 0.032 | Z7: =IF(secondaryInflationYear>=Z$9,secondaryInflation,Inflation) -> 0.032 | AA7: =IF(secondaryInflationYear>=AA$9,secondaryInflation,Inflation) -> 0.032 | AB7: =IF(secondaryInflationYear>=AB$9,secondaryInflation,Inflation) -> 0.032 | AC7: =IF(secondaryInflationYear>=AC$9,secondaryInflation,Inflation) -> 0.032 | AD7: =IF(secondaryInflationYear>=AD$9,secondaryInflation,Inflation) -> 0.032 | AE7: =IF(secondaryInflationYear>=AE$9,secondaryInflation,Inflation) -> 0.032 | ... BB7: =IF(secondaryInflationYear>=BB$9,secondaryInflation,Inflation) -> 0.032
B8: Partial | C8: Frequency | D8: Length | E8: Events | F8: Next Full | G8: Useful | H8: Round | J8: Line | K8: Total | L8: Per Phase | O8: 1st Year of | P8: Years | R8: Unit | S8: Percentage | T8: Per Phase | U8: Total | V8: 30-Year Total | W8: of Future | X8: 0 | Y8: 1 | Z8: 2 | AA8: 3 | AB8: 4 | AC8: 5 | AD8: 6 | AE8: 7 | AF8: 8 | AG8: 9 | AH8: 10 | AI8: 11 | AJ8: 12 | AK8: 13 | AL8: 14 | AM8: 15 | AN8: 16 | AO8: 17 | AP8: 18 | AQ8: 19 | AR8: 20 | AS8: 21 | AT8: 22 | AU8: 23 | AV8: 24 | AW8: 25 | AX8: 26 | AY8: 27 | AZ8: 28 | BA8: 29 | BB8: 30
B9: Quantity | C9: of Events | D9: of Phase | E9: Per Phase | F9: Repl. | G9: Life | H9: Phase | J9: Item | K9: Quantity | L9: Quantity | M9: Units | N9: Reserve Component Inventory | O9: Event | P9: Useful | Q9: Remaining | R9: ="(" & Current_Fiscal_Year & ")" -> (2026) | S9: Ownership | T9: ="(" & Current_Fiscal_Year & ")" -> (2026) | U9: ="(" & Current_Fiscal_Year & ")" -> (2026) | V9: (Inflated) | W9: Expenditures | X9: ='Property Info'!B10 -> 2026 | Y9: =X9+1 -> 2027 | Z9: =Y9+1 -> 2028 | AA9: =Z9+1 -> 2029 | AB9: =AA9+1 -> 2030 | AC9: =AB9+1 -> 2031 | AD9: =AC9+1 -> 2032 | AE9: =AD9+1 -> 2033 | AF9: =AE9+1 -> 2034 | ... BB9: =BA9+1 -> 2056
B10: - | C10: - | D10: - | E10: - | F10: - | G10: - | J10: - | L10: - | M10: - | N10: - | O10: - | P10: - | Q10: - | R10: - | S10: - | T10: - | U10: - | V10: - | W10: - | X10: - | Y10: - | Z10: - | AA10: - | AB10: - | AC10: - | AD10: - | AE10: - | AF10: - | AG10: - | AH10: - | AI10: - | AJ10: - | AK10: - | AL10: - | AM10: - | AN10: - | AO10: - | AP10: - | AQ10: - | AR10: - | AS10: - | AT10: - | AU10: - | AV10: - | AW10: - | AX10: - | AY10: - | AZ10: - | BA10: - | BB10: -
A11: =IF(OFFSET($B11,IF(AND($K11=0,NOT(ISBLANK($K11))),-4,-3),-1)=0,1,0) -> 1 | N11: Property Site Elements
A12: =IF(OFFSET($B12,IF(AND($K12=0,NOT(ISBLANK($K12))),-4,-3),-1)=0,1,0) -> 1 | B12: 1 | C12: 1 | D12: =(($E12-1)*$C12)+1 -> 1 | E12: 1 | F12: 2031 | G12: 5 | H12: 0.01 | J12: 4.02 | K12: 4200 | L12: =IF(M12="Allowance",1,ROUND(K12*B12/E12/H12,0)*H12) -> 4200 | M12: Square Yards | N12: Asphalt Pavement, Streets, Crack Repairs, Patch and Seal Coat | O12: =IF($F12>$BB$9,$F12,Current_Fiscal_Year+MATCH(TRUE,INDEX($X12:$BB12<>"",0),0)-1) -> 2031 | P12: 3 to 5 | Q12: =$O12-Current_Fiscal_Year&IF($B12<1," to "&Study_Length&"+",IF( $E12>1," to "&IF($O12-Current_Fiscal_Year+$D12-1>Study_Length,Study_Length&"+",$O12-Current_Fiscal_Year+$D12-1),"")) -> 5 | R12: 3 | S12: 1 | T12: =$L12*$R12*$S12 -> 12600 | U12: =$K12*$R12*$S12 -> 12600 | V12: =SUM(OFFSET($X12,,,1,Study_Length+1)) -> 115780.3 | W12: =$V12/Total_Study_Expenditures -> 0.14431038 | X12: =IFERROR(IF(OR(X$8 = ($F12 - Current_Fiscal_Year),AND(MOD($F12-X$9,$G12)=0,X$9>$F12)),IF(secondaryInflationYear- Current_Fiscal_Year >=X$8,ROUND($L12* $R12*$S12*((1 + X$7)^X$8),1),ROUND($L12* $R12*$S12*(((1+secondaryInflation)^(secondaryInflationYear-Current_Fiscal_Year)) * ((1+X$7)^(X$8-(secondaryInflationYear - Current_Fiscal_Year)))),1)),IF(AND($D12<>1,X$8 > ($F12 - Current_Fiscal_Year),(X$8 - (($F12 - Current_Fiscal_Year)+$G12*INT(((X$8 - ($F12 - Current_Fiscal_Year)) / $G12))))/((($D12 - $E12)/($E12-1))+1) = INT((X$8 - (($F12 - Current_Fiscal_Year)+$G12*INT(((X$8 - ($F12 - Current_Fiscal_Year)) / $G12))))/((($D12 - $E12)/($E12-1))+1)), (X$8 - (($F12 - Current_Fiscal_Year)+$G12*INT(((X$8 - ($F12 - Current_Fiscal_Year)) / $G12)))) <$D12),IF(secondaryInflationYear- Current_Fiscal_Year >=X$8,ROUND($L12* $R12*$S12*((1 + X$7)^X$8),1),ROUND($L12* $R12*$S12*(((1+secondaryInflation)^(secondaryInflationYear-Current_Fiscal_Year)) * ((1+X$7)^(X$8-(secondaryInflationYear - Current_Fiscal_Year)))),1)),"")),"") | Y12: =IFERROR(IF(OR(Y$8 = ($F12 - Current_Fiscal_Year),AND(MOD($F12-Y$9,$G12)=0,Y$9>$F12)),IF(secondaryInflationYear- Current_Fiscal_Year >=Y$8,ROUND($L12* $R12*$S12*((1 + Y$7)^Y$8),1),ROUND($L12* $R12*$S12*(((1+secondaryInflation)^(secondaryInflationYear-Current_Fiscal_Year)) * ((1+Y$7)^(Y$8-(secondaryInflationYear - Current_Fiscal_Year)))),1)),IF(AND($D12<>1,Y$8 > ($F12 - Current_Fiscal_Year),(Y$8 - (($F12 - Current_Fiscal_Year)+$G12*INT(((Y$8 - ($F12 - Current_Fiscal_Year)) / $G12))))/((($D12 - $E12)/($E12-1))+1) = INT((Y$8 - (($F12 - Current_Fiscal_Year)+$G12*INT(((Y$8 - ($F12 - Current_Fiscal_Year)) / $G12))))/((($D12 - $E12)/($E12-1))+1)), (Y$8 - (($F12 - Current_Fiscal_Year)+$G12*INT(((Y$8 - ($F12 - Current_Fiscal_Year)) / $G12)))) <$D12),IF(secondaryInflationYear- Current_Fiscal_Year >=Y$8,ROUND($L12* $R12*$S12*((1 + Y$7)^Y$8),1),ROUND($L12* $R12*$S12*(((1+secondaryInflation)^(secondaryInflationYear-Current_Fiscal_Year)) * ((1+Y$7)^(Y$8-(secondaryInflationYear - Current_Fiscal_Year)))),1)),"")),"") | Z12: =IFERROR(IF(OR(Z$8 = ($F12 - Current_Fiscal_Year),AND(MOD($F12-Z$9,$G12)=0,Z$9>$F12)),IF(secondaryInflationYear- Current_Fiscal_Year >=Z$8,ROUND($L12* $R12*$S12*((1 + Z$7)^Z$8),1),ROUND($L12* $R12*$S12*(((1+secondaryInflation)^(secondaryInflationYear-Current_Fiscal_Year)) * ((1+Z$7)^(Z$8-(secondaryInflationYear - Current_Fiscal_Year)))),1)),IF(AND($D12<>1,Z$8 > ($F12 - Current_Fiscal_Year),(Z$8 - (($F12 - Current_Fiscal_Year)+$G12*INT(((Z$8 - ($F12 - Current_Fiscal_Year)) / $G12))))/((($D12 - $E12)/($E12-1))+1) = INT((Z$8 - (($F12 - Current_Fiscal_Year)+$G12*INT(((Z$8 - ($F12 - Current_Fiscal_Year)) / $G12))))/((($D12 - $E12)/($E12-1))+1)), (Z$8 - (($F12 - Current_Fiscal_Year)+$G12*INT(((Z$8 - ($F12 - Current_Fiscal_Year)) / $G12)))) <$D12),IF(secondaryInflationYear- Current_Fiscal_Year >=Z$8,ROUND($L12* $R12*$S12*((1 + Z$7)^Z$8),1),ROUND($L12* $R12*$S12*(((1+secondaryInflation)^(secondaryInflationYear-Current_Fiscal_Year)) * ((1+Z$7)^(Z$8-(secondaryInflationYear - Current_Fiscal_Year)))),1)),"")),"") | AA12: =IFERROR(IF(OR(AA$8 = ($F12 - Current_Fiscal_Year),AND(MOD($F12-AA$9,$G12)=0,AA$9>$F12)),IF(secondaryInflationYear- Current_Fiscal_Year >=AA$8,ROUND($L12* $R12*$S12*((1 + AA$7)^AA$8),1),ROUND($L12* $R12*$S12*(((1+secondaryInflation)^(secondaryInflationYear-Current_Fiscal_Year)) * ((1+AA$7)^(AA$8-(secondaryInflationYear - Current_Fiscal_Year)))),1)),IF(AND($D12<>1,AA$8 > ($F12 - Current_Fiscal_Year),(AA$8 - (($F12 - Current_Fiscal_Year)+$G12*INT(((AA$8 - ($F12 - Current_Fiscal_Year)) / $G12))))/((($D12 - $E12)/($E12-1))+1) = INT((AA$8 - (($F12 - Current_Fiscal_Year)+$G12*INT(((AA$8 - ($F12 - Current_Fiscal_Year)) / $G12))))/((($D12 - $E12)/($E12-1))+1)), (AA$8 - (($F12 - Current_Fiscal_Year)+$G12*INT(((AA$8 - ($F12 - Current_Fiscal_Year)) / $G12)))) <$D12),IF(secondaryInflationYear- Current_Fiscal_Year >=AA$8,ROUND($L12* $R12*$S12*((1 + AA$7)^AA$8),1),ROUND($L12* $R12*$S12*(((1+secondaryInflation)^(secondaryInflationYear-Current_Fiscal_Year)) * ((1+AA$7)^(AA$8-(secondaryInflationYear - Current_Fiscal_Year)))),1)),"")),"") | AB12: =IFERROR(IF(OR(AB$8 = ($F12 - Current_Fiscal_Year),AND(MOD($F12-AB$9,$G12)=0,AB$9>$F12)),IF(secondaryInflationYear- Current_Fiscal_Year >=AB$8,ROUND($L12* $R12*$S12*((1 + AB$7)^AB$8),1),ROUND($L12* $R12*$S12*(((1+secondaryInflation)^(secondaryInflationYear-Current_Fiscal_Year)) * ((1+AB$7)^(AB$8-(secondaryInflationYear - Current_Fiscal_Year)))),1)),IF(AND($D12<>1,AB$8 > ($F12 - Current_Fiscal_Year),(AB$8 - (($F12 - Current_Fiscal_Year)+$G12*INT(((AB$8 - ($F12 - Current_Fiscal_Year)) / $G12))))/((($D12 - $E12)/($E12-1))+1) = INT((AB$8 - (($F12 - Current_Fiscal_Year)+$G12*INT(((AB$8 - ($F12 - Current_Fiscal_Year)) / $G12))))/((($D12 - $E12)/($E12-1))+1)), (AB$8 - (($F12 - Current_Fiscal_Year)+$G12*INT(((AB$8 - ($F12 - Current_Fiscal_Year)) / $G12)))) <$D12),IF(secondaryInflationYear- Current_Fiscal_Year >=AB$8,ROUND($L12* $R12*$S12*((1 + AB$7)^AB$8),1),ROUND($L12* $R12*$S12*(((1+secondaryInflation)^(secondaryInflationYear-Current_Fiscal_Year)) * ((1+AB$7)^(AB$8-(secondaryInflationYear - Current_Fiscal_Year)))),1)),"")),"") | AC12: =IFERROR(IF(OR(AC$8 = ($F12 - Current_Fiscal_Year),AND(MOD($F12-AC$9,$G12)=0,AC$9>$F12)),IF(secondaryInflationYear- Current_Fiscal_Year >=AC$8,ROUND($L12* $R12*$S12*((1 + AC$7)^AC$8),1),ROUND($L12* $R12*$S12*(((1+secondaryInflation)^(secondaryInflationYear-Current_Fiscal_Year)) * ((1+AC$7)^(AC$8-(secondaryInflationYear - Current_Fiscal_Year)))),1)),IF(AND($D12<>1,AC$8 > ($F12 - Current_Fiscal_Year),(AC$8 - (($F12 - Current_Fiscal_Year)+$G12*INT(((AC$8 - ($F12 - Current_Fiscal_Year)) / $G12))))/((($D12 - $E12)/($E12-1))+1) = INT((AC$8 - (($F12 - Current_Fiscal_Year)+$G12*INT(((AC$8 - ($F12 - Current_Fiscal_Year)) / $G12))))/((($D12 - $E12)/($E12-1))+1)), (AC$8 - (($F12 - Current_Fiscal_Year)+$G12*INT(((AC$8 - ($F12 - Current_Fiscal_Year)) / $G12)))) <$D12),IF(secondaryInflationYear- Current_Fiscal_Year >=AC$8,ROUND($L12* $R12*$S12*((1 + AC$7)^AC$8),1),ROUND($L12* $R12*$S12*(((1+secondaryInflation)^(secondaryInflationYear-Current_Fiscal_Year)) * ((1+AC$7)^(AC$8-(secondaryInflationYear - Current_Fiscal_Year)))),1)),"")),"") -> 14749.2 | AD12: =IFERROR(IF(OR(AD$8 = ($F12 - Current_Fiscal_Year),AND(MOD($F12-AD$9,$G12)=0,AD$9>$F12)),IF(secondaryInflationYear- Current_Fiscal_Year >=AD$8,ROUND($L12* $R12*$S12*((1 + AD$7)^AD$8),1),ROUND($L12* $R12*$S12*(((1+secondaryInflation)^(secondaryInflationYear-Current_Fiscal_Year)) * ((1+AD$7)^(AD$8-(secondaryInflationYear - Current_Fiscal_Year)))),1)),IF(AND($D12<>1,AD$8 > ($F12 - Current_Fiscal_Year),(AD$8 - (($F12 - Current_Fiscal_Year)+$G12*INT(((AD$8 - ($F12 - Current_Fiscal_Year)) / $G12))))/((($D12 - $E12)/($E12-1))+1) = INT((AD$8 - (($F12 - Current_Fiscal_Year)+$G12*INT(((AD$8 - ($F12 - Current_Fiscal_Year)) / $G12))))/((($D12 - $E12)/($E12-1))+1)), (AD$8 - (($F12 - Current_Fiscal_Year)+$G12*INT(((AD$8 - ($F12 - Current_Fiscal_Year)) / $G12)))) <$D12),IF(secondaryInflationYear- Current_Fiscal_Year >=AD$8,ROUND($L12* $R12*$S12*((1 + AD$7)^AD$8),1),ROUND($L12* $R12*$S12*(((1+secondaryInflation)^(secondaryInflationYear-Current_Fiscal_Year)) * ((1+AD$7)^(AD$8-(secondaryInflationYear - Current_Fiscal_Year)))),1)),"")),"") | AE12: =IFERROR(IF(OR(AE$8 = ($F12 - Current_Fiscal_Year),AND(MOD($F12-AE$9,$G12)=0,AE$9>$F12)),IF(secondaryInflationYear- Current_Fiscal_Year >=AE$8,ROUND($L12* $R12*$S12*((1 + AE$7)^AE$8),1),ROUND($L12* $R12*$S12*(((1+secondaryInflation)^(secondaryInflationYear-Current_Fiscal_Year)) * ((1+AE$7)^(AE$8-(secondaryInflationYear - Current_Fiscal_Year)))),1)),IF(AND($D12<>1,AE$8 > ($F12 - Current_Fiscal_Year),(AE$8 - (($F12 - Current_Fiscal_Year)+$G12*INT(((AE$8 - ($F12 - Current_Fiscal_Year)) / $G12))))/((($D12 - $E12)/($E12-1))+1) = INT((AE$8 - (($F12 - Current_Fiscal_Year)+$G12*INT(((AE$8 - ($F12 - Current_Fiscal_Year)) / $G12))))/((($D12 - $E12)/($E12-1))+1)), (AE$8 - (($F12 - Current_Fiscal_Year)+$G12*INT(((AE$8 - ($F12 - Current_Fiscal_Year)) / $G12)))) <$D12),IF(secondaryInflationYear- Current_Fiscal_Year >=AE$8,ROUND($L12* $R12*$S12*((1 + AE$7)^AE$8),1),ROUND($L12* $R12*$S12*(((1+secondaryInflation)^(secondaryInflationYear-Current_Fiscal_Year)) * ((1+AE$7)^(AE$8-(secondaryInflationYear - Current_Fiscal_Year)))),1)),"")),"") | ... AL12: =IFERROR(IF(OR(AL$8 = ($F12 - Current_Fiscal_Year),AND(MOD($F12-AL$9,$G12)=0,AL$9>$F12)),IF(secondaryInflationYear- Current_Fiscal_Year >=AL$8,ROUND($L12* $R12*$S12*((1 + AL$7)^AL$8),1),ROUND($L12* $R12*$S12*(((1+secondaryInflation)^(secondaryInflationYear-Current_Fiscal_Year)) * ((1+AL$7)^(AL$8-(secondaryInflationYear - Current_Fiscal_Year)))),1)),IF(AND($D12<>1,AL$8 > ($F12 - Current_Fiscal_Year),(AL$8 - (($F12 - Current_Fiscal_Year)+$G12*INT(((AL$8 - ($F12 - Current_Fiscal_Year)) / $G12))))/((($D12 - $E12)/($E12-1))+1) = INT((AL$8 - (($F12 - Current_Fiscal_Year)+$G12*INT(((AL$8 - ($F12 - Current_Fiscal_Year)) / $G12))))/((($D12 - $E12)/($E12-1))+1)), (AL$8 - (($F12 - Current_Fiscal_Year)+$G12*INT(((AL$8 - ($F12 - Current_Fiscal_Year)) / $G12)))) <$D12),IF(secondaryInflationYear- Current_Fiscal_Year >=AL$8,ROUND($L12* $R12*$S12*((1 + AL$7)^AL$8),1),ROUND($L12* $R12*$S12*(((1+secondaryInflation)^(secondaryInflationYear-Current_Fiscal_Year)) * ((1+AL$7)^(AL$8-(secondaryInflationYear - Current_Fiscal_Year)))),1)),"")),"") | AN12: =IFERROR(IF(OR(AN$8 = ($F12 - Current_Fiscal_Year),AND(MOD($F12-AN$9,$G12)=0,AN$9>$F12)),IF(secondaryInflationYear- Current_Fiscal_Year >=AN$8,ROUND($L12* $R12*$S12*((1 + AN$7)^AN$8),1),ROUND($L12* $R12*$S12*(((1+secondaryInflation)^(secondaryInflationYear-Current_Fiscal_Year)) * ((1+AN$7)^(AN$8-(secondaryInflationYear - Current_Fiscal_Year)))),1)),IF(AND($D12<>1,AN$8 > ($F12 - Current_Fiscal_Year),(AN$8 - (($F12 - Current_Fiscal_Year)+$G12*INT(((AN$8 - ($F12 - Current_Fiscal_Year)) / $G12))))/((($D12 - $E12)/($E12-1))+1) = INT((AN$8 - (($F12 - Current_Fiscal_Year)+$G12*INT(((AN$8 - ($F12 - Current_Fiscal_Year)) / $G12))))/((($D12 - $E12)/($E12-1))+1)), (AN$8 - (($F12 - Current_Fiscal_Year)+$G12*INT(((AN$8 - ($F12 - Current_Fiscal_Year)) / $G12)))) <$D12),IF(secondaryInflationYear- Current_Fiscal_Year >=AN$8,ROUND($L12* $R12*$S12*((1 + AN$7)^AN$8),1),ROUND($L12* $R12*$S12*(((1+secondaryInflation)^(secondaryInflationYear-Current_Fiscal_Year)) * ((1+AN$7)^(AN$8-(secondaryInflationYear - Current_Fiscal_Year)))),1)),"")),"") | AO12: =IFERROR(IF(OR(AO$8 = ($F12 - Current_Fiscal_Year),AND(MOD($F12-AO$9,$G12)=0,AO$9>$F12)),IF(secondaryInflationYear- Current_Fiscal_Year >=AO$8,ROUND($L12* $R12*$S12*((1 + AO$7)^AO$8),1),ROUND($L12* $R12*$S12*(((1+secondaryInflation)^(secondaryInflationYear-Current_Fiscal_Year)) * ((1+AO$7)^(AO$8-(secondaryInflationYear - Current_Fiscal_Year)))),1)),IF(AND($D12<>1,AO$8 > ($F12 - Current_Fiscal_Year),(AO$8 - (($F12 - Current_Fiscal_Year)+$G12*INT(((AO$8 - ($F12 - Current_Fiscal_Year)) / $G12))))/((($D12 - $E12)/($E12-1))+1) = INT((AO$8 - (($F12 - Current_Fiscal_Year)+$G12*INT(((AO$8 - ($F12 - Current_Fiscal_Year)) / $G12))))/((($D12 - $E12)/($E12-1))+1)), (AO$8 - (($F12 - Current_Fiscal_Year)+$G12*INT(((AO$8 - ($F12 - Current_Fiscal_Year)) / $G12)))) <$D12),IF(secondaryInflationYear- Current_Fiscal_Year >=AO$8,ROUND($L12* $R12*$S12*((1 + AO$7)^AO$8),1),ROUND($L12* $R12*$S12*(((1+secondaryInflation)^(secondaryInflationYear-Current_Fiscal_Year)) * ((1+AO$7)^(AO$8-(secondaryInflationYear - Current_Fiscal_Year)))),1)),"")),"") | AP12: =IFERROR(IF(OR(AP$8 = ($F12 - Current_Fiscal_Year),AND(MOD($F12-AP$9,$G12)=0,AP$9>$F12)),IF(secondaryInflationYear- Current_Fiscal_Year >=AP$8,ROUND($L12* $R12*$S12*((1 + AP$7)^AP$8),1),ROUND($L12* $R12*$S12*(((1+secondaryInflation)^(secondaryInflationYear-Current_Fiscal_Year)) * ((1+AP$7)^(AP$8-(secondaryInflationYear - Current_Fiscal_Year)))),1)),IF(AND($D12<>1,AP$8 > ($F12 - Current_Fiscal_Year),(AP$8 - (($F12 - Current_Fiscal_Year)+$G12*INT(((AP$8 - ($F12 - Current_Fiscal_Year)) / $G12))))/((($D12 - $E12)/($E12-1))+1) = INT((AP$8 - (($F12 - Current_Fiscal_Year)+$G12*INT(((AP$8 - ($F12 - Current_Fiscal_Year)) / $G12))))/((($D12 - $E12)/($E12-1))+1)), (AP$8 - (($F12 - Current_Fiscal_Year)+$G12*INT(((AP$8 - ($F12 - Current_Fiscal_Year)) / $G12)))) <$D12),IF(secondaryInflationYear- Current_Fiscal_Year >=AP$8,ROUND($L12* $R12*$S12*((1 + AP$7)^AP$8),1),ROUND($L12* $R12*$S12*(((1+secondaryInflation)^(secondaryInflationYear-Current_Fiscal_Year)) * ((1+AP$7)^(AP$8-(secondaryInflationYear - Current_Fiscal_Year)))),1)),"")),"") | AQ12: =IFERROR(IF(OR(AQ$8 = ($F12 - Current_Fiscal_Year),AND(MOD($F12-AQ$9,$G12)=0,AQ$9>$F12)),IF(secondaryInflationYear- Current_Fiscal_Year >=AQ$8,ROUND($L12* $R12*$S12*((1 + AQ$7)^AQ$8),1),ROUND($L12* $R12*$S12*(((1+secondaryInflation)^(secondaryInflationYear-Current_Fiscal_Year)) * ((1+AQ$7)^(AQ$8-(secondaryInflationYear - Current_Fiscal_Year)))),1)),IF(AND($D12<>1,AQ$8 > ($F12 - Current_Fiscal_Year),(AQ$8 - (($F12 - Current_Fiscal_Year)+$G12*INT(((AQ$8 - ($F12 - Current_Fiscal_Year)) / $G12))))/((($D12 - $E12)/($E12-1))+1) = INT((AQ$8 - (($F12 - Current_Fiscal_Year)+$G12*INT(((AQ$8 - ($F12 - Current_Fiscal_Year)) / $G12))))/((($D12 - $E12)/($E12-1))+1)), (AQ$8 - (($F12 - Current_Fiscal_Year)+$G12*INT(((AQ$8 - ($F12 - Current_Fiscal_Year)) / $G12)))) <$D12),IF(secondaryInflationYear- Current_Fiscal_Year >=AQ$8,ROUND($L12* $R12*$S12*((1 + AQ$7)^AQ$8),1),ROUND($L12* $R12*$S12*(((1+secondaryInflation)^(secondaryInflationYear-Current_Fiscal_Year)) * ((1+AQ$7)^(AQ$8-(secondaryInflationYear - Current_Fiscal_Year)))),1)),"")),"") | AR12: =IFERROR(IF(OR(AR$8 = ($F12 - Current_Fiscal_Year),AND(MOD($F12-AR$9,$G12)=0,AR$9>$F12)),IF(secondaryInflationYear- Current_Fiscal_Year >=AR$8,ROUND($L12* $R12*$S12*((1 + AR$7)^AR$8),1),ROUND($L12* $R12*$S12*(((1+secondaryInflation)^(secondaryInflationYear-Current_Fiscal_Year)) * ((1+AR$7)^(AR$8-(secondaryInflationYear - Current_Fiscal_Year)))),1)),IF(AND($D12<>1,AR$8 > ($F12 - Current_Fiscal_Year),(AR$8 - (($F12 - Current_Fiscal_Year)+$G12*INT(((AR$8 - ($F12 - Current_Fiscal_Year)) / $G12))))/((($D12 - $E12)/($E12-1))+1) = INT((AR$8 - (($F12 - Current_Fiscal_Year)+$G12*INT(((AR$8 - ($F12 - Current_Fiscal_Year)) / $G12))))/((($D12 - $E12)/($E12-1))+1)), (AR$8 - (($F12 - Current_Fiscal_Year)+$G12*INT(((AR$8 - ($F12 - Current_Fiscal_Year)) / $G12)))) <$D12),IF(secondaryInflationYear- Current_Fiscal_Year >=AR$8,ROUND($L12* $R12*$S12*((1 + AR$7)^AR$8),1),ROUND($L12* $R12*$S12*(((1+secondaryInflation)^(secondaryInflationYear-Current_Fiscal_Year)) * ((1+AR$7)^(AR$8-(secondaryInflationYear - Current_Fiscal_Year)))),1)),"")),"") -> 23657.3 | AS12: =IFERROR(IF(OR(AS$8 = ($F12 - Current_Fiscal_Year),AND(MOD($F12-AS$9,$G12)=0,AS$9>$F12)),IF(secondaryInflationYear- Current_Fiscal_Year >=AS$8,ROUND($L12* $R12*$S12*((1 + AS$7)^AS$8),1),ROUND($L12* $R12*$S12*(((1+secondaryInflation)^(secondaryInflationYear-Current_Fiscal_Year)) * ((1+AS$7)^(AS$8-(secondaryInflationYear - Current_Fiscal_Year)))),1)),IF(AND($D12<>1,AS$8 > ($F12 - Current_Fiscal_Year),(AS$8 - (($F12 - Current_Fiscal_Year)+$G12*INT(((AS$8 - ($F12 - Current_Fiscal_Year)) / $G12))))/((($D12 - $E12)/($E12-1))+1) = INT((AS$8 - (($F12 - Current_Fiscal_Year)+$G12*INT(((AS$8 - ($F12 - Current_Fiscal_Year)) / $G12))))/((($D12 - $E12)/($E12-1))+1)), (AS$8 - (($F12 - Current_Fiscal_Year)+$G12*INT(((AS$8 - ($F12 - Current_Fiscal_Year)) / $G12)))) <$D12),IF(secondaryInflationYear- Current_Fiscal_Year >=AS$8,ROUND($L12* $R12*$S12*((1 + AS$7)^AS$8),1),ROUND($L12* $R12*$S12*(((1+secondaryInflation)^(secondaryInflationYear-Current_Fiscal_Year)) * ((1+AS$7)^(AS$8-(secondaryInflationYear - Current_Fiscal_Year)))),1)),"")),"") | AT12: =IFERROR(IF(OR(AT$8 = ($F12 - Current_Fiscal_Year),AND(MOD($F12-AT$9,$G12)=0,AT$9>$F12)),IF(secondaryInflationYear- Current_Fiscal_Year >=AT$8,ROUND($L12* $R12*$S12*((1 + AT$7)^AT$8),1),ROUND($L12* $R12*$S12*(((1+secondaryInflation)^(secondaryInflationYear-Current_Fiscal_Year)) * ((1+AT$7)^(AT$8-(secondaryInflationYear - Current_Fiscal_Year)))),1)),IF(AND($D12<>1,AT$8 > ($F12 - Current_Fiscal_Year),(AT$8 - (($F12 - Current_Fiscal_Year)+$G12*INT(((AT$8 - ($F12 - Current_Fiscal_Year)) / $G12))))/((($D12 - $E12)/($E12-1))+1) = INT((AT$8 - (($F12 - Current_Fiscal_Year)+$G12*INT(((AT$8 - ($F12 - Current_Fiscal_Year)) / $G12))))/((($D12 - $E12)/($E12-1))+1)), (AT$8 - (($F12 - Current_Fiscal_Year)+$G12*INT(((AT$8 - ($F12 - Current_Fiscal_Year)) / $G12)))) <$D12),IF(secondaryInflationYear- Current_Fiscal_Year >=AT$8,ROUND($L12* $R12*$S12*((1 + AT$7)^AT$8),1),ROUND($L12* $R12*$S12*(((1+secondaryInflation)^(secondaryInflationYear-Current_Fiscal_Year)) * ((1+AT$7)^(AT$8-(secondaryInflationYear - Current_Fiscal_Year)))),1)),"")),"") | AU12: =IFERROR(IF(OR(AU$8 = ($F12 - Current_Fiscal_Year),AND(MOD($F12-AU$9,$G12)=0,AU$9>$F12)),IF(secondaryInflationYear- Current_Fiscal_Year >=AU$8,ROUND($L12* $R12*$S12*((1 + AU$7)^AU$8),1),ROUND($L12* $R12*$S12*(((1+secondaryInflation)^(secondaryInflationYear-Current_Fiscal_Year)) * ((1+AU$7)^(AU$8-(secondaryInflationYear - Current_Fiscal_Year)))),1)),IF(AND($D12<>1,AU$8 > ($F12 - Current_Fiscal_Year),(AU$8 - (($F12 - Current_Fiscal_Year)+$G12*INT(((AU$8 - ($F12 - Current_Fiscal_Year)) / $G12))))/((($D12 - $E12)/($E12-1))+1) = INT((AU$8 - (($F12 - Current_Fiscal_Year)+$G12*INT(((AU$8 - ($F12 - Current_Fiscal_Year)) / $G12))))/((($D12 - $E12)/($E12-1))+1)), (AU$8 - (($F12 - Current_Fiscal_Year)+$G12*INT(((AU$8 - ($F12 - Current_Fiscal_Year)) / $G12)))) <$D12),IF(secondaryInflationYear- Current_Fiscal_Year >=AU$8,ROUND($L12* $R12*$S12*((1 + AU$7)^AU$8),1),ROUND($L12* $R12*$S12*(((1+secondaryInflation)^(secondaryInflationYear-Current_Fiscal_Year)) * ((1+AU$7)^(AU$8-(secondaryInflationYear - Current_Fiscal_Year)))),1)),"")),"") | ... BB12: =IFERROR(IF(OR(BB$8 = ($F12 - Current_Fiscal_Year),AND(MOD($F12-BB$9,$G12)=0,BB$9>$F12)),IF(secondaryInflationYear- Current_Fiscal_Year >=BB$8,ROUND($L12* $R12*$S12*((1 + BB$7)^BB$8),1),ROUND($L12* $R12*$S12*(((1+secondaryInflation)^(secondaryInflationYear-Current_Fiscal_Year)) * ((1+BB$7)^(BB$8-(secondaryInflationYear - Current_Fiscal_Year)))),1)),IF(AND($D12<>1,BB$8 > ($F12 - Current_Fiscal_Year),(BB$8 - (($F12 - Current_Fiscal_Year)+$G12*INT(((BB$8 - ($F12 - Current_Fiscal_Year)) / $G12))))/((($D12 - $E12)/($E12-1))+1) = INT((BB$8 - (($F12 - Current_Fiscal_Year)+$G12*INT(((BB$8 - ($F12 - Current_Fiscal_Year)) / $G12))))/((($D12 - $E12)/($E12-1))+1)), (BB$8 - (($F12 - Current_Fiscal_Year)+$G12*INT(((BB$8 - ($F12 - Current_Fiscal_Year)) / $G12)))) <$D12),IF(secondaryInflationYear- Current_Fiscal_Year >=BB$8,ROUND($L12* $R12*$S12*((1 + BB$7)^BB$8),1),ROUND($L12* $R12*$S12*(((1+secondaryInflation)^(secondaryInflationYear-Current_Fiscal_Year)) * ((1+BB$7)^(BB$8-(secondaryInflationYear - Current_Fiscal_Year)))),1)),"")),"") -> 32416.2
A13: =IF(OFFSET($B13,IF(AND($K13=0,NOT(ISBLANK($K13))),-4,-3),-1)=0,1,0) -> 1 | B13: 1 | C13: 1 | D13: =(($E13-1)*$C13)+1 -> 1 | E13: 1 | F13: 2041 | G13: 25 | H13: 0.01 | J13: 4.04 | K13: 4200 | L13: =IF(M13="Allowance",1,ROUND(K13*B13/E13/H13,0)*H13) -> 4200 | M13: Square Yards | N13: Asphalt Pavement, Streets, Mill and Overlay | O13: =IF($F13>$BB$9,$F13,Current_Fiscal_Year+MATCH(TRUE,INDEX($X13:$BB13<>"",0),0)-1) -> 2041 | P13: 15 to 25 | Q13: =$O13-Current_Fiscal_Year&IF($B13<1," to "&Study_Length&"+",IF( $E13>1," to "&IF($O13-Current_Fiscal_Year+$D13-1>Study_Length,Study_Length&"+",$O13-Current_Fiscal_Year+$D13-1),"")) -> 15 | R13: 20 | S13: 1 | T13: =$L13*$R13*$S13 -> 84000 | U13: =$K13*$R13*$S13 -> 84000 | V13: =SUM(OFFSET($X13,,,1,Study_Length+1)) -> 134733.2 | W13: =$V13/Total_Study_Expenditures -> 0.16793358 | X13: =IFERROR(IF(OR(X$8 = ($F13 - Current_Fiscal_Year),AND(MOD($F13-X$9,$G13)=0,X$9>$F13)),IF(secondaryInflationYear- Current_Fiscal_Year >=X$8,ROUND($L13* $R13*$S13*((1 + X$7)^X$8),1),ROUND($L13* $R13*$S13*(((1+secondaryInflation)^(secondaryInflationYear-Current_Fiscal_Year)) * ((1+X$7)^(X$8-(secondaryInflationYear - Current_Fiscal_Year)))),1)),IF(AND($D13<>1,X$8 > ($F13 - Current_Fiscal_Year),(X$8 - (($F13 - Current_Fiscal_Year)+$G13*INT(((X$8 - ($F13 - Current_Fiscal_Year)) / $G13))))/((($D13 - $E13)/($E13-1))+1) = INT((X$8 - (($F13 - Current_Fiscal_Year)+$G13*INT(((X$8 - ($F13 - Current_Fiscal_Year)) / $G13))))/((($D13 - $E13)/($E13-1))+1)), (X$8 - (($F13 - Current_Fiscal_Year)+$G13*INT(((X$8 - ($F13 - Current_Fiscal_Year)) / $G13)))) <$D13),IF(secondaryInflationYear- Current_Fiscal_Year >=X$8,ROUND($L13* $R13*$S13*((1 + X$7)^X$8),1),ROUND($L13* $R13*$S13*(((1+secondaryInflation)^(secondaryInflationYear-Current_Fiscal_Year)) * ((1+X$7)^(X$8-(secondaryInflationYear - Current_Fiscal_Year)))),1)),"")),"") | Y13: =IFERROR(IF(OR(Y$8 = ($F13 - Current_Fiscal_Year),AND(MOD($F13-Y$9,$G13)=0,Y$9>$F13)),IF(secondaryInflationYear- Current_Fiscal_Year >=Y$8,ROUND($L13* $R13*$S13*((1 + Y$7)^Y$8),1),ROUND($L13* $R13*$S13*(((1+secondaryInflation)^(secondaryInflationYear-Current_Fiscal_Year)) * ((1+Y$7)^(Y$8-(secondaryInflationYear - Current_Fiscal_Year)))),1)),IF(AND($D13<>1,Y$8 > ($F13 - Current_Fiscal_Year),(Y$8 - (($F13 - Current_Fiscal_Year)+$G13*INT(((Y$8 - ($F13 - Current_Fiscal_Year)) / $G13))))/((($D13 - $E13)/($E13-1))+1) = INT((Y$8 - (($F13 - Current_Fiscal_Year)+$G13*INT(((Y$8 - ($F13 - Current_Fiscal_Year)) / $G13))))/((($D13 - $E13)/($E13-1))+1)), (Y$8 - (($F13 - Current_Fiscal_Year)+$G13*INT(((Y$8 - ($F13 - Current_Fiscal_Year)) / $G13)))) <$D13),IF(secondaryInflationYear- Current_Fiscal_Year >=Y$8,ROUND($L13* $R13*$S13*((1 + Y$7)^Y$8),1),ROUND($L13* $R13*$S13*(((1+secondaryInflation)^(secondaryInflationYear-Current_Fiscal_Year)) * ((1+Y$7)^(Y$8-(secondaryInflationYear - Current_Fiscal_Year)))),1)),"")),"") | Z13: =IFERROR(IF(OR(Z$8 = ($F13 - Current_Fiscal_Year),AND(MOD($F13-Z$9,$G13)=0,Z$9>$F13)),IF(secondaryInflationYear- Current_Fiscal_Year >=Z$8,ROUND($L13* $R13*$S13*((1 + Z$7)^Z$8),1),ROUND($L13* $R13*$S13*(((1+secondaryInflation)^(secondaryInflationYear-Current_Fiscal_Year)) * ((1+Z$7)^(Z$8-(secondaryInflationYear - Current_Fiscal_Year)))),1)),IF(AND($D13<>1,Z$8 > ($F13 - Current_Fiscal_Year),(Z$8 - (($F13 - Current_Fiscal_Year)+$G13*INT(((Z$8 - ($F13 - Current_Fiscal_Year)) / $G13))))/((($D13 - $E13)/($E13-1))+1) = INT((Z$8 - (($F13 - Current_Fiscal_Year)+$G13*INT(((Z$8 - ($F13 - Current_Fiscal_Year)) / $G13))))/((($D13 - $E13)/($E13-1))+1)), (Z$8 - (($F13 - Current_Fiscal_Year)+$G13*INT(((Z$8 - ($F13 - Current_Fiscal_Year)) / $G13)))) <$D13),IF(secondaryInflationYear- Current_Fiscal_Year >=Z$8,ROUND($L13* $R13*$S13*((1 + Z$7)^Z$8),1),ROUND($L13* $R13*$S13*(((1+secondaryInflation)^(secondaryInflationYear-Current_Fiscal_Year)) * ((1+Z$7)^(Z$8-(secondaryInflationYear - Current_Fiscal_Year)))),1)),"")),"") | AA13: =IFERROR(IF(OR(AA$8 = ($F13 - Current_Fiscal_Year),AND(MOD($F13-AA$9,$G13)=0,AA$9>$F13)),IF(secondaryInflationYear- Current_Fiscal_Year >=AA$8,ROUND($L13* $R13*$S13*((1 + AA$7)^AA$8),1),ROUND($L13* $R13*$S13*(((1+secondaryInflation)^(secondaryInflationYear-Current_Fiscal_Year)) * ((1+AA$7)^(AA$8-(secondaryInflationYear - Current_Fiscal_Year)))),1)),IF(AND($D13<>1,AA$8 > ($F13 - Current_Fiscal_Year),(AA$8 - (($F13 - Current_Fiscal_Year)+$G13*INT(((AA$8 - ($F13 - Current_Fiscal_Year)) / $G13))))/((($D13 - $E13)/($E13-1))+1) = INT((AA$8 - (($F13 - Current_Fiscal_Year)+$G13*INT(((AA$8 - ($F13 - Current_Fiscal_Year)) / $G13))))/((($D13 - $E13)/($E13-1))+1)), (AA$8 - (($F13 - Current_Fiscal_Year)+$G13*INT(((AA$8 - ($F13 - Current_Fiscal_Year)) / $G13)))) <$D13),IF(secondaryInflationYear- Current_Fiscal_Year >=AA$8,ROUND($L13* $R13*$S13*((1 + AA$7)^AA$8),1),ROUND($L13* $R13*$S13*(((1+secondaryInflation)^(secondaryInflationYear-Current_Fiscal_Year)) * ((1+AA$7)^(AA$8-(secondaryInflationYear - Current_Fiscal_Year)))),1)),"")),"") | AB13: =IFERROR(IF(OR(AB$8 = ($F13 - Current_Fiscal_Year),AND(MOD($F13-AB$9,$G13)=0,AB$9>$F13)),IF(secondaryInflationYear- Current_Fiscal_Year >=AB$8,ROUND($L13* $R13*$S13*((1 + AB$7)^AB$8),1),ROUND($L13* $R13*$S13*(((1+secondaryInflation)^(secondaryInflationYear-Current_Fiscal_Year)) * ((1+AB$7)^(AB$8-(secondaryInflationYear - Current_Fiscal_Year)))),1)),IF(AND($D13<>1,AB$8 > ($F13 - Current_Fiscal_Year),(AB$8 - (($F13 - Current_Fiscal_Year)+$G13*INT(((AB$8 - ($F13 - Current_Fiscal_Year)) / $G13))))/((($D13 - $E13)/($E13-1))+1) = INT((AB$8 - (($F13 - Current_Fiscal_Year)+$G13*INT(((AB$8 - ($F13 - Current_Fiscal_Year)) / $G13))))/((($D13 - $E13)/($E13-1))+1)), (AB$8 - (($F13 - Current_Fiscal_Year)+$G13*INT(((AB$8 - ($F13 - Current_Fiscal_Year)) / $G13)))) <$D13),IF(secondaryInflationYear- Current_Fiscal_Year >=AB$8,ROUND($L13* $R13*$S13*((1 + AB$7)^AB$8),1),ROUND($L13* $R13*$S13*(((1+secondaryInflation)^(secondaryInflationYear-Current_Fiscal_Year)) * ((1+AB$7)^(AB$8-(secondaryInflationYear - Current_Fiscal_Year)))),1)),"")),"") | AC13: =IFERROR(IF(OR(AC$8 = ($F13 - Current_Fiscal_Year),AND(MOD($F13-AC$9,$G13)=0,AC$9>$F13)),IF(secondaryInflationYear- Current_Fiscal_Year >=AC$8,ROUND($L13* $R13*$S13*((1 + AC$7)^AC$8),1),ROUND($L13* $R13*$S13*(((1+secondaryInflation)^(secondaryInflationYear-Current_Fiscal_Year)) * ((1+AC$7)^(AC$8-(secondaryInflationYear - Current_Fiscal_Year)))),1)),IF(AND($D13<>1,AC$8 > ($F13 - Current_Fiscal_Year),(AC$8 - (($F13 - Current_Fiscal_Year)+$G13*INT(((AC$8 - ($F13 - Current_Fiscal_Year)) / $G13))))/((($D13 - $E13)/($E13-1))+1) = INT((AC$8 - (($F13 - Current_Fiscal_Year)+$G13*INT(((AC$8 - ($F13 - Current_Fiscal_Year)) / $G13))))/((($D13 - $E13)/($E13-1))+1)), (AC$8 - (($F13 - Current_Fiscal_Year)+$G13*INT(((AC$8 - ($F13 - Current_Fiscal_Year)) / $G13)))) <$D13),IF(secondaryInflationYear- Current_Fiscal_Year >=AC$8,ROUND($L13* $R13*$S13*((1 + AC$7)^AC$8),1),ROUND($L13* $R13*$S13*(((1+secondaryInflation)^(secondaryInflationYear-Current_Fiscal_Year)) * ((1+AC$7)^(AC$8-(secondaryInflationYear - Current_Fiscal_Year)))),1)),"")),"") | AD13: =IFERROR(IF(OR(AD$8 = ($F13 - Current_Fiscal_Year),AND(MOD($F13-AD$9,$G13)=0,AD$9>$F13)),IF(secondaryInflationYear- Current_Fiscal_Year >=AD$8,ROUND($L13* $R13*$S13*((1 + AD$7)^AD$8),1),ROUND($L13* $R13*$S13*(((1+secondaryInflation)^(secondaryInflationYear-Current_Fiscal_Year)) * ((1+AD$7)^(AD$8-(secondaryInflationYear - Current_Fiscal_Year)))),1)),IF(AND($D13<>1,AD$8 > ($F13 - Current_Fiscal_Year),(AD$8 - (($F13 - Current_Fiscal_Year)+$G13*INT(((AD$8 - ($F13 - Current_Fiscal_Year)) / $G13))))/((($D13 - $E13)/($E13-1))+1) = INT((AD$8 - (($F13 - Current_Fiscal_Year)+$G13*INT(((AD$8 - ($F13 - Current_Fiscal_Year)) / $G13))))/((($D13 - $E13)/($E13-1))+1)), (AD$8 - (($F13 - Current_Fiscal_Year)+$G13*INT(((AD$8 - ($F13 - Current_Fiscal_Year)) / $G13)))) <$D13),IF(secondaryInflationYear- Current_Fiscal_Year >=AD$8,ROUND($L13* $R13*$S13*((1 + AD$7)^AD$8),1),ROUND($L13* $R13*$S13*(((1+secondaryInflation)^(secondaryInflationYear-Current_Fiscal_Year)) * ((1+AD$7)^(AD$8-(secondaryInflationYear - Current_Fiscal_Year)))),1)),"")),"") | AE13: =IFERROR(IF(OR(AE$8 = ($F13 - Current_Fiscal_Year),AND(MOD($F13-AE$9,$G13)=0,AE$9>$F13)),IF(secondaryInflationYear- Current_Fiscal_Year >=AE$8,ROUND($L13* $R13*$S13*((1 + AE$7)^AE$8),1),ROUND($L13* $R13*$S13*(((1+secondaryInflation)^(secondaryInflationYear-Current_Fiscal_Year)) * ((1+AE$7)^(AE$8-(secondaryInflationYear - Current_Fiscal_Year)))),1)),IF(AND($D13<>1,AE$8 > ($F13 - Current_Fiscal_Year),(AE$8 - (($F13 - Current_Fiscal_Year)+$G13*INT(((AE$8 - ($F13 - Current_Fiscal_Year)) / $G13))))/((($D13 - $E13)/($E13-1))+1) = INT((AE$8 - (($F13 - Current_Fiscal_Year)+$G13*INT(((AE$8 - ($F13 - Current_Fiscal_Year)) / $G13))))/((($D13 - $E13)/($E13-1))+1)), (AE$8 - (($F13 - Current_Fiscal_Year)+$G13*INT(((AE$8 - ($F13 - Current_Fiscal_Year)) / $G13)))) <$D13),IF(secondaryInflationYear- Current_Fiscal_Year >=AE$8,ROUND($L13* $R13*$S13*((1 + AE$7)^AE$8),1),ROUND($L13* $R13*$S13*(((1+secondaryInflation)^(secondaryInflationYear-Current_Fiscal_Year)) * ((1+AE$7)^(AE$8-(secondaryInflationYear - Current_Fiscal_Year)))),1)),"")),"") | ... BB13: =IFERROR(IF(OR(BB$8 = ($F13 - Current_Fiscal_Year),AND(MOD($F13-BB$9,$G13)=0,BB$9>$F13)),IF(secondaryInflationYear- Current_Fiscal_Year >=BB$8,ROUND($L13* $R13*$S13*((1 + BB$7)^BB$8),1),ROUND($L13* $R13*$S13*(((1+secondaryInflation)^(secondaryInflationYear-Current_Fiscal_Year)) * ((1+BB$7)^(BB$8-(secondaryInflationYear - Current_Fiscal_Year)))),1)),IF(AND($D13<>1,BB$8 > ($F13 - Current_Fiscal_Year),(BB$8 - (($F13 - Current_Fiscal_Year)+$G13*INT(((BB$8 - ($F13 - Current_Fiscal_Year)) / $G13))))/((($D13 - $E13)/($E13-1))+1) = INT((BB$8 - (($F13 - Current_Fiscal_Year)+$G13*INT(((BB$8 - ($F13 - Current_Fiscal_Year)) / $G13))))/((($D13 - $E13)/($E13-1))+1)), (BB$8 - (($F13 - Current_Fiscal_Year)+$G13*INT(((BB$8 - ($F13 - Current_Fiscal_Year)) / $G13)))) <$D13),IF(secondaryInflationYear- Current_Fiscal_Year >=BB$8,ROUND($L13* $R13*$S13*((1 + BB$7)^BB$8),1),ROUND($L13* $R13*$S13*(((1+secondaryInflation)^(secondaryInflationYear-Current_Fiscal_Year)) * ((1+BB$7)^(BB$8-(secondaryInflationYear - Current_Fiscal_Year)))),1)),"")),"")
A14: =IF(OFFSET($B14,IF(AND($K14=0,NOT(ISBLANK($K14))),-4,-3),-1)=0,1,0) -> 0 | B14: 0.3 | C14: 1 | D14: =(($E14-1)*$C14)+1 -> 1 | E14: 1 | F14: 2041 | G14: 25 | H14: 0.01 | J14: 4.11 | K14: 3200 | L14: =IF(M14="Allowance",1,ROUND(K14*B14/E14/H14,0)*H14) -> 960 | M14: Linear Feet | N14: Concrete Curbs and Gutters, Partial | O14: =IF($F14>$BB$9,$F14,Current_Fiscal_Year+MATCH(TRUE,INDEX($X14:$BB14<>"",0),0)-1) -> 2041 | P14: to 65 | Q14: =$O14-Current_Fiscal_Year&IF($B14<1," to "&Study_Length&"+",IF( $E14>1," to "&IF($O14-Current_Fiscal_Year+$D14-1>Study_Length,Study_Length&"+",$O14-Current_Fiscal_Year+$D14-1),"")) -> 15 to 30+ | R14: 40 | S14: 1 | T14: =$L14*$R14*$S14 -> 38400 | U14: =$K14*$R14*$S14 -> 128000 | V14: =SUM(OFFSET($X14,,,1,Study_Length+1)) -> 61592.3 | W14: =$V14/Total_Study_Expenditures -> 0.07676961 | X14: =IFERROR(IF(OR(X$8 = ($F14 - Current_Fiscal_Year),AND(MOD($F14-X$9,$G14)=0,X$9>$F14)),IF(secondaryInflationYear- Current_Fiscal_Year >=X$8,ROUND($L14* $R14*$S14*((1 + X$7)^X$8),1),ROUND($L14* $R14*$S14*(((1+secondaryInflation)^(secondaryInflationYear-Current_Fiscal_Year)) * ((1+X$7)^(X$8-(secondaryInflationYear - Current_Fiscal_Year)))),1)),IF(AND($D14<>1,X$8 > ($F14 - Current_Fiscal_Year),(X$8 - (($F14 - Current_Fiscal_Year)+$G14*INT(((X$8 - ($F14 - Current_Fiscal_Year)) / $G14))))/((($D14 - $E14)/($E14-1))+1) = INT((X$8 - (($F14 - Current_Fiscal_Year)+$G14*INT(((X$8 - ($F14 - Current_Fiscal_Year)) / $G14))))/((($D14 - $E14)/($E14-1))+1)), (X$8 - (($F14 - Current_Fiscal_Year)+$G14*INT(((X$8 - ($F14 - Current_Fiscal_Year)) / $G14)))) <$D14),IF(secondaryInflationYear- Current_Fiscal_Year >=X$8,ROUND($L14* $R14*$S14*((1 + X$7)^X$8),1),ROUND($L14* $R14*$S14*(((1+secondaryInflation)^(secondaryInflationYear-Current_Fiscal_Year)) * ((1+X$7)^(X$8-(secondaryInflationYear - Current_Fiscal_Year)))),1)),"")),"") | Y14: =IFERROR(IF(OR(Y$8 = ($F14 - Current_Fiscal_Year),AND(MOD($F14-Y$9,$G14)=0,Y$9>$F14)),IF(secondaryInflationYear- Current_Fiscal_Year >=Y$8,ROUND($L14* $R14*$S14*((1 + Y$7)^Y$8),1),ROUND($L14* $R14*$S14*(((1+secondaryInflation)^(secondaryInflationYear-Current_Fiscal_Year)) * ((1+Y$7)^(Y$8-(secondaryInflationYear - Current_Fiscal_Year)))),1)),IF(AND($D14<>1,Y$8 > ($F14 - Current_Fiscal_Year),(Y$8 - (($F14 - Current_Fiscal_Year)+$G14*INT(((Y$8 - ($F14 - Current_Fiscal_Year)) / $G14))))/((($D14 - $E14)/($E14-1))+1) = INT((Y$8 - (($F14 - Current_Fiscal_Year)+$G14*INT(((Y$8 - ($F14 - Current_Fiscal_Year)) / $G14))))/((($D14 - $E14)/($E14-1))+1)), (Y$8 - (($F14 - Current_Fiscal_Year)+$G14*INT(((Y$8 - ($F14 - Current_Fiscal_Year)) / $G14)))) <$D14),IF(secondaryInflationYear- Current_Fiscal_Year >=Y$8,ROUND($L14* $R14*$S14*((1 + Y$7)^Y$8),1),ROUND($L14* $R14*$S14*(((1+secondaryInflation)^(secondaryInflationYear-Current_Fiscal_Year)) * ((1+Y$7)^(Y$8-(secondaryInflationYear - Current_Fiscal_Year)))),1)),"")),"") | Z14: =IFERROR(IF(OR(Z$8 = ($F14 - Current_Fiscal_Year),AND(MOD($F14-Z$9,$G14)=0,Z$9>$F14)),IF(secondaryInflationYear- Current_Fiscal_Year >=Z$8,ROUND($L14* $R14*$S14*((1 + Z$7)^Z$8),1),ROUND($L14* $R14*$S14*(((1+secondaryInflation)^(secondaryInflationYear-Current_Fiscal_Year)) * ((1+Z$7)^(Z$8-(secondaryInflationYear - Current_Fiscal_Year)))),1)),IF(AND($D14<>1,Z$8 > ($F14 - Current_Fiscal_Year),(Z$8 - (($F14 - Current_Fiscal_Year)+$G14*INT(((Z$8 - ($F14 - Current_Fiscal_Year)) / $G14))))/((($D14 - $E14)/($E14-1))+1) = INT((Z$8 - (($F14 - Current_Fiscal_Year)+$G14*INT(((Z$8 - ($F14 - Current_Fiscal_Year)) / $G14))))/((($D14 - $E14)/($E14-1))+1)), (Z$8 - (($F14 - Current_Fiscal_Year)+$G14*INT(((Z$8 - ($F14 - Current_Fiscal_Year)) / $G14)))) <$D14),IF(secondaryInflationYear- Current_Fiscal_Year >=Z$8,ROUND($L14* $R14*$S14*((1 + Z$7)^Z$8),1),ROUND($L14* $R14*$S14*(((1+secondaryInflation)^(secondaryInflationYear-Current_Fiscal_Year)) * ((1+Z$7)^(Z$8-(secondaryInflationYear - Current_Fiscal_Year)))),1)),"")),"") | AA14: =IFERROR(IF(OR(AA$8 = ($F14 - Current_Fiscal_Year),AND(MOD($F14-AA$9,$G14)=0,AA$9>$F14)),IF(secondaryInflationYear- Current_Fiscal_Year >=AA$8,ROUND($L14* $R14*$S14*((1 + AA$7)^AA$8),1),ROUND($L14* $R14*$S14*(((1+secondaryInflation)^(secondaryInflationYear-Current_Fiscal_Year)) * ((1+AA$7)^(AA$8-(secondaryInflationYear - Current_Fiscal_Year)))),1)),IF(AND($D14<>1,AA$8 > ($F14 - Current_Fiscal_Year),(AA$8 - (($F14 - Current_Fiscal_Year)+$G14*INT(((AA$8 - ($F14 - Current_Fiscal_Year)) / $G14))))/((($D14 - $E14)/($E14-1))+1) = INT((AA$8 - (($F14 - Current_Fiscal_Year)+$G14*INT(((AA$8 - ($F14 - Current_Fiscal_Year)) / $G14))))/((($D14 - $E14)/($E14-1))+1)), (AA$8 - (($F14 - Current_Fiscal_Year)+$G14*INT(((AA$8 - ($F14 - Current_Fiscal_Year)) / $G14)))) <$D14),IF(secondaryInflationYear- Current_Fiscal_Year >=AA$8,ROUND($L14* $R14*$S14*((1 + AA$7)^AA$8),1),ROUND($L14* $R14*$S14*(((1+secondaryInflation)^(secondaryInflationYear-Current_Fiscal_Year)) * ((1+AA$7)^(AA$8-(secondaryInflationYear - Current_Fiscal_Year)))),1)),"")),"") | AB14: =IFERROR(IF(OR(AB$8 = ($F14 - Current_Fiscal_Year),AND(MOD($F14-AB$9,$G14)=0,AB$9>$F14)),IF(secondaryInflationYear- Current_Fiscal_Year >=AB$8,ROUND($L14* $R14*$S14*((1 + AB$7)^AB$8),1),ROUND($L14* $R14*$S14*(((1+secondaryInflation)^(secondaryInflationYear-Current_Fiscal_Year)) * ((1+AB$7)^(AB$8-(secondaryInflationYear - Current_Fiscal_Year)))),1)),IF(AND($D14<>1,AB$8 > ($F14 - Current_Fiscal_Year),(AB$8 - (($F14 - Current_Fiscal_Year)+$G14*INT(((AB$8 - ($F14 - Current_Fiscal_Year)) / $G14))))/((($D14 - $E14)/($E14-1))+1) = INT((AB$8 - (($F14 - Current_Fiscal_Year)+$G14*INT(((AB$8 - ($F14 - Current_Fiscal_Year)) / $G14))))/((($D14 - $E14)/($E14-1))+1)), (AB$8 - (($F14 - Current_Fiscal_Year)+$G14*INT(((AB$8 - ($F14 - Current_Fiscal_Year)) / $G14)))) <$D14),IF(secondaryInflationYear- Current_Fiscal_Year >=AB$8,ROUND($L14* $R14*$S14*((1 + AB$7)^AB$8),1),ROUND($L14* $R14*$S14*(((1+secondaryInflation)^(secondaryInflationYear-Current_Fiscal_Year)) * ((1+AB$7)^(AB$8-(secondaryInflationYear - Current_Fiscal_Year)))),1)),"")),"") | AC14: =IFERROR(IF(OR(AC$8 = ($F14 - Current_Fiscal_Year),AND(MOD($F14-AC$9,$G14)=0,AC$9>$F14)),IF(secondaryInflationYear- Current_Fiscal_Year >=AC$8,ROUND($L14* $R14*$S14*((1 + AC$7)^AC$8),1),ROUND($L14* $R14*$S14*(((1+secondaryInflation)^(secondaryInflationYear-Current_Fiscal_Year)) * ((1+AC$7)^(AC$8-(secondaryInflationYear - Current_Fiscal_Year)))),1)),IF(AND($D14<>1,AC$8 > ($F14 - Current_Fiscal_Year),(AC$8 - (($F14 - Current_Fiscal_Year)+$G14*INT(((AC$8 - ($F14 - Current_Fiscal_Year)) / $G14))))/((($D14 - $E14)/($E14-1))+1) = INT((AC$8 - (($F14 - Current_Fiscal_Year)+$G14*INT(((AC$8 - ($F14 - Current_Fiscal_Year)) / $G14))))/((($D14 - $E14)/($E14-1))+1)), (AC$8 - (($F14 - Current_Fiscal_Year)+$G14*INT(((AC$8 - ($F14 - Current_Fiscal_Year)) / $G14)))) <$D14),IF(secondaryInflationYear- Current_Fiscal_Year >=AC$8,ROUND($L14* $R14*$S14*((1 + AC$7)^AC$8),1),ROUND($L14* $R14*$S14*(((1+secondaryInflation)^(secondaryInflationYear-Current_Fiscal_Year)) * ((1+AC$7)^(AC$8-(secondaryInflationYear - Current_Fiscal_Year)))),1)),"")),"") | AD14: =IFERROR(IF(OR(AD$8 = ($F14 - Current_Fiscal_Year),AND(MOD($F14-AD$9,$G14)=0,AD$9>$F14)),IF(secondaryInflationYear- Current_Fiscal_Year >=AD$8,ROUND($L14* $R14*$S14*((1 + AD$7)^AD$8),1),ROUND($L14* $R14*$S14*(((1+secondaryInflation)^(secondaryInflationYear-Current_Fiscal_Year)) * ((1+AD$7)^(AD$8-(secondaryInflationYear - Current_Fiscal_Year)))),1)),IF(AND($D14<>1,AD$8 > ($F14 - Current_Fiscal_Year),(AD$8 - (($F14 - Current_Fiscal_Year)+$G14*INT(((AD$8 - ($F14 - Current_Fiscal_Year)) / $G14))))/((($D14 - $E14)/($E14-1))+1) = INT((AD$8 - (($F14 - Current_Fiscal_Year)+$G14*INT(((AD$8 - ($F14 - Current_Fiscal_Year)) / $G14))))/((($D14 - $E14)/($E14-1))+1)), (AD$8 - (($F14 - Current_Fiscal_Year)+$G14*INT(((AD$8 - ($F14 - Current_Fiscal_Year)) / $G14)))) <$D14),IF(secondaryInflationYear- Current_Fiscal_Year >=AD$8,ROUND($L14* $R14*$S14*((1 + AD$7)^AD$8),1),ROUND($L14* $R14*$S14*(((1+secondaryInflation)^(secondaryInflationYear-Current_Fiscal_Year)) * ((1+AD$7)^(AD$8-(secondaryInflationYear - Current_Fiscal_Year)))),1)),"")),"") | AE14: =IFERROR(IF(OR(AE$8 = ($F14 - Current_Fiscal_Year),AND(MOD($F14-AE$9,$G14)=0,AE$9>$F14)),IF(secondaryInflationYear- Current_Fiscal_Year >=AE$8,ROUND($L14* $R14*$S14*((1 + AE$7)^AE$8),1),ROUND($L14* $R14*$S14*(((1+secondaryInflation)^(secondaryInflationYear-Current_Fiscal_Year)) * ((1+AE$7)^(AE$8-(secondaryInflationYear - Current_Fiscal_Year)))),1)),IF(AND($D14<>1,AE$8 > ($F14 - Current_Fiscal_Year),(AE$8 - (($F14 - Current_Fiscal_Year)+$G14*INT(((AE$8 - ($F14 - Current_Fiscal_Year)) / $G14))))/((($D14 - $E14)/($E14-1))+1) = INT((AE$8 - (($F14 - Current_Fiscal_Year)+$G14*INT(((AE$8 - ($F14 - Current_Fiscal_Year)) / $G14))))/((($D14 - $E14)/($E14-1))+1)), (AE$8 - (($F14 - Current_Fiscal_Year)+$G14*INT(((AE$8 - ($F14 - Current_Fiscal_Year)) / $G14)))) <$D14),IF(secondaryInflationYear- Current_Fiscal_Year >=AE$8,ROUND($L14* $R14*$S14*((1 + AE$7)^AE$8),1),ROUND($L14* $R14*$S14*(((1+secondaryInflation)^(secondaryInflationYear-Current_Fiscal_Year)) * ((1+AE$7)^(AE$8-(secondaryInflationYear - Current_Fiscal_Year)))),1)),"")),"") | ... BB14: =IFERROR(IF(OR(BB$8 = ($F14 - Current_Fiscal_Year),AND(MOD($F14-BB$9,$G14)=0,BB$9>$F14)),IF(secondaryInflationYear- Current_Fiscal_Year >=BB$8,ROUND($L14* $R14*$S14*((1 + BB$7)^BB$8),1),ROUND($L14* $R14*$S14*(((1+secondaryInflation)^(secondaryInflationYear-Current_Fiscal_Year)) * ((1+BB$7)^(BB$8-(secondaryInflationYear - Current_Fiscal_Year)))),1)),IF(AND($D14<>1,BB$8 > ($F14 - Current_Fiscal_Year),(BB$8 - (($F14 - Current_Fiscal_Year)+$G14*INT(((BB$8 - ($F14 - Current_Fiscal_Year)) / $G14))))/((($D14 - $E14)/($E14-1))+1) = INT((BB$8 - (($F14 - Current_Fiscal_Year)+$G14*INT(((BB$8 - ($F14 - Current_Fiscal_Year)) / $G14))))/((($D14 - $E14)/($E14-1))+1)), (BB$8 - (($F14 - Current_Fiscal_Year)+$G14*INT(((BB$8 - ($F14 - Current_Fiscal_Year)) / $G14)))) <$D14),IF(secondaryInflationYear- Current_Fiscal_Year >=BB$8,ROUND($L14* $R14*$S14*((1 + BB$7)^BB$8),1),ROUND($L14* $R14*$S14*(((1+secondaryInflation)^(secondaryInflationYear-Current_Fiscal_Year)) * ((1+BB$7)^(BB$8-(secondaryInflationYear - Current_Fiscal_Year)))),1)),"")),"")
A15: =IF(OFFSET($B15,IF(AND($K15=0,NOT(ISBLANK($K15))),-4,-3),-1)=0,1,0) -> 0 | B15: 1 | C15: 1 | D15: =(($E15-1)*$C15)+1 -> 1 | E15: 1 | F15: 2029 | G15: 7 | H15: 0.01 | J15: 4.24 | K15: 450 | L15: =IF(M15="Allowance",1,ROUND(K15*B15/E15/H15,0)*H15) -> 450 | M15: Linear Feet | N15: Fences, Steel, Paint Finishes | O15: =IF($F15>$BB$9,$F15,Current_Fiscal_Year+MATCH(TRUE,INDEX($X15:$BB15<>"",0),0)-1) -> 2029 | P15: 6 to 8 | Q15: =$O15-Current_Fiscal_Year&IF($B15<1," to "&Study_Length&"+",IF( $E15>1," to "&IF($O15-Current_Fiscal_Year+$D15-1>Study_Length,Study_Length&"+",$O15-Current_Fiscal_Year+$D15-1),"")) -> 3 | R15: 11 | S15: 1 | T15: =$L15*$R15*$S15 -> 4950 | U15: =$K15*$R15*$S15 -> 4950 | V15: =SUM(OFFSET($X15,,,1,Study_Length+1)) -> 20679.2 | W15: =$V15/Total_Study_Expenditures -> 0.02577488 | X15: =IFERROR(IF(OR(X$8 = ($F15 - Current_Fiscal_Year),AND(MOD($F15-X$9,$G15)=0,X$9>$F15)),IF(secondaryInflationYear- Current_Fiscal_Year >=X$8,ROUND($L15* $R15*$S15*((1 + X$7)^X$8),1),ROUND($L15* $R15*$S15*(((1+secondaryInflation)^(secondaryInflationYear-Current_Fiscal_Year)) * ((1+X$7)^(X$8-(secondaryInflationYear - Current_Fiscal_Year)))),1)),IF(AND($D15<>1,X$8 > ($F15 - Current_Fiscal_Year),(X$8 - (($F15 - Current_Fiscal_Year)+$G15*INT(((X$8 - ($F15 - Current_Fiscal_Year)) / $G15))))/((($D15 - $E15)/($E15-1))+1) = INT((X$8 - (($F15 - Current_Fiscal_Year)+$G15*INT(((X$8 - ($F15 - Current_Fiscal_Year)) / $G15))))/((($D15 - $E15)/($E15-1))+1)), (X$8 - (($F15 - Current_Fiscal_Year)+$G15*INT(((X$8 - ($F15 - Current_Fiscal_Year)) / $G15)))) <$D15),IF(secondaryInflationYear- Current_Fiscal_Year >=X$8,ROUND($L15* $R15*$S15*((1 + X$7)^X$8),1),ROUND($L15* $R15*$S15*(((1+secondaryInflation)^(secondaryInflationYear-Current_Fiscal_Year)) * ((1+X$7)^(X$8-(secondaryInflationYear - Current_Fiscal_Year)))),1)),"")),"") | Y15: =IFERROR(IF(OR(Y$8 = ($F15 - Current_Fiscal_Year),AND(MOD($F15-Y$9,$G15)=0,Y$9>$F15)),IF(secondaryInflationYear- Current_Fiscal_Year >=Y$8,ROUND($L15* $R15*$S15*((1 + Y$7)^Y$8),1),ROUND($L15* $R15*$S15*(((1+secondaryInflation)^(secondaryInflationYear-Current_Fiscal_Year)) * ((1+Y$7)^(Y$8-(secondaryInflationYear - Current_Fiscal_Year)))),1)),IF(AND($D15<>1,Y$8 > ($F15 - Current_Fiscal_Year),(Y$8 - (($F15 - Current_Fiscal_Year)+$G15*INT(((Y$8 - ($F15 - Current_Fiscal_Year)) / $G15))))/((($D15 - $E15)/($E15-1))+1) = INT((Y$8 - (($F15 - Current_Fiscal_Year)+$G15*INT(((Y$8 - ($F15 - Current_Fiscal_Year)) / $G15))))/((($D15 - $E15)/($E15-1))+1)), (Y$8 - (($F15 - Current_Fiscal_Year)+$G15*INT(((Y$8 - ($F15 - Current_Fiscal_Year)) / $G15)))) <$D15),IF(secondaryInflationYear- Current_Fiscal_Year >=Y$8,ROUND($L15* $R15*$S15*((1 + Y$7)^Y$8),1),ROUND($L15* $R15*$S15*(((1+secondaryInflation)^(secondaryInflationYear-Current_Fiscal_Year)) * ((1+Y$7)^(Y$8-(secondaryInflationYear - Current_Fiscal_Year)))),1)),"")),"") | Z15: =IFERROR(IF(OR(Z$8 = ($F15 - Current_Fiscal_Year),AND(MOD($F15-Z$9,$G15)=0,Z$9>$F15)),IF(secondaryInflationYear- Current_Fiscal_Year >=Z$8,ROUND($L15* $R15*$S15*((1 + Z$7)^Z$8),1),ROUND($L15* $R15*$S15*(((1+secondaryInflation)^(secondaryInflationYear-Current_Fiscal_Year)) * ((1+Z$7)^(Z$8-(secondaryInflationYear - Current_Fiscal_Year)))),1)),IF(AND($D15<>1,Z$8 > ($F15 - Current_Fiscal_Year),(Z$8 - (($F15 - Current_Fiscal_Year)+$G15*INT(((Z$8 - ($F15 - Current_Fiscal_Year)) / $G15))))/((($D15 - $E15)/($E15-1))+1) = INT((Z$8 - (($F15 - Current_Fiscal_Year)+$G15*INT(((Z$8 - ($F15 - Current_Fiscal_Year)) / $G15))))/((($D15 - $E15)/($E15-1))+1)), (Z$8 - (($F15 - Current_Fiscal_Year)+$G15*INT(((Z$8 - ($F15 - Current_Fiscal_Year)) / $G15)))) <$D15),IF(secondaryInflationYear- Current_Fiscal_Year >=Z$8,ROUND($L15* $R15*$S15*((1 + Z$7)^Z$8),1),ROUND($L15* $R15*$S15*(((1+secondaryInflation)^(secondaryInflationYear-Current_Fiscal_Year)) * ((1+Z$7)^(Z$8-(secondaryInflationYear - Current_Fiscal_Year)))),1)),"")),"") | AA15: =IFERROR(IF(OR(AA$8 = ($F15 - Current_Fiscal_Year),AND(MOD($F15-AA$9,$G15)=0,AA$9>$F15)),IF(secondaryInflationYear- Current_Fiscal_Year >=AA$8,ROUND($L15* $R15*$S15*((1 + AA$7)^AA$8),1),ROUND($L15* $R15*$S15*(((1+secondaryInflation)^(secondaryInflationYear-Current_Fiscal_Year)) * ((1+AA$7)^(AA$8-(secondaryInflationYear - Current_Fiscal_Year)))),1)),IF(AND($D15<>1,AA$8 > ($F15 - Current_Fiscal_Year),(AA$8 - (($F15 - Current_Fiscal_Year)+$G15*INT(((AA$8 - ($F15 - Current_Fiscal_Year)) / $G15))))/((($D15 - $E15)/($E15-1))+1) = INT((AA$8 - (($F15 - Current_Fiscal_Year)+$G15*INT(((AA$8 - ($F15 - Current_Fiscal_Year)) / $G15))))/((($D15 - $E15)/($E15-1))+1)), (AA$8 - (($F15 - Current_Fiscal_Year)+$G15*INT(((AA$8 - ($F15 - Current_Fiscal_Year)) / $G15)))) <$D15),IF(secondaryInflationYear- Current_Fiscal_Year >=AA$8,ROUND($L15* $R15*$S15*((1 + AA$7)^AA$8),1),ROUND($L15* $R15*$S15*(((1+secondaryInflation)^(secondaryInflationYear-Current_Fiscal_Year)) * ((1+AA$7)^(AA$8-(secondaryInflationYear - Current_Fiscal_Year)))),1)),"")),"") -> 5440.6 | AB15: =IFERROR(IF(OR(AB$8 = ($F15 - Current_Fiscal_Year),AND(MOD($F15-AB$9,$G15)=0,AB$9>$F15)),IF(secondaryInflationYear- Current_Fiscal_Year >=AB$8,ROUND($L15* $R15*$S15*((1 + AB$7)^AB$8),1),ROUND($L15* $R15*$S15*(((1+secondaryInflation)^(secondaryInflationYear-Current_Fiscal_Year)) * ((1+AB$7)^(AB$8-(secondaryInflationYear - Current_Fiscal_Year)))),1)),IF(AND($D15<>1,AB$8 > ($F15 - Current_Fiscal_Year),(AB$8 - (($F15 - Current_Fiscal_Year)+$G15*INT(((AB$8 - ($F15 - Current_Fiscal_Year)) / $G15))))/((($D15 - $E15)/($E15-1))+1) = INT((AB$8 - (($F15 - Current_Fiscal_Year)+$G15*INT(((AB$8 - ($F15 - Current_Fiscal_Year)) / $G15))))/((($D15 - $E15)/($E15-1))+1)), (AB$8 - (($F15 - Current_Fiscal_Year)+$G15*INT(((AB$8 - ($F15 - Current_Fiscal_Year)) / $G15)))) <$D15),IF(secondaryInflationYear- Current_Fiscal_Year >=AB$8,ROUND($L15* $R15*$S15*((1 + AB$7)^AB$8),1),ROUND($L15* $R15*$S15*(((1+secondaryInflation)^(secondaryInflationYear-Current_Fiscal_Year)) * ((1+AB$7)^(AB$8-(secondaryInflationYear - Current_Fiscal_Year)))),1)),"")),"") | AC15: =IFERROR(IF(OR(AC$8 = ($F15 - Current_Fiscal_Year),AND(MOD($F15-AC$9,$G15)=0,AC$9>$F15)),IF(secondaryInflationYear- Current_Fiscal_Year >=AC$8,ROUND($L15* $R15*$S15*((1 + AC$7)^AC$8),1),ROUND($L15* $R15*$S15*(((1+secondaryInflation)^(secondaryInflationYear-Current_Fiscal_Year)) * ((1+AC$7)^(AC$8-(secondaryInflationYear - Current_Fiscal_Year)))),1)),IF(AND($D15<>1,AC$8 > ($F15 - Current_Fiscal_Year),(AC$8 - (($F15 - Current_Fiscal_Year)+$G15*INT(((AC$8 - ($F15 - Current_Fiscal_Year)) / $G15))))/((($D15 - $E15)/($E15-1))+1) = INT((AC$8 - (($F15 - Current_Fiscal_Year)+$G15*INT(((AC$8 - ($F15 - Current_Fiscal_Year)) / $G15))))/((($D15 - $E15)/($E15-1))+1)), (AC$8 - (($F15 - Current_Fiscal_Year)+$G15*INT(((AC$8 - ($F15 - Current_Fiscal_Year)) / $G15)))) <$D15),IF(secondaryInflationYear- Current_Fiscal_Year >=AC$8,ROUND($L15* $R15*$S15*((1 + AC$7)^AC$8),1),ROUND($L15* $R15*$S15*(((1+secondaryInflation)^(secondaryInflationYear-Current_Fiscal_Year)) * ((1+AC$7)^(AC$8-(secondaryInflationYear - Current_Fiscal_Year)))),1)),"")),"") | AD15: =IFERROR(IF(OR(AD$8 = ($F15 - Current_Fiscal_Year),AND(MOD($F15-AD$9,$G15)=0,AD$9>$F15)),IF(secondaryInflationYear- Current_Fiscal_Year >=AD$8,ROUND($L15* $R15*$S15*((1 + AD$7)^AD$8),1),ROUND($L15* $R15*$S15*(((1+secondaryInflation)^(secondaryInflationYear-Current_Fiscal_Year)) * ((1+AD$7)^(AD$8-(secondaryInflationYear - Current_Fiscal_Year)))),1)),IF(AND($D15<>1,AD$8 > ($F15 - Current_Fiscal_Year),(AD$8 - (($F15 - Current_Fiscal_Year)+$G15*INT(((AD$8 - ($F15 - Current_Fiscal_Year)) / $G15))))/((($D15 - $E15)/($E15-1))+1) = INT((AD$8 - (($F15 - Current_Fiscal_Year)+$G15*INT(((AD$8 - ($F15 - Current_Fiscal_Year)) / $G15))))/((($D15 - $E15)/($E15-1))+1)), (AD$8 - (($F15 - Current_Fiscal_Year)+$G15*INT(((AD$8 - ($F15 - Current_Fiscal_Year)) / $G15)))) <$D15),IF(secondaryInflationYear- Current_Fiscal_Year >=AD$8,ROUND($L15* $R15*$S15*((1 + AD$7)^AD$8),1),ROUND($L15* $R15*$S15*(((1+secondaryInflation)^(secondaryInflationYear-Current_Fiscal_Year)) * ((1+AD$7)^(AD$8-(secondaryInflationYear - Current_Fiscal_Year)))),1)),"")),"") | AE15: =IFERROR(IF(OR(AE$8 = ($F15 - Current_Fiscal_Year),AND(MOD($F15-AE$9,$G15)=0,AE$9>$F15)),IF(secondaryInflationYear- Current_Fiscal_Year >=AE$8,ROUND($L15* $R15*$S15*((1 + AE$7)^AE$8),1),ROUND($L15* $R15*$S15*(((1+secondaryInflation)^(secondaryInflationYear-Current_Fiscal_Year)) * ((1+AE$7)^(AE$8-(secondaryInflationYear - Current_Fiscal_Year)))),1)),IF(AND($D15<>1,AE$8 > ($F15 - Current_Fiscal_Year),(AE$8 - (($F15 - Current_Fiscal_Year)+$G15*INT(((AE$8 - ($F15 - Current_Fiscal_Year)) / $G15))))/((($D15 - $E15)/($E15-1))+1) = INT((AE$8 - (($F15 - Current_Fiscal_Year)+$G15*INT(((AE$8 - ($F15 - Current_Fiscal_Year)) / $G15))))/((($D15 - $E15)/($E15-1))+1)), (AE$8 - (($F15 - Current_Fiscal_Year)+$G15*INT(((AE$8 - ($F15 - Current_Fiscal_Year)) / $G15)))) <$D15),IF(secondaryInflationYear- Current_Fiscal_Year >=AE$8,ROUND($L15* $R15*$S15*((1 + AE$7)^AE$8),1),ROUND($L15* $R15*$S15*(((1+secondaryInflation)^(secondaryInflationYear-Current_Fiscal_Year)) * ((1+AE$7)^(AE$8-(secondaryInflationYear - Current_Fiscal_Year)))),1)),"")),"") | ... AU15: =IFERROR(IF(OR(AU$8 = ($F15 - Current_Fiscal_Year),AND(MOD($F15-AU$9,$G15)=0,AU$9>$F15)),IF(secondaryInflationYear- Current_Fiscal_Year >=AU$8,ROUND($L15* $R15*$S15*((1 + AU$7)^AU$8),1),ROUND($L15* $R15*$S15*(((1+secondaryInflation)^(secondaryInflationYear-Current_Fiscal_Year)) * ((1+AU$7)^(AU$8-(secondaryInflationYear - Current_Fiscal_Year)))),1)),IF(AND($D15<>1,AU$8 > ($F15 - Current_Fiscal_Year),(AU$8 - (($F15 - Current_Fiscal_Year)+$G15*INT(((AU$8 - ($F15 - Current_Fiscal_Year)) / $G15))))/((($D15 - $E15)/($E15-1))+1) = INT((AU$8 - (($F15 - Current_Fiscal_Year)+$G15*INT(((AU$8 - ($F15 - Current_Fiscal_Year)) / $G15))))/((($D15 - $E15)/($E15-1))+1)), (AU$8 - (($F15 - Current_Fiscal_Year)+$G15*INT(((AU$8 - ($F15 - Current_Fiscal_Year)) / $G15)))) <$D15),IF(secondaryInflationYear- Current_Fiscal_Year >=AU$8,ROUND($L15* $R15*$S15*((1 + AU$7)^AU$8),1),ROUND($L15* $R15*$S15*(((1+secondaryInflation)^(secondaryInflationYear-Current_Fiscal_Year)) * ((1+AU$7)^(AU$8-(secondaryInflationYear - Current_Fiscal_Year)))),1)),"")),"") | AX15: =IFERROR(IF(OR(AX$8 = ($F15 - Current_Fiscal_Year),AND(MOD($F15-AX$9,$G15)=0,AX$9>$F15)),IF(secondaryInflationYear- Current_Fiscal_Year >=AX$8,ROUND($L15* $R15*$S15*((1 + AX$7)^AX$8),1),ROUND($L15* $R15*$S15*(((1+secondaryInflation)^(secondaryInflationYear-Current_Fiscal_Year)) * ((1+AX$7)^(AX$8-(secondaryInflationYear - Current_Fiscal_Year)))),1)),IF(AND($D15<>1,AX$8 > ($F15 - Current_Fiscal_Year),(AX$8 - (($F15 - Current_Fiscal_Year)+$G15*INT(((AX$8 - ($F15 - Current_Fiscal_Year)) / $G15))))/((($D15 - $E15)/($E15-1))+1) = INT((AX$8 - (($F15 - Current_Fiscal_Year)+$G15*INT(((AX$8 - ($F15 - Current_Fiscal_Year)) / $G15))))/((($D15 - $E15)/($E15-1))+1)), (AX$8 - (($F15 - Current_Fiscal_Year)+$G15*INT(((AX$8 - ($F15 - Current_Fiscal_Year)) / $G15)))) <$D15),IF(secondaryInflationYear- Current_Fiscal_Year >=AX$8,ROUND($L15* $R15*$S15*((1 + AX$7)^AX$8),1),ROUND($L15* $R15*$S15*(((1+secondaryInflation)^(secondaryInflationYear-Current_Fiscal_Year)) * ((1+AX$7)^(AX$8-(secondaryInflationYear - Current_Fiscal_Year)))),1)),"")),"") | AY15: =IFERROR(IF(OR(AY$8 = ($F15 - Current_Fiscal_Year),AND(MOD($F15-AY$9,$G15)=0,AY$9>$F15)),IF(secondaryInflationYear- Current_Fiscal_Year >=AY$8,ROUND($L15* $R15*$S15*((1 + AY$7)^AY$8),1),ROUND($L15* $R15*$S15*(((1+secondaryInflation)^(secondaryInflationYear-Current_Fiscal_Year)) * ((1+AY$7)^(AY$8-(secondaryInflationYear - Current_Fiscal_Year)))),1)),IF(AND($D15<>1,AY$8 > ($F15 - Current_Fiscal_Year),(AY$8 - (($F15 - Current_Fiscal_Year)+$G15*INT(((AY$8 - ($F15 - Current_Fiscal_Year)) / $G15))))/((($D15 - $E15)/($E15-1))+1) = INT((AY$8 - (($F15 - Current_Fiscal_Year)+$G15*INT(((AY$8 - ($F15 - Current_Fiscal_Year)) / $G15))))/((($D15 - $E15)/($E15-1))+1)), (AY$8 - (($F15 - Current_Fiscal_Year)+$G15*INT(((AY$8 - ($F15 - Current_Fiscal_Year)) / $G15)))) <$D15),IF(secondaryInflationYear- Current_Fiscal_Year >=AY$8,ROUND($L15* $R15*$S15*((1 + AY$7)^AY$8),1),ROUND($L15* $R15*$S15*(((1+secondaryInflation)^(secondaryInflationYear-Current_Fiscal_Year)) * ((1+AY$7)^(AY$8-(secondaryInflationYear - Current_Fiscal_Year)))),1)),"")),"") | AZ15: =IFERROR(IF(OR(AZ$8 = ($F15 - Current_Fiscal_Year),AND(MOD($F15-AZ$9,$G15)=0,AZ$9>$F15)),IF(secondaryInflationYear- Current_Fiscal_Year >=AZ$8,ROUND($L15* $R15*$S15*((1 + AZ$7)^AZ$8),1),ROUND($L15* $R15*$S15*(((1+secondaryInflation)^(secondaryInflationYear-Current_Fiscal_Year)) * ((1+AZ$7)^(AZ$8-(secondaryInflationYear - Current_Fiscal_Year)))),1)),IF(AND($D15<>1,AZ$8 > ($F15 - Current_Fiscal_Year),(AZ$8 - (($F15 - Current_Fiscal_Year)+$G15*INT(((AZ$8 - ($F15 - Current_Fiscal_Year)) / $G15))))/((($D15 - $E15)/($E15-1))+1) = INT((AZ$8 - (($F15 - Current_Fiscal_Year)+$G15*INT(((AZ$8 - ($F15 - Current_Fiscal_Year)) / $G15))))/((($D15 - $E15)/($E15-1))+1)), (AZ$8 - (($F15 - Current_Fiscal_Year)+$G15*INT(((AZ$8 - ($F15 - Current_Fiscal_Year)) / $G15)))) <$D15),IF(secondaryInflationYear- Current_Fiscal_Year >=AZ$8,ROUND($L15* $R15*$S15*((1 + AZ$7)^AZ$8),1),ROUND($L15* $R15*$S15*(((1+secondaryInflation)^(secondaryInflationYear-Current_Fiscal_Year)) * ((1+AZ$7)^(AZ$8-(secondaryInflationYear - Current_Fiscal_Year)))),1)),"")),"") | BA15: =IFERROR(IF(OR(BA$8 = ($F15 - Current_Fiscal_Year),AND(MOD($F15-BA$9,$G15)=0,BA$9>$F15)),IF(secondaryInflationYear- Current_Fiscal_Year >=BA$8,ROUND($L15* $R15*$S15*((1 + BA$7)^BA$8),1),ROUND($L15* $R15*$S15*(((1+secondaryInflation)^(secondaryInflationYear-Current_Fiscal_Year)) * ((1+BA$7)^(BA$8-(secondaryInflationYear - Current_Fiscal_Year)))),1)),IF(AND($D15<>1,BA$8 > ($F15 - Current_Fiscal_Year),(BA$8 - (($F15 - Current_Fiscal_Year)+$G15*INT(((BA$8 - ($F15 - Current_Fiscal_Year)) / $G15))))/((($D15 - $E15)/($E15-1))+1) = INT((BA$8 - (($F15 - Current_Fiscal_Year)+$G15*INT(((BA$8 - ($F15 - Current_Fiscal_Year)) / $G15))))/((($D15 - $E15)/($E15-1))+1)), (BA$8 - (($F15 - Current_Fiscal_Year)+$G15*INT(((BA$8 - ($F15 - Current_Fiscal_Year)) / $G15)))) <$D15),IF(secondaryInflationYear- Current_Fiscal_Year >=BA$8,ROUND($L15* $R15*$S15*((1 + BA$7)^BA$8),1),ROUND($L15* $R15*$S15*(((1+secondaryInflation)^(secondaryInflationYear-Current_Fiscal_Year)) * ((1+BA$7)^(BA$8-(secondaryInflationYear - Current_Fiscal_Year)))),1)),"")),"") | BB15: =IFERROR(IF(OR(BB$8 = ($F15 - Current_Fiscal_Year),AND(MOD($F15-BB$9,$G15)=0,BB$9>$F15)),IF(secondaryInflationYear- Current_Fiscal_Year >=BB$8,ROUND($L15* $R15*$S15*((1 + BB$7)^BB$8),1),ROUND($L15* $R15*$S15*(((1+secondaryInflation)^(secondaryInflationYear-Current_Fiscal_Year)) * ((1+BB$7)^(BB$8-(secondaryInflationYear - Current_Fiscal_Year)))),1)),IF(AND($D15<>1,BB$8 > ($F15 - Current_Fiscal_Year),(BB$8 - (($F15 - Current_Fiscal_Year)+$G15*INT(((BB$8 - ($F15 - Current_Fiscal_Year)) / $G15))))/((($D15 - $E15)/($E15-1))+1) = INT((BB$8 - (($F15 - Current_Fiscal_Year)+$G15*INT(((BB$8 - ($F15 - Current_Fiscal_Year)) / $G15))))/((($D15 - $E15)/($E15-1))+1)), (BB$8 - (($F15 - Current_Fiscal_Year)+$G15*INT(((BB$8 - ($F15 - Current_Fiscal_Year)) / $G15)))) <$D15),IF(secondaryInflationYear- Current_Fiscal_Year >=BB$8,ROUND($L15* $R15*$S15*((1 + BB$7)^BB$8),1),ROUND($L15* $R15*$S15*(((1+secondaryInflation)^(secondaryInflationYear-Current_Fiscal_Year)) * ((1+BB$7)^(BB$8-(secondaryInflationYear - Current_Fiscal_Year)))),1)),"")),"")
A16: =IF(OFFSET($B16,IF(AND($K16=0,NOT(ISBLANK($K16))),-4,-3),-1)=0,1,0) -> 0 | B16: 1 | C16: 1 | D16: =(($E16-1)*$C16)+1 -> 1 | E16: 1 | F16: 2050 | G16: 35 | H16: 0.01 | J16: 4.245 | K16: 450 | L16: =IF(M16="Allowance",1,ROUND(K16*B16/E16/H16,0)*H16) -> 450 | M16: Linear Feet | N16: Fences, Steel, Replacement | O16: =IF($F16>$BB$9,$F16,Current_Fiscal_Year+MATCH(TRUE,INDEX($X16:$BB16<>"",0),0)-1) -> 2050 | P16: to 35 | Q16: =$O16-Current_Fiscal_Year&IF($B16<1," to "&Study_Length&"+",IF( $E16>1," to "&IF($O16-Current_Fiscal_Year+$D16-1>Study_Length,Study_Length&"+",$O16-Current_Fiscal_Year+$D16-1),"")) -> 24 | R16: 100 | S16: 1 | T16: =$L16*$R16*$S16 -> 45000 | U16: =$K16*$R16*$S16 -> 45000 | V16: =SUM(OFFSET($X16,,,1,Study_Length+1)) -> 95835.2 | W16: =$V16/Total_Study_Expenditures -> 0.1194505 | X16: =IFERROR(IF(OR(X$8 = ($F16 - Current_Fiscal_Year),AND(MOD($F16-X$9,$G16)=0,X$9>$F16)),IF(secondaryInflationYear- Current_Fiscal_Year >=X$8,ROUND($L16* $R16*$S16*((1 + X$7)^X$8),1),ROUND($L16* $R16*$S16*(((1+secondaryInflation)^(secondaryInflationYear-Current_Fiscal_Year)) * ((1+X$7)^(X$8-(secondaryInflationYear - Current_Fiscal_Year)))),1)),IF(AND($D16<>1,X$8 > ($F16 - Current_Fiscal_Year),(X$8 - (($F16 - Current_Fiscal_Year)+$G16*INT(((X$8 - ($F16 - Current_Fiscal_Year)) / $G16))))/((($D16 - $E16)/($E16-1))+1) = INT((X$8 - (($F16 - Current_Fiscal_Year)+$G16*INT(((X$8 - ($F16 - Current_Fiscal_Year)) / $G16))))/((($D16 - $E16)/($E16-1))+1)), (X$8 - (($F16 - Current_Fiscal_Year)+$G16*INT(((X$8 - ($F16 - Current_Fiscal_Year)) / $G16)))) <$D16),IF(secondaryInflationYear- Current_Fiscal_Year >=X$8,ROUND($L16* $R16*$S16*((1 + X$7)^X$8),1),ROUND($L16* $R16*$S16*(((1+secondaryInflation)^(secondaryInflationYear-Current_Fiscal_Year)) * ((1+X$7)^(X$8-(secondaryInflationYear - Current_Fiscal_Year)))),1)),"")),"") | Y16: =IFERROR(IF(OR(Y$8 = ($F16 - Current_Fiscal_Year),AND(MOD($F16-Y$9,$G16)=0,Y$9>$F16)),IF(secondaryInflationYear- Current_Fiscal_Year >=Y$8,ROUND($L16* $R16*$S16*((1 + Y$7)^Y$8),1),ROUND($L16* $R16*$S16*(((1+secondaryInflation)^(secondaryInflationYear-Current_Fiscal_Year)) * ((1+Y$7)^(Y$8-(secondaryInflationYear - Current_Fiscal_Year)))),1)),IF(AND($D16<>1,Y$8 > ($F16 - Current_Fiscal_Year),(Y$8 - (($F16 - Current_Fiscal_Year)+$G16*INT(((Y$8 - ($F16 - Current_Fiscal_Year)) / $G16))))/((($D16 - $E16)/($E16-1))+1) = INT((Y$8 - (($F16 - Current_Fiscal_Year)+$G16*INT(((Y$8 - ($F16 - Current_Fiscal_Year)) / $G16))))/((($D16 - $E16)/($E16-1))+1)), (Y$8 - (($F16 - Current_Fiscal_Year)+$G16*INT(((Y$8 - ($F16 - Current_Fiscal_Year)) / $G16)))) <$D16),IF(secondaryInflationYear- Current_Fiscal_Year >=Y$8,ROUND($L16* $R16*$S16*((1 + Y$7)^Y$8),1),ROUND($L16* $R16*$S16*(((1+secondaryInflation)^(secondaryInflationYear-Current_Fiscal_Year)) * ((1+Y$7)^(Y$8-(secondaryInflationYear - Current_Fiscal_Year)))),1)),"")),"") | Z16: =IFERROR(IF(OR(Z$8 = ($F16 - Current_Fiscal_Year),AND(MOD($F16-Z$9,$G16)=0,Z$9>$F16)),IF(secondaryInflationYear- Current_Fiscal_Year >=Z$8,ROUND($L16* $R16*$S16*((1 + Z$7)^Z$8),1),ROUND($L16* $R16*$S16*(((1+secondaryInflation)^(secondaryInflationYear-Current_Fiscal_Year)) * ((1+Z$7)^(Z$8-(secondaryInflationYear - Current_Fiscal_Year)))),1)),IF(AND($D16<>1,Z$8 > ($F16 - Current_Fiscal_Year),(Z$8 - (($F16 - Current_Fiscal_Year)+$G16*INT(((Z$8 - ($F16 - Current_Fiscal_Year)) / $G16))))/((($D16 - $E16)/($E16-1))+1) = INT((Z$8 - (($F16 - Current_Fiscal_Year)+$G16*INT(((Z$8 - ($F16 - Current_Fiscal_Year)) / $G16))))/((($D16 - $E16)/($E16-1))+1)), (Z$8 - (($F16 - Current_Fiscal_Year)+$G16*INT(((Z$8 - ($F16 - Current_Fiscal_Year)) / $G16)))) <$D16),IF(secondaryInflationYear- Current_Fiscal_Year >=Z$8,ROUND($L16* $R16*$S16*((1 + Z$7)^Z$8),1),ROUND($L16* $R16*$S16*(((1+secondaryInflation)^(secondaryInflationYear-Current_Fiscal_Year)) * ((1+Z$7)^(Z$8-(secondaryInflationYear - Current_Fiscal_Year)))),1)),"")),"") | AA16: =IFERROR(IF(OR(AA$8 = ($F16 - Current_Fiscal_Year),AND(MOD($F16-AA$9,$G16)=0,AA$9>$F16)),IF(secondaryInflationYear- Current_Fiscal_Year >=AA$8,ROUND($L16* $R16*$S16*((1 + AA$7)^AA$8),1),ROUND($L16* $R16*$S16*(((1+secondaryInflation)^(secondaryInflationYear-Current_Fiscal_Year)) * ((1+AA$7)^(AA$8-(secondaryInflationYear - Current_Fiscal_Year)))),1)),IF(AND($D16<>1,AA$8 > ($F16 - Current_Fiscal_Year),(AA$8 - (($F16 - Current_Fiscal_Year)+$G16*INT(((AA$8 - ($F16 - Current_Fiscal_Year)) / $G16))))/((($D16 - $E16)/($E16-1))+1) = INT((AA$8 - (($F16 - Current_Fiscal_Year)+$G16*INT(((AA$8 - ($F16 - Current_Fiscal_Year)) / $G16))))/((($D16 - $E16)/($E16-1))+1)), (AA$8 - (($F16 - Current_Fiscal_Year)+$G16*INT(((AA$8 - ($F16 - Current_Fiscal_Year)) / $G16)))) <$D16),IF(secondaryInflationYear- Current_Fiscal_Year >=AA$8,ROUND($L16* $R16*$S16*((1 + AA$7)^AA$8),1),ROUND($L16* $R16*$S16*(((1+secondaryInflation)^(secondaryInflationYear-Current_Fiscal_Year)) * ((1+AA$7)^(AA$8-(secondaryInflationYear - Current_Fiscal_Year)))),1)),"")),"") | AB16: =IFERROR(IF(OR(AB$8 = ($F16 - Current_Fiscal_Year),AND(MOD($F16-AB$9,$G16)=0,AB$9>$F16)),IF(secondaryInflationYear- Current_Fiscal_Year >=AB$8,ROUND($L16* $R16*$S16*((1 + AB$7)^AB$8),1),ROUND($L16* $R16*$S16*(((1+secondaryInflation)^(secondaryInflationYear-Current_Fiscal_Year)) * ((1+AB$7)^(AB$8-(secondaryInflationYear - Current_Fiscal_Year)))),1)),IF(AND($D16<>1,AB$8 > ($F16 - Current_Fiscal_Year),(AB$8 - (($F16 - Current_Fiscal_Year)+$G16*INT(((AB$8 - ($F16 - Current_Fiscal_Year)) / $G16))))/((($D16 - $E16)/($E16-1))+1) = INT((AB$8 - (($F16 - Current_Fiscal_Year)+$G16*INT(((AB$8 - ($F16 - Current_Fiscal_Year)) / $G16))))/((($D16 - $E16)/($E16-1))+1)), (AB$8 - (($F16 - Current_Fiscal_Year)+$G16*INT(((AB$8 - ($F16 - Current_Fiscal_Year)) / $G16)))) <$D16),IF(secondaryInflationYear- Current_Fiscal_Year >=AB$8,ROUND($L16* $R16*$S16*((1 + AB$7)^AB$8),1),ROUND($L16* $R16*$S16*(((1+secondaryInflation)^(secondaryInflationYear-Current_Fiscal_Year)) * ((1+AB$7)^(AB$8-(secondaryInflationYear - Current_Fiscal_Year)))),1)),"")),"") | AC16: =IFERROR(IF(OR(AC$8 = ($F16 - Current_Fiscal_Year),AND(MOD($F16-AC$9,$G16)=0,AC$9>$F16)),IF(secondaryInflationYear- Current_Fiscal_Year >=AC$8,ROUND($L16* $R16*$S16*((1 + AC$7)^AC$8),1),ROUND($L16* $R16*$S16*(((1+secondaryInflation)^(secondaryInflationYear-Current_Fiscal_Year)) * ((1+AC$7)^(AC$8-(secondaryInflationYear - Current_Fiscal_Year)))),1)),IF(AND($D16<>1,AC$8 > ($F16 - Current_Fiscal_Year),(AC$8 - (($F16 - Current_Fiscal_Year)+$G16*INT(((AC$8 - ($F16 - Current_Fiscal_Year)) / $G16))))/((($D16 - $E16)/($E16-1))+1) = INT((AC$8 - (($F16 - Current_Fiscal_Year)+$G16*INT(((AC$8 - ($F16 - Current_Fiscal_Year)) / $G16))))/((($D16 - $E16)/($E16-1))+1)), (AC$8 - (($F16 - Current_Fiscal_Year)+$G16*INT(((AC$8 - ($F16 - Current_Fiscal_Year)) / $G16)))) <$D16),IF(secondaryInflationYear- Current_Fiscal_Year >=AC$8,ROUND($L16* $R16*$S16*((1 + AC$7)^AC$8),1),ROUND($L16* $R16*$S16*(((1+secondaryInflation)^(secondaryInflationYear-Current_Fiscal_Year)) * ((1+AC$7)^(AC$8-(secondaryInflationYear - Current_Fiscal_Year)))),1)),"")),"") | AD16: =IFERROR(IF(OR(AD$8 = ($F16 - Current_Fiscal_Year),AND(MOD($F16-AD$9,$G16)=0,AD$9>$F16)),IF(secondaryInflationYear- Current_Fiscal_Year >=AD$8,ROUND($L16* $R16*$S16*((1 + AD$7)^AD$8),1),ROUND($L16* $R16*$S16*(((1+secondaryInflation)^(secondaryInflationYear-Current_Fiscal_Year)) * ((1+AD$7)^(AD$8-(secondaryInflationYear - Current_Fiscal_Year)))),1)),IF(AND($D16<>1,AD$8 > ($F16 - Current_Fiscal_Year),(AD$8 - (($F16 - Current_Fiscal_Year)+$G16*INT(((AD$8 - ($F16 - Current_Fiscal_Year)) / $G16))))/((($D16 - $E16)/($E16-1))+1) = INT((AD$8 - (($F16 - Current_Fiscal_Year)+$G16*INT(((AD$8 - ($F16 - Current_Fiscal_Year)) / $G16))))/((($D16 - $E16)/($E16-1))+1)), (AD$8 - (($F16 - Current_Fiscal_Year)+$G16*INT(((AD$8 - ($F16 - Current_Fiscal_Year)) / $G16)))) <$D16),IF(secondaryInflationYear- Current_Fiscal_Year >=AD$8,ROUND($L16* $R16*$S16*((1 + AD$7)^AD$8),1),ROUND($L16* $R16*$S16*(((1+secondaryInflation)^(secondaryInflationYear-Current_Fiscal_Year)) * ((1+AD$7)^(AD$8-(secondaryInflationYear - Current_Fiscal_Year)))),1)),"")),"") | AE16: =IFERROR(IF(OR(AE$8 = ($F16 - Current_Fiscal_Year),AND(MOD($F16-AE$9,$G16)=0,AE$9>$F16)),IF(secondaryInflationYear- Current_Fiscal_Year >=AE$8,ROUND($L16* $R16*$S16*((1 + AE$7)^AE$8),1),ROUND($L16* $R16*$S16*(((1+secondaryInflation)^(secondaryInflationYear-Current_Fiscal_Year)) * ((1+AE$7)^(AE$8-(secondaryInflationYear - Current_Fiscal_Year)))),1)),IF(AND($D16<>1,AE$8 > ($F16 - Current_Fiscal_Year),(AE$8 - (($F16 - Current_Fiscal_Year)+$G16*INT(((AE$8 - ($F16 - Current_Fiscal_Year)) / $G16))))/((($D16 - $E16)/($E16-1))+1) = INT((AE$8 - (($F16 - Current_Fiscal_Year)+$G16*INT(((AE$8 - ($F16 - Current_Fiscal_Year)) / $G16))))/((($D16 - $E16)/($E16-1))+1)), (AE$8 - (($F16 - Current_Fiscal_Year)+$G16*INT(((AE$8 - ($F16 - Current_Fiscal_Year)) / $G16)))) <$D16),IF(secondaryInflationYear- Current_Fiscal_Year >=AE$8,ROUND($L16* $R16*$S16*((1 + AE$7)^AE$8),1),ROUND($L16* $R16*$S16*(((1+secondaryInflation)^(secondaryInflationYear-Current_Fiscal_Year)) * ((1+AE$7)^(AE$8-(secondaryInflationYear - Current_Fiscal_Year)))),1)),"")),"") | ... BB16: =IFERROR(IF(OR(BB$8 = ($F16 - Current_Fiscal_Year),AND(MOD($F16-BB$9,$G16)=0,BB$9>$F16)),IF(secondaryInflationYear- Current_Fiscal_Year >=BB$8,ROUND($L16* $R16*$S16*((1 + BB$7)^BB$8),1),ROUND($L16* $R16*$S16*(((1+secondaryInflation)^(secondaryInflationYear-Current_Fiscal_Year)) * ((1+BB$7)^(BB$8-(secondaryInflationYear - Current_Fiscal_Year)))),1)),IF(AND($D16<>1,BB$8 > ($F16 - Current_Fiscal_Year),(BB$8 - (($F16 - Current_Fiscal_Year)+$G16*INT(((BB$8 - ($F16 - Current_Fiscal_Year)) / $G16))))/((($D16 - $E16)/($E16-1))+1) = INT((BB$8 - (($F16 - Current_Fiscal_Year)+$G16*INT(((BB$8 - ($F16 - Current_Fiscal_Year)) / $G16))))/((($D16 - $E16)/($E16-1))+1)), (BB$8 - (($F16 - Current_Fiscal_Year)+$G16*INT(((BB$8 - ($F16 - Current_Fiscal_Year)) / $G16)))) <$D16),IF(secondaryInflationYear- Current_Fiscal_Year >=BB$8,ROUND($L16* $R16*$S16*((1 + BB$7)^BB$8),1),ROUND($L16* $R16*$S16*(((1+secondaryInflation)^(secondaryInflationYear-Current_Fiscal_Year)) * ((1+BB$7)^(BB$8-(secondaryInflationYear - Current_Fiscal_Year)))),1)),"")),"")
A17: =IF(OFFSET($B17,IF(AND($K17=0,NOT(ISBLANK($K17))),-4,-3),-1)=0,1,0) -> 1 | B17: 1 | C17: 1 | D17: =(($E17-1)*$C17)+1 -> 1 | E17: 1 | F17: 2036 | G17: 15 | H17: 0.01 | J17: 4.31 | K17: 1 | L17: =IF(M17="Allowance",1,ROUND(K17*B17/E17/H17,0)*H17) -> 1 | M17: Allowance | N17: Gate Entry System | O17: =IF($F17>$BB$9,$F17,Current_Fiscal_Year+MATCH(TRUE,INDEX($X17:$BB17<>"",0),0)-1) -> 2036 | P17: 10 to 15 | Q17: =$O17-Current_Fiscal_Year&IF($B17<1," to "&Study_Length&"+",IF( $E17>1," to "&IF($O17-Current_Fiscal_Year+$D17-1>Study_Length,Study_Length&"+",$O17-Current_Fiscal_Year+$D17-1),"")) -> 10 | R17: 34000 | S17: 1 | T17: =$L17*$R17*$S17 -> 34000 | U17: =$K17*$R17*$S17 -> 34000 | V17: =SUM(OFFSET($X17,,,1,Study_Length+1)) -> 121314.1 | W17: =$V17/Total_Study_Expenditures -> 0.1512078 | X17: =IFERROR(IF(OR(X$8 = ($F17 - Current_Fiscal_Year),AND(MOD($F17-X$9,$G17)=0,X$9>$F17)),IF(secondaryInflationYear- Current_Fiscal_Year >=X$8,ROUND($L17* $R17*$S17*((1 + X$7)^X$8),1),ROUND($L17* $R17*$S17*(((1+secondaryInflation)^(secondaryInflationYear-Current_Fiscal_Year)) * ((1+X$7)^(X$8-(secondaryInflationYear - Current_Fiscal_Year)))),1)),IF(AND($D17<>1,X$8 > ($F17 - Current_Fiscal_Year),(X$8 - (($F17 - Current_Fiscal_Year)+$G17*INT(((X$8 - ($F17 - Current_Fiscal_Year)) / $G17))))/((($D17 - $E17)/($E17-1))+1) = INT((X$8 - (($F17 - Current_Fiscal_Year)+$G17*INT(((X$8 - ($F17 - Current_Fiscal_Year)) / $G17))))/((($D17 - $E17)/($E17-1))+1)), (X$8 - (($F17 - Current_Fiscal_Year)+$G17*INT(((X$8 - ($F17 - Current_Fiscal_Year)) / $G17)))) <$D17),IF(secondaryInflationYear- Current_Fiscal_Year >=X$8,ROUND($L17* $R17*$S17*((1 + X$7)^X$8),1),ROUND($L17* $R17*$S17*(((1+secondaryInflation)^(secondaryInflationYear-Current_Fiscal_Year)) * ((1+X$7)^(X$8-(secondaryInflationYear - Current_Fiscal_Year)))),1)),"")),"") | Y17: =IFERROR(IF(OR(Y$8 = ($F17 - Current_Fiscal_Year),AND(MOD($F17-Y$9,$G17)=0,Y$9>$F17)),IF(secondaryInflationYear- Current_Fiscal_Year >=Y$8,ROUND($L17* $R17*$S17*((1 + Y$7)^Y$8),1),ROUND($L17* $R17*$S17*(((1+secondaryInflation)^(secondaryInflationYear-Current_Fiscal_Year)) * ((1+Y$7)^(Y$8-(secondaryInflationYear - Current_Fiscal_Year)))),1)),IF(AND($D17<>1,Y$8 > ($F17 - Current_Fiscal_Year),(Y$8 - (($F17 - Current_Fiscal_Year)+$G17*INT(((Y$8 - ($F17 - Current_Fiscal_Year)) / $G17))))/((($D17 - $E17)/($E17-1))+1) = INT((Y$8 - (($F17 - Current_Fiscal_Year)+$G17*INT(((Y$8 - ($F17 - Current_Fiscal_Year)) / $G17))))/((($D17 - $E17)/($E17-1))+1)), (Y$8 - (($F17 - Current_Fiscal_Year)+$G17*INT(((Y$8 - ($F17 - Current_Fiscal_Year)) / $G17)))) <$D17),IF(secondaryInflationYear- Current_Fiscal_Year >=Y$8,ROUND($L17* $R17*$S17*((1 + Y$7)^Y$8),1),ROUND($L17* $R17*$S17*(((1+secondaryInflation)^(secondaryInflationYear-Current_Fiscal_Year)) * ((1+Y$7)^(Y$8-(secondaryInflationYear - Current_Fiscal_Year)))),1)),"")),"") | Z17: =IFERROR(IF(OR(Z$8 = ($F17 - Current_Fiscal_Year),AND(MOD($F17-Z$9,$G17)=0,Z$9>$F17)),IF(secondaryInflationYear- Current_Fiscal_Year >=Z$8,ROUND($L17* $R17*$S17*((1 + Z$7)^Z$8),1),ROUND($L17* $R17*$S17*(((1+secondaryInflation)^(secondaryInflationYear-Current_Fiscal_Year)) * ((1+Z$7)^(Z$8-(secondaryInflationYear - Current_Fiscal_Year)))),1)),IF(AND($D17<>1,Z$8 > ($F17 - Current_Fiscal_Year),(Z$8 - (($F17 - Current_Fiscal_Year)+$G17*INT(((Z$8 - ($F17 - Current_Fiscal_Year)) / $G17))))/((($D17 - $E17)/($E17-1))+1) = INT((Z$8 - (($F17 - Current_Fiscal_Year)+$G17*INT(((Z$8 - ($F17 - Current_Fiscal_Year)) / $G17))))/((($D17 - $E17)/($E17-1))+1)), (Z$8 - (($F17 - Current_Fiscal_Year)+$G17*INT(((Z$8 - ($F17 - Current_Fiscal_Year)) / $G17)))) <$D17),IF(secondaryInflationYear- Current_Fiscal_Year >=Z$8,ROUND($L17* $R17*$S17*((1 + Z$7)^Z$8),1),ROUND($L17* $R17*$S17*(((1+secondaryInflation)^(secondaryInflationYear-Current_Fiscal_Year)) * ((1+Z$7)^(Z$8-(secondaryInflationYear - Current_Fiscal_Year)))),1)),"")),"") | AA17: =IFERROR(IF(OR(AA$8 = ($F17 - Current_Fiscal_Year),AND(MOD($F17-AA$9,$G17)=0,AA$9>$F17)),IF(secondaryInflationYear- Current_Fiscal_Year >=AA$8,ROUND($L17* $R17*$S17*((1 + AA$7)^AA$8),1),ROUND($L17* $R17*$S17*(((1+secondaryInflation)^(secondaryInflationYear-Current_Fiscal_Year)) * ((1+AA$7)^(AA$8-(secondaryInflationYear - Current_Fiscal_Year)))),1)),IF(AND($D17<>1,AA$8 > ($F17 - Current_Fiscal_Year),(AA$8 - (($F17 - Current_Fiscal_Year)+$G17*INT(((AA$8 - ($F17 - Current_Fiscal_Year)) / $G17))))/((($D17 - $E17)/($E17-1))+1) = INT((AA$8 - (($F17 - Current_Fiscal_Year)+$G17*INT(((AA$8 - ($F17 - Current_Fiscal_Year)) / $G17))))/((($D17 - $E17)/($E17-1))+1)), (AA$8 - (($F17 - Current_Fiscal_Year)+$G17*INT(((AA$8 - ($F17 - Current_Fiscal_Year)) / $G17)))) <$D17),IF(secondaryInflationYear- Current_Fiscal_Year >=AA$8,ROUND($L17* $R17*$S17*((1 + AA$7)^AA$8),1),ROUND($L17* $R17*$S17*(((1+secondaryInflation)^(secondaryInflationYear-Current_Fiscal_Year)) * ((1+AA$7)^(AA$8-(secondaryInflationYear - Current_Fiscal_Year)))),1)),"")),"") | AB17: =IFERROR(IF(OR(AB$8 = ($F17 - Current_Fiscal_Year),AND(MOD($F17-AB$9,$G17)=0,AB$9>$F17)),IF(secondaryInflationYear- Current_Fiscal_Year >=AB$8,ROUND($L17* $R17*$S17*((1 + AB$7)^AB$8),1),ROUND($L17* $R17*$S17*(((1+secondaryInflation)^(secondaryInflationYear-Current_Fiscal_Year)) * ((1+AB$7)^(AB$8-(secondaryInflationYear - Current_Fiscal_Year)))),1)),IF(AND($D17<>1,AB$8 > ($F17 - Current_Fiscal_Year),(AB$8 - (($F17 - Current_Fiscal_Year)+$G17*INT(((AB$8 - ($F17 - Current_Fiscal_Year)) / $G17))))/((($D17 - $E17)/($E17-1))+1) = INT((AB$8 - (($F17 - Current_Fiscal_Year)+$G17*INT(((AB$8 - ($F17 - Current_Fiscal_Year)) / $G17))))/((($D17 - $E17)/($E17-1))+1)), (AB$8 - (($F17 - Current_Fiscal_Year)+$G17*INT(((AB$8 - ($F17 - Current_Fiscal_Year)) / $G17)))) <$D17),IF(secondaryInflationYear- Current_Fiscal_Year >=AB$8,ROUND($L17* $R17*$S17*((1 + AB$7)^AB$8),1),ROUND($L17* $R17*$S17*(((1+secondaryInflation)^(secondaryInflationYear-Current_Fiscal_Year)) * ((1+AB$7)^(AB$8-(secondaryInflationYear - Current_Fiscal_Year)))),1)),"")),"") | AC17: =IFERROR(IF(OR(AC$8 = ($F17 - Current_Fiscal_Year),AND(MOD($F17-AC$9,$G17)=0,AC$9>$F17)),IF(secondaryInflationYear- Current_Fiscal_Year >=AC$8,ROUND($L17* $R17*$S17*((1 + AC$7)^AC$8),1),ROUND($L17* $R17*$S17*(((1+secondaryInflation)^(secondaryInflationYear-Current_Fiscal_Year)) * ((1+AC$7)^(AC$8-(secondaryInflationYear - Current_Fiscal_Year)))),1)),IF(AND($D17<>1,AC$8 > ($F17 - Current_Fiscal_Year),(AC$8 - (($F17 - Current_Fiscal_Year)+$G17*INT(((AC$8 - ($F17 - Current_Fiscal_Year)) / $G17))))/((($D17 - $E17)/($E17-1))+1) = INT((AC$8 - (($F17 - Current_Fiscal_Year)+$G17*INT(((AC$8 - ($F17 - Current_Fiscal_Year)) / $G17))))/((($D17 - $E17)/($E17-1))+1)), (AC$8 - (($F17 - Current_Fiscal_Year)+$G17*INT(((AC$8 - ($F17 - Current_Fiscal_Year)) / $G17)))) <$D17),IF(secondaryInflationYear- Current_Fiscal_Year >=AC$8,ROUND($L17* $R17*$S17*((1 + AC$7)^AC$8),1),ROUND($L17* $R17*$S17*(((1+secondaryInflation)^(secondaryInflationYear-Current_Fiscal_Year)) * ((1+AC$7)^(AC$8-(secondaryInflationYear - Current_Fiscal_Year)))),1)),"")),"") | AD17: =IFERROR(IF(OR(AD$8 = ($F17 - Current_Fiscal_Year),AND(MOD($F17-AD$9,$G17)=0,AD$9>$F17)),IF(secondaryInflationYear- Current_Fiscal_Year >=AD$8,ROUND($L17* $R17*$S17*((1 + AD$7)^AD$8),1),ROUND($L17* $R17*$S17*(((1+secondaryInflation)^(secondaryInflationYear-Current_Fiscal_Year)) * ((1+AD$7)^(AD$8-(secondaryInflationYear - Current_Fiscal_Year)))),1)),IF(AND($D17<>1,AD$8 > ($F17 - Current_Fiscal_Year),(AD$8 - (($F17 - Current_Fiscal_Year)+$G17*INT(((AD$8 - ($F17 - Current_Fiscal_Year)) / $G17))))/((($D17 - $E17)/($E17-1))+1) = INT((AD$8 - (($F17 - Current_Fiscal_Year)+$G17*INT(((AD$8 - ($F17 - Current_Fiscal_Year)) / $G17))))/((($D17 - $E17)/($E17-1))+1)), (AD$8 - (($F17 - Current_Fiscal_Year)+$G17*INT(((AD$8 - ($F17 - Current_Fiscal_Year)) / $G17)))) <$D17),IF(secondaryInflationYear- Current_Fiscal_Year >=AD$8,ROUND($L17* $R17*$S17*((1 + AD$7)^AD$8),1),ROUND($L17* $R17*$S17*(((1+secondaryInflation)^(secondaryInflationYear-Current_Fiscal_Year)) * ((1+AD$7)^(AD$8-(secondaryInflationYear - Current_Fiscal_Year)))),1)),"")),"") | AE17: =IFERROR(IF(OR(AE$8 = ($F17 - Current_Fiscal_Year),AND(MOD($F17-AE$9,$G17)=0,AE$9>$F17)),IF(secondaryInflationYear- Current_Fiscal_Year >=AE$8,ROUND($L17* $R17*$S17*((1 + AE$7)^AE$8),1),ROUND($L17* $R17*$S17*(((1+secondaryInflation)^(secondaryInflationYear-Current_Fiscal_Year)) * ((1+AE$7)^(AE$8-(secondaryInflationYear - Current_Fiscal_Year)))),1)),IF(AND($D17<>1,AE$8 > ($F17 - Current_Fiscal_Year),(AE$8 - (($F17 - Current_Fiscal_Year)+$G17*INT(((AE$8 - ($F17 - Current_Fiscal_Year)) / $G17))))/((($D17 - $E17)/($E17-1))+1) = INT((AE$8 - (($F17 - Current_Fiscal_Year)+$G17*INT(((AE$8 - ($F17 - Current_Fiscal_Year)) / $G17))))/((($D17 - $E17)/($E17-1))+1)), (AE$8 - (($F17 - Current_Fiscal_Year)+$G17*INT(((AE$8 - ($F17 - Current_Fiscal_Year)) / $G17)))) <$D17),IF(secondaryInflationYear- Current_Fiscal_Year >=AE$8,ROUND($L17* $R17*$S17*((1 + AE$7)^AE$8),1),ROUND($L17* $R17*$S17*(((1+secondaryInflation)^(secondaryInflationYear-Current_Fiscal_Year)) * ((1+AE$7)^(AE$8-(secondaryInflationYear - Current_Fiscal_Year)))),1)),"")),"") | ... BB17: =IFERROR(IF(OR(BB$8 = ($F17 - Current_Fiscal_Year),AND(MOD($F17-BB$9,$G17)=0,BB$9>$F17)),IF(secondaryInflationYear- Current_Fiscal_Year >=BB$8,ROUND($L17* $R17*$S17*((1 + BB$7)^BB$8),1),ROUND($L17* $R17*$S17*(((1+secondaryInflation)^(secondaryInflationYear-Current_Fiscal_Year)) * ((1+BB$7)^(BB$8-(secondaryInflationYear - Current_Fiscal_Year)))),1)),IF(AND($D17<>1,BB$8 > ($F17 - Current_Fiscal_Year),(BB$8 - (($F17 - Current_Fiscal_Year)+$G17*INT(((BB$8 - ($F17 - Current_Fiscal_Year)) / $G17))))/((($D17 - $E17)/($E17-1))+1) = INT((BB$8 - (($F17 - Current_Fiscal_Year)+$G17*INT(((BB$8 - ($F17 - Current_Fiscal_Year)) / $G17))))/((($D17 - $E17)/($E17-1))+1)), (BB$8 - (($F17 - Current_Fiscal_Year)+$G17*INT(((BB$8 - ($F17 - Current_Fiscal_Year)) / $G17)))) <$D17),IF(secondaryInflationYear- Current_Fiscal_Year >=BB$8,ROUND($L17* $R17*$S17*((1 + BB$7)^BB$8),1),ROUND($L17* $R17*$S17*(((1+secondaryInflation)^(secondaryInflationYear-Current_Fiscal_Year)) * ((1+BB$7)^(BB$8-(secondaryInflationYear - Current_Fiscal_Year)))),1)),"")),"")
A18: =IF(OFFSET($B18,IF(AND($K18=0,NOT(ISBLANK($K18))),-4,-3),-1)=0,1,0) -> 1 | B18: 1 | C18: 1 | D18: =(($E18-1)*$C18)+1 -> 2 | E18: 2 | F18: 2028 | G18: 10 | H18: 0.01 | J18: 4.32 | K18: 8 | L18: =IF(M18="Allowance",1,ROUND(K18*B18/E18/H18,0)*H18) -> 4 | M18: Each | N18: Gate Operators, Phased | O18: =IF($F18>$BB$9,$F18,Current_Fiscal_Year+MATCH(TRUE,INDEX($X18:$BB18<>"",0),0)-1) -> 2028 | P18: to 10 | Q18: =$O18-Current_Fiscal_Year&IF($B18<1," to "&Study_Length&"+",IF( $E18>1," to "&IF($O18-Current_Fiscal_Year+$D18-1>Study_Length,Study_Length&"+",$O18-Current_Fiscal_Year+$D18-1),"")) -> 2 to 3 | R18: 4900 | S18: 1 | T18: =$L18*$R18*$S18 -> 19600 | U18: =$K18*$R18*$S18 -> 39200 | V18: =SUM(OFFSET($X18,,,1,Study_Length+1)) -> 180178.85 | W18: =$V18/Total_Study_Expenditures -> 0.22457775 | X18: =IFERROR(IF(OR(X$8 = ($F18 - Current_Fiscal_Year),AND(MOD($F18-X$9,$G18)=0,X$9>$F18)),IF(secondaryInflationYear- Current_Fiscal_Year >=X$8,ROUND($L18* $R18*$S18*((1 + X$7)^X$8),1),ROUND($L18* $R18*$S18*(((1+secondaryInflation)^(secondaryInflationYear-Current_Fiscal_Year)) * ((1+X$7)^(X$8-(secondaryInflationYear - Current_Fiscal_Year)))),1)),IF(AND($D18<>1,X$8 > ($F18 - Current_Fiscal_Year),(X$8 - (($F18 - Current_Fiscal_Year)+$G18*INT(((X$8 - ($F18 - Current_Fiscal_Year)) / $G18))))/((($D18 - $E18)/($E18-1))+1) = INT((X$8 - (($F18 - Current_Fiscal_Year)+$G18*INT(((X$8 - ($F18 - Current_Fiscal_Year)) / $G18))))/((($D18 - $E18)/($E18-1))+1)), (X$8 - (($F18 - Current_Fiscal_Year)+$G18*INT(((X$8 - ($F18 - Current_Fiscal_Year)) / $G18)))) <$D18),IF(secondaryInflationYear- Current_Fiscal_Year >=X$8,ROUND($L18* $R18*$S18*((1 + X$7)^X$8),1),ROUND($L18* $R18*$S18*(((1+secondaryInflation)^(secondaryInflationYear-Current_Fiscal_Year)) * ((1+X$7)^(X$8-(secondaryInflationYear - Current_Fiscal_Year)))),1)),"")),"") | Y18: =IFERROR(IF(OR(Y$8 = ($F18 - Current_Fiscal_Year),AND(MOD($F18-Y$9,$G18)=0,Y$9>$F18)),IF(secondaryInflationYear- Current_Fiscal_Year >=Y$8,ROUND($L18* $R18*$S18*((1 + Y$7)^Y$8),1),ROUND($L18* $R18*$S18*(((1+secondaryInflation)^(secondaryInflationYear-Current_Fiscal_Year)) * ((1+Y$7)^(Y$8-(secondaryInflationYear - Current_Fiscal_Year)))),1)),IF(AND($D18<>1,Y$8 > ($F18 - Current_Fiscal_Year),(Y$8 - (($F18 - Current_Fiscal_Year)+$G18*INT(((Y$8 - ($F18 - Current_Fiscal_Year)) / $G18))))/((($D18 - $E18)/($E18-1))+1) = INT((Y$8 - (($F18 - Current_Fiscal_Year)+$G18*INT(((Y$8 - ($F18 - Current_Fiscal_Year)) / $G18))))/((($D18 - $E18)/($E18-1))+1)), (Y$8 - (($F18 - Current_Fiscal_Year)+$G18*INT(((Y$8 - ($F18 - Current_Fiscal_Year)) / $G18)))) <$D18),IF(secondaryInflationYear- Current_Fiscal_Year >=Y$8,ROUND($L18* $R18*$S18*((1 + Y$7)^Y$8),1),ROUND($L18* $R18*$S18*(((1+secondaryInflation)^(secondaryInflationYear-Current_Fiscal_Year)) * ((1+Y$7)^(Y$8-(secondaryInflationYear - Current_Fiscal_Year)))),1)),"")),"") | Z18: =IFERROR(IF(OR(Z$8 = ($F18 - Current_Fiscal_Year),AND(MOD($F18-Z$9,$G18)=0,Z$9>$F18)),IF(secondaryInflationYear- Current_Fiscal_Year >=Z$8,ROUND($L18* $R18*$S18*((1 + Z$7)^Z$8),1),ROUND($L18* $R18*$S18*(((1+secondaryInflation)^(secondaryInflationYear-Current_Fiscal_Year)) * ((1+Z$7)^(Z$8-(secondaryInflationYear - Current_Fiscal_Year)))),1)),IF(AND($D18<>1,Z$8 > ($F18 - Current_Fiscal_Year),(Z$8 - (($F18 - Current_Fiscal_Year)+$G18*INT(((Z$8 - ($F18 - Current_Fiscal_Year)) / $G18))))/((($D18 - $E18)/($E18-1))+1) = INT((Z$8 - (($F18 - Current_Fiscal_Year)+$G18*INT(((Z$8 - ($F18 - Current_Fiscal_Year)) / $G18))))/((($D18 - $E18)/($E18-1))+1)), (Z$8 - (($F18 - Current_Fiscal_Year)+$G18*INT(((Z$8 - ($F18 - Current_Fiscal_Year)) / $G18)))) <$D18),IF(secondaryInflationYear- Current_Fiscal_Year >=Z$8,ROUND($L18* $R18*$S18*((1 + Z$7)^Z$8),1),ROUND($L18* $R18*$S18*(((1+secondaryInflation)^(secondaryInflationYear-Current_Fiscal_Year)) * ((1+Z$7)^(Z$8-(secondaryInflationYear - Current_Fiscal_Year)))),1)),"")),"") -> 20874.5 | AA18: =IFERROR(IFERROR(IF(OR(AA$8 = ($F18 - Current_Fiscal_Year),AND(MOD($F18-AA$9,$G18)=0,AA$9>$F18)),IF(secondaryInflationYear- Current_Fiscal_Year >=AA$8,ROUND($L18* $R18*$S18*((1 + AA$7)^AA$8),1),ROUND($L18* $R18*$S18*(((1+secondaryInflation)^(secondaryInflationYear-Current_Fiscal_Year)) * ((1+AA$7)^(AA$8-(secondaryInflationYear - Current_Fiscal_Year)))),1)),IF(AND($D18<>1,AA$8 > ($F18 - Current_Fiscal_Year),(AA$8 - (($F18 - Current_Fiscal_Year)+$G18*INT(((AA$8 - ($F18 - Current_Fiscal_Year)) / $G18))))/((($D18 - $E18)/($E18-1))+1) = INT((AA$8 - (($F18 - Current_Fiscal_Year)+$G18*INT(((AA$8 - ($F18 - Current_Fiscal_Year)) / $G18))))/((($D18 - $E18)/($E18-1))+1)), (AA$8 - (($F18 - Current_Fiscal_Year)+$G18*INT(((AA$8 - ($F18 - Current_Fiscal_Year)) / $G18)))) <$D18),IF(secondaryInflationYear- Current_Fiscal_Year >=AA$8,ROUND($L18* $R18*$S18*((1 + AA$7)^AA$8),1),ROUND($L18* $R18*$S18*(((1+secondaryInflation)^(secondaryInflationYear-Current_Fiscal_Year)) * ((1+AA$7)^(AA$8-(secondaryInflationYear - Current_Fiscal_Year)))),1)),"")),"")*0.999997679006615,"") -> 21542.45 | AB18: =IFERROR(IF(OR(AB$8 = ($F18 - Current_Fiscal_Year),AND(MOD($F18-AB$9,$G18)=0,AB$9>$F18)),IF(secondaryInflationYear- Current_Fiscal_Year >=AB$8,ROUND($L18* $R18*$S18*((1 + AB$7)^AB$8),1),ROUND($L18* $R18*$S18*(((1+secondaryInflation)^(secondaryInflationYear-Current_Fiscal_Year)) * ((1+AB$7)^(AB$8-(secondaryInflationYear - Current_Fiscal_Year)))),1)),IF(AND($D18<>1,AB$8 > ($F18 - Current_Fiscal_Year),(AB$8 - (($F18 - Current_Fiscal_Year)+$G18*INT(((AB$8 - ($F18 - Current_Fiscal_Year)) / $G18))))/((($D18 - $E18)/($E18-1))+1) = INT((AB$8 - (($F18 - Current_Fiscal_Year)+$G18*INT(((AB$8 - ($F18 - Current_Fiscal_Year)) / $G18))))/((($D18 - $E18)/($E18-1))+1)), (AB$8 - (($F18 - Current_Fiscal_Year)+$G18*INT(((AB$8 - ($F18 - Current_Fiscal_Year)) / $G18)))) <$D18),IF(secondaryInflationYear- Current_Fiscal_Year >=AB$8,ROUND($L18* $R18*$S18*((1 + AB$7)^AB$8),1),ROUND($L18* $R18*$S18*(((1+secondaryInflation)^(secondaryInflationYear-Current_Fiscal_Year)) * ((1+AB$7)^(AB$8-(secondaryInflationYear - Current_Fiscal_Year)))),1)),"")),"") | AC18: =IFERROR(IF(OR(AC$8 = ($F18 - Current_Fiscal_Year),AND(MOD($F18-AC$9,$G18)=0,AC$9>$F18)),IF(secondaryInflationYear- Current_Fiscal_Year >=AC$8,ROUND($L18* $R18*$S18*((1 + AC$7)^AC$8),1),ROUND($L18* $R18*$S18*(((1+secondaryInflation)^(secondaryInflationYear-Current_Fiscal_Year)) * ((1+AC$7)^(AC$8-(secondaryInflationYear - Current_Fiscal_Year)))),1)),IF(AND($D18<>1,AC$8 > ($F18 - Current_Fiscal_Year),(AC$8 - (($F18 - Current_Fiscal_Year)+$G18*INT(((AC$8 - ($F18 - Current_Fiscal_Year)) / $G18))))/((($D18 - $E18)/($E18-1))+1) = INT((AC$8 - (($F18 - Current_Fiscal_Year)+$G18*INT(((AC$8 - ($F18 - Current_Fiscal_Year)) / $G18))))/((($D18 - $E18)/($E18-1))+1)), (AC$8 - (($F18 - Current_Fiscal_Year)+$G18*INT(((AC$8 - ($F18 - Current_Fiscal_Year)) / $G18)))) <$D18),IF(secondaryInflationYear- Current_Fiscal_Year >=AC$8,ROUND($L18* $R18*$S18*((1 + AC$7)^AC$8),1),ROUND($L18* $R18*$S18*(((1+secondaryInflation)^(secondaryInflationYear-Current_Fiscal_Year)) * ((1+AC$7)^(AC$8-(secondaryInflationYear - Current_Fiscal_Year)))),1)),"")),"") | AD18: =IFERROR(IF(OR(AD$8 = ($F18 - Current_Fiscal_Year),AND(MOD($F18-AD$9,$G18)=0,AD$9>$F18)),IF(secondaryInflationYear- Current_Fiscal_Year >=AD$8,ROUND($L18* $R18*$S18*((1 + AD$7)^AD$8),1),ROUND($L18* $R18*$S18*(((1+secondaryInflation)^(secondaryInflationYear-Current_Fiscal_Year)) * ((1+AD$7)^(AD$8-(secondaryInflationYear - Current_Fiscal_Year)))),1)),IF(AND($D18<>1,AD$8 > ($F18 - Current_Fiscal_Year),(AD$8 - (($F18 - Current_Fiscal_Year)+$G18*INT(((AD$8 - ($F18 - Current_Fiscal_Year)) / $G18))))/((($D18 - $E18)/($E18-1))+1) = INT((AD$8 - (($F18 - Current_Fiscal_Year)+$G18*INT(((AD$8 - ($F18 - Current_Fiscal_Year)) / $G18))))/((($D18 - $E18)/($E18-1))+1)), (AD$8 - (($F18 - Current_Fiscal_Year)+$G18*INT(((AD$8 - ($F18 - Current_Fiscal_Year)) / $G18)))) <$D18),IF(secondaryInflationYear- Current_Fiscal_Year >=AD$8,ROUND($L18* $R18*$S18*((1 + AD$7)^AD$8),1),ROUND($L18* $R18*$S18*(((1+secondaryInflation)^(secondaryInflationYear-Current_Fiscal_Year)) * ((1+AD$7)^(AD$8-(secondaryInflationYear - Current_Fiscal_Year)))),1)),"")),"") | AE18: =IFERROR(IF(OR(AE$8 = ($F18 - Current_Fiscal_Year),AND(MOD($F18-AE$9,$G18)=0,AE$9>$F18)),IF(secondaryInflationYear- Current_Fiscal_Year >=AE$8,ROUND($L18* $R18*$S18*((1 + AE$7)^AE$8),1),ROUND($L18* $R18*$S18*(((1+secondaryInflation)^(secondaryInflationYear-Current_Fiscal_Year)) * ((1+AE$7)^(AE$8-(secondaryInflationYear - Current_Fiscal_Year)))),1)),IF(AND($D18<>1,AE$8 > ($F18 - Current_Fiscal_Year),(AE$8 - (($F18 - Current_Fiscal_Year)+$G18*INT(((AE$8 - ($F18 - Current_Fiscal_Year)) / $G18))))/((($D18 - $E18)/($E18-1))+1) = INT((AE$8 - (($F18 - Current_Fiscal_Year)+$G18*INT(((AE$8 - ($F18 - Current_Fiscal_Year)) / $G18))))/((($D18 - $E18)/($E18-1))+1)), (AE$8 - (($F18 - Current_Fiscal_Year)+$G18*INT(((AE$8 - ($F18 - Current_Fiscal_Year)) / $G18)))) <$D18),IF(secondaryInflationYear- Current_Fiscal_Year >=AE$8,ROUND($L18* $R18*$S18*((1 + AE$7)^AE$8),1),ROUND($L18* $R18*$S18*(((1+secondaryInflation)^(secondaryInflationYear-Current_Fiscal_Year)) * ((1+AE$7)^(AE$8-(secondaryInflationYear - Current_Fiscal_Year)))),1)),"")),"") | AF18: =IFERROR(IF(OR(AF$8 = ($F18 - Current_Fiscal_Year),AND(MOD($F18-AF$9,$G18)=0,AF$9>$F18)),IF(secondaryInflationYear- Current_Fiscal_Year >=AF$8,ROUND($L18* $R18*$S18*((1 + AF$7)^AF$8),1),ROUND($L18* $R18*$S18*(((1+secondaryInflation)^(secondaryInflationYear-Current_Fiscal_Year)) * ((1+AF$7)^(AF$8-(secondaryInflationYear - Current_Fiscal_Year)))),1)),IF(AND($D18<>1,AF$8 > ($F18 - Current_Fiscal_Year),(AF$8 - (($F18 - Current_Fiscal_Year)+$G18*INT(((AF$8 - ($F18 - Current_Fiscal_Year)) / $G18))))/((($D18 - $E18)/($E18-1))+1) = INT((AF$8 - (($F18 - Current_Fiscal_Year)+$G18*INT(((AF$8 - ($F18 - Current_Fiscal_Year)) / $G18))))/((($D18 - $E18)/($E18-1))+1)), (AF$8 - (($F18 - Current_Fiscal_Year)+$G18*INT(((AF$8 - ($F18 - Current_Fiscal_Year)) / $G18)))) <$D18),IF(secondaryInflationYear- Current_Fiscal_Year >=AF$8,ROUND($L18* $R18*$S18*((1 + AF$7)^AF$8),1),ROUND($L18* $R18*$S18*(((1+secondaryInflation)^(secondaryInflationYear-Current_Fiscal_Year)) * ((1+AF$7)^(AF$8-(secondaryInflationYear - Current_Fiscal_Year)))),1)),"")),"") | AG18: =IFERROR(IF(OR(AG$8 = ($F18 - Current_Fiscal_Year),AND(MOD($F18-AG$9,$G18)=0,AG$9>$F18)),IF(secondaryInflationYear- Current_Fiscal_Year >=AG$8,ROUND($L18* $R18*$S18*((1 + AG$7)^AG$8),1),ROUND($L18* $R18*$S18*(((1+secondaryInflation)^(secondaryInflationYear-Current_Fiscal_Year)) * ((1+AG$7)^(AG$8-(secondaryInflationYear - Current_Fiscal_Year)))),1)),IF(AND($D18<>1,AG$8 > ($F18 - Current_Fiscal_Year),(AG$8 - (($F18 - Current_Fiscal_Year)+$G18*INT(((AG$8 - ($F18 - Current_Fiscal_Year)) / $G18))))/((($D18 - $E18)/($E18-1))+1) = INT((AG$8 - (($F18 - Current_Fiscal_Year)+$G18*INT(((AG$8 - ($F18 - Current_Fiscal_Year)) / $G18))))/((($D18 - $E18)/($E18-1))+1)), (AG$8 - (($F18 - Current_Fiscal_Year)+$G18*INT(((AG$8 - ($F18 - Current_Fiscal_Year)) / $G18)))) <$D18),IF(secondaryInflationYear- Current_Fiscal_Year >=AG$8,ROUND($L18* $R18*$S18*((1 + AG$7)^AG$8),1),ROUND($L18* $R18*$S18*(((1+secondaryInflation)^(secondaryInflationYear-Current_Fiscal_Year)) * ((1+AG$7)^(AG$8-(secondaryInflationYear - Current_Fiscal_Year)))),1)),"")),"") | AH18: =IFERROR(IF(OR(AH$8 = ($F18 - Current_Fiscal_Year),AND(MOD($F18-AH$9,$G18)=0,AH$9>$F18)),IF(secondaryInflationYear- Current_Fiscal_Year >=AH$8,ROUND($L18* $R18*$S18*((1 + AH$7)^AH$8),1),ROUND($L18* $R18*$S18*(((1+secondaryInflation)^(secondaryInflationYear-Current_Fiscal_Year)) * ((1+AH$7)^(AH$8-(secondaryInflationYear - Current_Fiscal_Year)))),1)),IF(AND($D18<>1,AH$8 > ($F18 - Current_Fiscal_Year),(AH$8 - (($F18 - Current_Fiscal_Year)+$G18*INT(((AH$8 - ($F18 - Current_Fiscal_Year)) / $G18))))/((($D18 - $E18)/($E18-1))+1) = INT((AH$8 - (($F18 - Current_Fiscal_Year)+$G18*INT(((AH$8 - ($F18 - Current_Fiscal_Year)) / $G18))))/((($D18 - $E18)/($E18-1))+1)), (AH$8 - (($F18 - Current_Fiscal_Year)+$G18*INT(((AH$8 - ($F18 - Current_Fiscal_Year)) / $G18)))) <$D18),IF(secondaryInflationYear- Current_Fiscal_Year >=AH$8,ROUND($L18* $R18*$S18*((1 + AH$7)^AH$8),1),ROUND($L18* $R18*$S18*(((1+secondaryInflation)^(secondaryInflationYear-Current_Fiscal_Year)) * ((1+AH$7)^(AH$8-(secondaryInflationYear - Current_Fiscal_Year)))),1)),"")),"") | AI18: =IFERROR(IF(OR(AI$8 = ($F18 - Current_Fiscal_Year),AND(MOD($F18-AI$9,$G18)=0,AI$9>$F18)),IF(secondaryInflationYear- Current_Fiscal_Year >=AI$8,ROUND($L18* $R18*$S18*((1 + AI$7)^AI$8),1),ROUND($L18* $R18*$S18*(((1+secondaryInflation)^(secondaryInflationYear-Current_Fiscal_Year)) * ((1+AI$7)^(AI$8-(secondaryInflationYear - Current_Fiscal_Year)))),1)),IF(AND($D18<>1,AI$8 > ($F18 - Current_Fiscal_Year),(AI$8 - (($F18 - Current_Fiscal_Year)+$G18*INT(((AI$8 - ($F18 - Current_Fiscal_Year)) / $G18))))/((($D18 - $E18)/($E18-1))+1) = INT((AI$8 - (($F18 - Current_Fiscal_Year)+$G18*INT(((AI$8 - ($F18 - Current_Fiscal_Year)) / $G18))))/((($D18 - $E18)/($E18-1))+1)), (AI$8 - (($F18 - Current_Fiscal_Year)+$G18*INT(((AI$8 - ($F18 - Current_Fiscal_Year)) / $G18)))) <$D18),IF(secondaryInflationYear- Current_Fiscal_Year >=AI$8,ROUND($L18* $R18*$S18*((1 + AI$7)^AI$8),1),ROUND($L18* $R18*$S18*(((1+secondaryInflation)^(secondaryInflationYear-Current_Fiscal_Year)) * ((1+AI$7)^(AI$8-(secondaryInflationYear - Current_Fiscal_Year)))),1)),"")),"") | ... BB18: =IFERROR(IF(OR(BB$8 = ($F18 - Current_Fiscal_Year),AND(MOD($F18-BB$9,$G18)=0,BB$9>$F18)),IF(secondaryInflationYear- Current_Fiscal_Year >=BB$8,ROUND($L18* $R18*$S18*((1 + BB$7)^BB$8),1),ROUND($L18* $R18*$S18*(((1+secondaryInflation)^(secondaryInflationYear-Current_Fiscal_Year)) * ((1+BB$7)^(BB$8-(secondaryInflationYear - Current_Fiscal_Year)))),1)),IF(AND($D18<>1,BB$8 > ($F18 - Current_Fiscal_Year),(BB$8 - (($F18 - Current_Fiscal_Year)+$G18*INT(((BB$8 - ($F18 - Current_Fiscal_Year)) / $G18))))/((($D18 - $E18)/($E18-1))+1) = INT((BB$8 - (($F18 - Current_Fiscal_Year)+$G18*INT(((BB$8 - ($F18 - Current_Fiscal_Year)) / $G18))))/((($D18 - $E18)/($E18-1))+1)), (BB$8 - (($F18 - Current_Fiscal_Year)+$G18*INT(((BB$8 - ($F18 - Current_Fiscal_Year)) / $G18)))) <$D18),IF(secondaryInflationYear- Current_Fiscal_Year >=BB$8,ROUND($L18* $R18*$S18*((1 + BB$7)^BB$8),1),ROUND($L18* $R18*$S18*(((1+secondaryInflation)^(secondaryInflationYear-Current_Fiscal_Year)) * ((1+BB$7)^(BB$8-(secondaryInflationYear - Current_Fiscal_Year)))),1)),"")),"")
A19: =IF(OFFSET($B19,IF(AND($K19=0,NOT(ISBLANK($K19))),-4,-3),-1)=0,1,0) -> 1 | B19: 1 | C19: 1 | D19: =(($E19-1)*$C19)+1 -> 1 | E19: 1 | F19: 2038 | G19: 20 | H19: 0.01 | J19: 4.33 | K19: 4 | L19: =IF(M19="Allowance",1,ROUND(K19*B19/E19/H19,0)*H19) -> 4 | M19: Each | N19: Gates | O19: =IF($F19>$BB$9,$F19,Current_Fiscal_Year+MATCH(TRUE,INDEX($X19:$BB19<>"",0),0)-1) -> 2038 | P19: to 20 | Q19: =$O19-Current_Fiscal_Year&IF($B19<1," to "&Study_Length&"+",IF( $E19>1," to "&IF($O19-Current_Fiscal_Year+$D19-1>Study_Length,Study_Length&"+",$O19-Current_Fiscal_Year+$D19-1),"")) -> 12 | R19: 7800 | S19: 1 | T19: =$L19*$R19*$S19 -> 31200 | U19: =$K19*$R19*$S19 -> 31200 | V19: =SUM(OFFSET($X19,,,1,Study_Length+1)) -> 45531.4 | W19: =$V19/Total_Study_Expenditures -> 0.056751052 | X19: =IFERROR(IF(OR(X$8 = ($F19 - Current_Fiscal_Year),AND(MOD($F19-X$9,$G19)=0,X$9>$F19)),IF(secondaryInflationYear- Current_Fiscal_Year >=X$8,ROUND($L19* $R19*$S19*((1 + X$7)^X$8),1),ROUND($L19* $R19*$S19*(((1+secondaryInflation)^(secondaryInflationYear-Current_Fiscal_Year)) * ((1+X$7)^(X$8-(secondaryInflationYear - Current_Fiscal_Year)))),1)),IF(AND($D19<>1,X$8 > ($F19 - Current_Fiscal_Year),(X$8 - (($F19 - Current_Fiscal_Year)+$G19*INT(((X$8 - ($F19 - Current_Fiscal_Year)) / $G19))))/((($D19 - $E19)/($E19-1))+1) = INT((X$8 - (($F19 - Current_Fiscal_Year)+$G19*INT(((X$8 - ($F19 - Current_Fiscal_Year)) / $G19))))/((($D19 - $E19)/($E19-1))+1)), (X$8 - (($F19 - Current_Fiscal_Year)+$G19*INT(((X$8 - ($F19 - Current_Fiscal_Year)) / $G19)))) <$D19),IF(secondaryInflationYear- Current_Fiscal_Year >=X$8,ROUND($L19* $R19*$S19*((1 + X$7)^X$8),1),ROUND($L19* $R19*$S19*(((1+secondaryInflation)^(secondaryInflationYear-Current_Fiscal_Year)) * ((1+X$7)^(X$8-(secondaryInflationYear - Current_Fiscal_Year)))),1)),"")),"") | Y19: =IFERROR(IF(OR(Y$8 = ($F19 - Current_Fiscal_Year),AND(MOD($F19-Y$9,$G19)=0,Y$9>$F19)),IF(secondaryInflationYear- Current_Fiscal_Year >=Y$8,ROUND($L19* $R19*$S19*((1 + Y$7)^Y$8),1),ROUND($L19* $R19*$S19*(((1+secondaryInflation)^(secondaryInflationYear-Current_Fiscal_Year)) * ((1+Y$7)^(Y$8-(secondaryInflationYear - Current_Fiscal_Year)))),1)),IF(AND($D19<>1,Y$8 > ($F19 - Current_Fiscal_Year),(Y$8 - (($F19 - Current_Fiscal_Year)+$G19*INT(((Y$8 - ($F19 - Current_Fiscal_Year)) / $G19))))/((($D19 - $E19)/($E19-1))+1) = INT((Y$8 - (($F19 - Current_Fiscal_Year)+$G19*INT(((Y$8 - ($F19 - Current_Fiscal_Year)) / $G19))))/((($D19 - $E19)/($E19-1))+1)), (Y$8 - (($F19 - Current_Fiscal_Year)+$G19*INT(((Y$8 - ($F19 - Current_Fiscal_Year)) / $G19)))) <$D19),IF(secondaryInflationYear- Current_Fiscal_Year >=Y$8,ROUND($L19* $R19*$S19*((1 + Y$7)^Y$8),1),ROUND($L19* $R19*$S19*(((1+secondaryInflation)^(secondaryInflationYear-Current_Fiscal_Year)) * ((1+Y$7)^(Y$8-(secondaryInflationYear - Current_Fiscal_Year)))),1)),"")),"") | Z19: =IFERROR(IF(OR(Z$8 = ($F19 - Current_Fiscal_Year),AND(MOD($F19-Z$9,$G19)=0,Z$9>$F19)),IF(secondaryInflationYear- Current_Fiscal_Year >=Z$8,ROUND($L19* $R19*$S19*((1 + Z$7)^Z$8),1),ROUND($L19* $R19*$S19*(((1+secondaryInflation)^(secondaryInflationYear-Current_Fiscal_Year)) * ((1+Z$7)^(Z$8-(secondaryInflationYear - Current_Fiscal_Year)))),1)),IF(AND($D19<>1,Z$8 > ($F19 - Current_Fiscal_Year),(Z$8 - (($F19 - Current_Fiscal_Year)+$G19*INT(((Z$8 - ($F19 - Current_Fiscal_Year)) / $G19))))/((($D19 - $E19)/($E19-1))+1) = INT((Z$8 - (($F19 - Current_Fiscal_Year)+$G19*INT(((Z$8 - ($F19 - Current_Fiscal_Year)) / $G19))))/((($D19 - $E19)/($E19-1))+1)), (Z$8 - (($F19 - Current_Fiscal_Year)+$G19*INT(((Z$8 - ($F19 - Current_Fiscal_Year)) / $G19)))) <$D19),IF(secondaryInflationYear- Current_Fiscal_Year >=Z$8,ROUND($L19* $R19*$S19*((1 + Z$7)^Z$8),1),ROUND($L19* $R19*$S19*(((1+secondaryInflation)^(secondaryInflationYear-Current_Fiscal_Year)) * ((1+Z$7)^(Z$8-(secondaryInflationYear - Current_Fiscal_Year)))),1)),"")),"") | AA19: =IFERROR(IF(OR(AA$8 = ($F19 - Current_Fiscal_Year),AND(MOD($F19-AA$9,$G19)=0,AA$9>$F19)),IF(secondaryInflationYear- Current_Fiscal_Year >=AA$8,ROUND($L19* $R19*$S19*((1 + AA$7)^AA$8),1),ROUND($L19* $R19*$S19*(((1+secondaryInflation)^(secondaryInflationYear-Current_Fiscal_Year)) * ((1+AA$7)^(AA$8-(secondaryInflationYear - Current_Fiscal_Year)))),1)),IF(AND($D19<>1,AA$8 > ($F19 - Current_Fiscal_Year),(AA$8 - (($F19 - Current_Fiscal_Year)+$G19*INT(((AA$8 - ($F19 - Current_Fiscal_Year)) / $G19))))/((($D19 - $E19)/($E19-1))+1) = INT((AA$8 - (($F19 - Current_Fiscal_Year)+$G19*INT(((AA$8 - ($F19 - Current_Fiscal_Year)) / $G19))))/((($D19 - $E19)/($E19-1))+1)), (AA$8 - (($F19 - Current_Fiscal_Year)+$G19*INT(((AA$8 - ($F19 - Current_Fiscal_Year)) / $G19)))) <$D19),IF(secondaryInflationYear- Current_Fiscal_Year >=AA$8,ROUND($L19* $R19*$S19*((1 + AA$7)^AA$8),1),ROUND($L19* $R19*$S19*(((1+secondaryInflation)^(secondaryInflationYear-Current_Fiscal_Year)) * ((1+AA$7)^(AA$8-(secondaryInflationYear - Current_Fiscal_Year)))),1)),"")),"") | AB19: =IFERROR(IF(OR(AB$8 = ($F19 - Current_Fiscal_Year),AND(MOD($F19-AB$9,$G19)=0,AB$9>$F19)),IF(secondaryInflationYear- Current_Fiscal_Year >=AB$8,ROUND($L19* $R19*$S19*((1 + AB$7)^AB$8),1),ROUND($L19* $R19*$S19*(((1+secondaryInflation)^(secondaryInflationYear-Current_Fiscal_Year)) * ((1+AB$7)^(AB$8-(secondaryInflationYear - Current_Fiscal_Year)))),1)),IF(AND($D19<>1,AB$8 > ($F19 - Current_Fiscal_Year),(AB$8 - (($F19 - Current_Fiscal_Year)+$G19*INT(((AB$8 - ($F19 - Current_Fiscal_Year)) / $G19))))/((($D19 - $E19)/($E19-1))+1) = INT((AB$8 - (($F19 - Current_Fiscal_Year)+$G19*INT(((AB$8 - ($F19 - Current_Fiscal_Year)) / $G19))))/((($D19 - $E19)/($E19-1))+1)), (AB$8 - (($F19 - Current_Fiscal_Year)+$G19*INT(((AB$8 - ($F19 - Current_Fiscal_Year)) / $G19)))) <$D19),IF(secondaryInflationYear- Current_Fiscal_Year >=AB$8,ROUND($L19* $R19*$S19*((1 + AB$7)^AB$8),1),ROUND($L19* $R19*$S19*(((1+secondaryInflation)^(secondaryInflationYear-Current_Fiscal_Year)) * ((1+AB$7)^(AB$8-(secondaryInflationYear - Current_Fiscal_Year)))),1)),"")),"") | AC19: =IFERROR(IF(OR(AC$8 = ($F19 - Current_Fiscal_Year),AND(MOD($F19-AC$9,$G19)=0,AC$9>$F19)),IF(secondaryInflationYear- Current_Fiscal_Year >=AC$8,ROUND($L19* $R19*$S19*((1 + AC$7)^AC$8),1),ROUND($L19* $R19*$S19*(((1+secondaryInflation)^(secondaryInflationYear-Current_Fiscal_Year)) * ((1+AC$7)^(AC$8-(secondaryInflationYear - Current_Fiscal_Year)))),1)),IF(AND($D19<>1,AC$8 > ($F19 - Current_Fiscal_Year),(AC$8 - (($F19 - Current_Fiscal_Year)+$G19*INT(((AC$8 - ($F19 - Current_Fiscal_Year)) / $G19))))/((($D19 - $E19)/($E19-1))+1) = INT((AC$8 - (($F19 - Current_Fiscal_Year)+$G19*INT(((AC$8 - ($F19 - Current_Fiscal_Year)) / $G19))))/((($D19 - $E19)/($E19-1))+1)), (AC$8 - (($F19 - Current_Fiscal_Year)+$G19*INT(((AC$8 - ($F19 - Current_Fiscal_Year)) / $G19)))) <$D19),IF(secondaryInflationYear- Current_Fiscal_Year >=AC$8,ROUND($L19* $R19*$S19*((1 + AC$7)^AC$8),1),ROUND($L19* $R19*$S19*(((1+secondaryInflation)^(secondaryInflationYear-Current_Fiscal_Year)) * ((1+AC$7)^(AC$8-(secondaryInflationYear - Current_Fiscal_Year)))),1)),"")),"") | AD19: =IFERROR(IF(OR(AD$8 = ($F19 - Current_Fiscal_Year),AND(MOD($F19-AD$9,$G19)=0,AD$9>$F19)),IF(secondaryInflationYear- Current_Fiscal_Year >=AD$8,ROUND($L19* $R19*$S19*((1 + AD$7)^AD$8),1),ROUND($L19* $R19*$S19*(((1+secondaryInflation)^(secondaryInflationYear-Current_Fiscal_Year)) * ((1+AD$7)^(AD$8-(secondaryInflationYear - Current_Fiscal_Year)))),1)),IF(AND($D19<>1,AD$8 > ($F19 - Current_Fiscal_Year),(AD$8 - (($F19 - Current_Fiscal_Year)+$G19*INT(((AD$8 - ($F19 - Current_Fiscal_Year)) / $G19))))/((($D19 - $E19)/($E19-1))+1) = INT((AD$8 - (($F19 - Current_Fiscal_Year)+$G19*INT(((AD$8 - ($F19 - Current_Fiscal_Year)) / $G19))))/((($D19 - $E19)/($E19-1))+1)), (AD$8 - (($F19 - Current_Fiscal_Year)+$G19*INT(((AD$8 - ($F19 - Current_Fiscal_Year)) / $G19)))) <$D19),IF(secondaryInflationYear- Current_Fiscal_Year >=AD$8,ROUND($L19* $R19*$S19*((1 + AD$7)^AD$8),1),ROUND($L19* $R19*$S19*(((1+secondaryInflation)^(secondaryInflationYear-Current_Fiscal_Year)) * ((1+AD$7)^(AD$8-(secondaryInflationYear - Current_Fiscal_Year)))),1)),"")),"") | AE19: =IFERROR(IF(OR(AE$8 = ($F19 - Current_Fiscal_Year),AND(MOD($F19-AE$9,$G19)=0,AE$9>$F19)),IF(secondaryInflationYear- Current_Fiscal_Year >=AE$8,ROUND($L19* $R19*$S19*((1 + AE$7)^AE$8),1),ROUND($L19* $R19*$S19*(((1+secondaryInflation)^(secondaryInflationYear-Current_Fiscal_Year)) * ((1+AE$7)^(AE$8-(secondaryInflationYear - Current_Fiscal_Year)))),1)),IF(AND($D19<>1,AE$8 > ($F19 - Current_Fiscal_Year),(AE$8 - (($F19 - Current_Fiscal_Year)+$G19*INT(((AE$8 - ($F19 - Current_Fiscal_Year)) / $G19))))/((($D19 - $E19)/($E19-1))+1) = INT((AE$8 - (($F19 - Current_Fiscal_Year)+$G19*INT(((AE$8 - ($F19 - Current_Fiscal_Year)) / $G19))))/((($D19 - $E19)/($E19-1))+1)), (AE$8 - (($F19 - Current_Fiscal_Year)+$G19*INT(((AE$8 - ($F19 - Current_Fiscal_Year)) / $G19)))) <$D19),IF(secondaryInflationYear- Current_Fiscal_Year >=AE$8,ROUND($L19* $R19*$S19*((1 + AE$7)^AE$8),1),ROUND($L19* $R19*$S19*(((1+secondaryInflation)^(secondaryInflationYear-Current_Fiscal_Year)) * ((1+AE$7)^(AE$8-(secondaryInflationYear - Current_Fiscal_Year)))),1)),"")),"") | ... BB19: =IFERROR(IF(OR(BB$8 = ($F19 - Current_Fiscal_Year),AND(MOD($F19-BB$9,$G19)=0,BB$9>$F19)),IF(secondaryInflationYear- Current_Fiscal_Year >=BB$8,ROUND($L19* $R19*$S19*((1 + BB$7)^BB$8),1),ROUND($L19* $R19*$S19*(((1+secondaryInflation)^(secondaryInflationYear-Current_Fiscal_Year)) * ((1+BB$7)^(BB$8-(secondaryInflationYear - Current_Fiscal_Year)))),1)),IF(AND($D19<>1,BB$8 > ($F19 - Current_Fiscal_Year),(BB$8 - (($F19 - Current_Fiscal_Year)+$G19*INT(((BB$8 - ($F19 - Current_Fiscal_Year)) / $G19))))/((($D19 - $E19)/($E19-1))+1) = INT((BB$8 - (($F19 - Current_Fiscal_Year)+$G19*INT(((BB$8 - ($F19 - Current_Fiscal_Year)) / $G19))))/((($D19 - $E19)/($E19-1))+1)), (BB$8 - (($F19 - Current_Fiscal_Year)+$G19*INT(((BB$8 - ($F19 - Current_Fiscal_Year)) / $G19)))) <$D19),IF(secondaryInflationYear- Current_Fiscal_Year >=BB$8,ROUND($L19* $R19*$S19*((1 + BB$7)^BB$8),1),ROUND($L19* $R19*$S19*(((1+secondaryInflation)^(secondaryInflationYear-Current_Fiscal_Year)) * ((1+BB$7)^(BB$8-(secondaryInflationYear - Current_Fiscal_Year)))),1)),"")),"")
A20: =IF(OFFSET($B20,IF(AND($K20=0,NOT(ISBLANK($K20))),-4,-3),-1)=0,1,0) -> 0 | B20: 1 | C20: 1 | D20: =(($E20-1)*$C20)+1 -> 1 | E20: 1 | F20: 2034 | G20: 20 | H20: 0.01 | J20: 4.8 | K20: 1 | L20: =IF(M20="Allowance",1,ROUND(K20*B20/E20/H20,0)*H20) -> 1 | M20: Allowance | N20: Signage, Monuments, Renovation | O20: =IF($F20>$BB$9,$F20,Current_Fiscal_Year+MATCH(TRUE,INDEX($X20:$BB20<>"",0),0)-1) -> 2034 | P20: 15 to 20 | Q20: =$O20-Current_Fiscal_Year&IF($B20<1," to "&Study_Length&"+",IF( $E20>1," to "&IF($O20-Current_Fiscal_Year+$D20-1>Study_Length,Study_Length&"+",$O20-Current_Fiscal_Year+$D20-1),"")) -> 8 | R20: 7200 | S20: 1 | T20: =$L20*$R20*$S20 -> 7200 | U20: =$K20*$R20*$S20 -> 7200 | V20: =SUM(OFFSET($X20,,,1,Study_Length+1)) -> 26656 | W20: =$V20/Total_Study_Expenditures -> 0.033224457 | X20: =IFERROR(IF(OR(X$8 = ($F20 - Current_Fiscal_Year),AND(MOD($F20-X$9,$G20)=0,X$9>$F20)),IF(secondaryInflationYear- Current_Fiscal_Year >=X$8,ROUND($L20* $R20*$S20*((1 + X$7)^X$8),1),ROUND($L20* $R20*$S20*(((1+secondaryInflation)^(secondaryInflationYear-Current_Fiscal_Year)) * ((1+X$7)^(X$8-(secondaryInflationYear - Current_Fiscal_Year)))),1)),IF(AND($D20<>1,X$8 > ($F20 - Current_Fiscal_Year),(X$8 - (($F20 - Current_Fiscal_Year)+$G20*INT(((X$8 - ($F20 - Current_Fiscal_Year)) / $G20))))/((($D20 - $E20)/($E20-1))+1) = INT((X$8 - (($F20 - Current_Fiscal_Year)+$G20*INT(((X$8 - ($F20 - Current_Fiscal_Year)) / $G20))))/((($D20 - $E20)/($E20-1))+1)), (X$8 - (($F20 - Current_Fiscal_Year)+$G20*INT(((X$8 - ($F20 - Current_Fiscal_Year)) / $G20)))) <$D20),IF(secondaryInflationYear- Current_Fiscal_Year >=X$8,ROUND($L20* $R20*$S20*((1 + X$7)^X$8),1),ROUND($L20* $R20*$S20*(((1+secondaryInflation)^(secondaryInflationYear-Current_Fiscal_Year)) * ((1+X$7)^(X$8-(secondaryInflationYear - Current_Fiscal_Year)))),1)),"")),"") | Y20: =IFERROR(IF(OR(Y$8 = ($F20 - Current_Fiscal_Year),AND(MOD($F20-Y$9,$G20)=0,Y$9>$F20)),IF(secondaryInflationYear- Current_Fiscal_Year >=Y$8,ROUND($L20* $R20*$S20*((1 + Y$7)^Y$8),1),ROUND($L20* $R20*$S20*(((1+secondaryInflation)^(secondaryInflationYear-Current_Fiscal_Year)) * ((1+Y$7)^(Y$8-(secondaryInflationYear - Current_Fiscal_Year)))),1)),IF(AND($D20<>1,Y$8 > ($F20 - Current_Fiscal_Year),(Y$8 - (($F20 - Current_Fiscal_Year)+$G20*INT(((Y$8 - ($F20 - Current_Fiscal_Year)) / $G20))))/((($D20 - $E20)/($E20-1))+1) = INT((Y$8 - (($F20 - Current_Fiscal_Year)+$G20*INT(((Y$8 - ($F20 - Current_Fiscal_Year)) / $G20))))/((($D20 - $E20)/($E20-1))+1)), (Y$8 - (($F20 - Current_Fiscal_Year)+$G20*INT(((Y$8 - ($F20 - Current_Fiscal_Year)) / $G20)))) <$D20),IF(secondaryInflationYear- Current_Fiscal_Year >=Y$8,ROUND($L20* $R20*$S20*((1 + Y$7)^Y$8),1),ROUND($L20* $R20*$S20*(((1+secondaryInflation)^(secondaryInflationYear-Current_Fiscal_Year)) * ((1+Y$7)^(Y$8-(secondaryInflationYear - Current_Fiscal_Year)))),1)),"")),"") | Z20: =IFERROR(IF(OR(Z$8 = ($F20 - Current_Fiscal_Year),AND(MOD($F20-Z$9,$G20)=0,Z$9>$F20)),IF(secondaryInflationYear- Current_Fiscal_Year >=Z$8,ROUND($L20* $R20*$S20*((1 + Z$7)^Z$8),1),ROUND($L20* $R20*$S20*(((1+secondaryInflation)^(secondaryInflationYear-Current_Fiscal_Year)) * ((1+Z$7)^(Z$8-(secondaryInflationYear - Current_Fiscal_Year)))),1)),IF(AND($D20<>1,Z$8 > ($F20 - Current_Fiscal_Year),(Z$8 - (($F20 - Current_Fiscal_Year)+$G20*INT(((Z$8 - ($F20 - Current_Fiscal_Year)) / $G20))))/((($D20 - $E20)/($E20-1))+1) = INT((Z$8 - (($F20 - Current_Fiscal_Year)+$G20*INT(((Z$8 - ($F20 - Current_Fiscal_Year)) / $G20))))/((($D20 - $E20)/($E20-1))+1)), (Z$8 - (($F20 - Current_Fiscal_Year)+$G20*INT(((Z$8 - ($F20 - Current_Fiscal_Year)) / $G20)))) <$D20),IF(secondaryInflationYear- Current_Fiscal_Year >=Z$8,ROUND($L20* $R20*$S20*((1 + Z$7)^Z$8),1),ROUND($L20* $R20*$S20*(((1+secondaryInflation)^(secondaryInflationYear-Current_Fiscal_Year)) * ((1+Z$7)^(Z$8-(secondaryInflationYear - Current_Fiscal_Year)))),1)),"")),"") | AA20: =IFERROR(IF(OR(AA$8 = ($F20 - Current_Fiscal_Year),AND(MOD($F20-AA$9,$G20)=0,AA$9>$F20)),IF(secondaryInflationYear- Current_Fiscal_Year >=AA$8,ROUND($L20* $R20*$S20*((1 + AA$7)^AA$8),1),ROUND($L20* $R20*$S20*(((1+secondaryInflation)^(secondaryInflationYear-Current_Fiscal_Year)) * ((1+AA$7)^(AA$8-(secondaryInflationYear - Current_Fiscal_Year)))),1)),IF(AND($D20<>1,AA$8 > ($F20 - Current_Fiscal_Year),(AA$8 - (($F20 - Current_Fiscal_Year)+$G20*INT(((AA$8 - ($F20 - Current_Fiscal_Year)) / $G20))))/((($D20 - $E20)/($E20-1))+1) = INT((AA$8 - (($F20 - Current_Fiscal_Year)+$G20*INT(((AA$8 - ($F20 - Current_Fiscal_Year)) / $G20))))/((($D20 - $E20)/($E20-1))+1)), (AA$8 - (($F20 - Current_Fiscal_Year)+$G20*INT(((AA$8 - ($F20 - Current_Fiscal_Year)) / $G20)))) <$D20),IF(secondaryInflationYear- Current_Fiscal_Year >=AA$8,ROUND($L20* $R20*$S20*((1 + AA$7)^AA$8),1),ROUND($L20* $R20*$S20*(((1+secondaryInflation)^(secondaryInflationYear-Current_Fiscal_Year)) * ((1+AA$7)^(AA$8-(secondaryInflationYear - Current_Fiscal_Year)))),1)),"")),"") | AB20: =IFERROR(IF(OR(AB$8 = ($F20 - Current_Fiscal_Year),AND(MOD($F20-AB$9,$G20)=0,AB$9>$F20)),IF(secondaryInflationYear- Current_Fiscal_Year >=AB$8,ROUND($L20* $R20*$S20*((1 + AB$7)^AB$8),1),ROUND($L20* $R20*$S20*(((1+secondaryInflation)^(secondaryInflationYear-Current_Fiscal_Year)) * ((1+AB$7)^(AB$8-(secondaryInflationYear - Current_Fiscal_Year)))),1)),IF(AND($D20<>1,AB$8 > ($F20 - Current_Fiscal_Year),(AB$8 - (($F20 - Current_Fiscal_Year)+$G20*INT(((AB$8 - ($F20 - Current_Fiscal_Year)) / $G20))))/((($D20 - $E20)/($E20-1))+1) = INT((AB$8 - (($F20 - Current_Fiscal_Year)+$G20*INT(((AB$8 - ($F20 - Current_Fiscal_Year)) / $G20))))/((($D20 - $E20)/($E20-1))+1)), (AB$8 - (($F20 - Current_Fiscal_Year)+$G20*INT(((AB$8 - ($F20 - Current_Fiscal_Year)) / $G20)))) <$D20),IF(secondaryInflationYear- Current_Fiscal_Year >=AB$8,ROUND($L20* $R20*$S20*((1 + AB$7)^AB$8),1),ROUND($L20* $R20*$S20*(((1+secondaryInflation)^(secondaryInflationYear-Current_Fiscal_Year)) * ((1+AB$7)^(AB$8-(secondaryInflationYear - Current_Fiscal_Year)))),1)),"")),"") | AC20: =IFERROR(IF(OR(AC$8 = ($F20 - Current_Fiscal_Year),AND(MOD($F20-AC$9,$G20)=0,AC$9>$F20)),IF(secondaryInflationYear- Current_Fiscal_Year >=AC$8,ROUND($L20* $R20*$S20*((1 + AC$7)^AC$8),1),ROUND($L20* $R20*$S20*(((1+secondaryInflation)^(secondaryInflationYear-Current_Fiscal_Year)) * ((1+AC$7)^(AC$8-(secondaryInflationYear - Current_Fiscal_Year)))),1)),IF(AND($D20<>1,AC$8 > ($F20 - Current_Fiscal_Year),(AC$8 - (($F20 - Current_Fiscal_Year)+$G20*INT(((AC$8 - ($F20 - Current_Fiscal_Year)) / $G20))))/((($D20 - $E20)/($E20-1))+1) = INT((AC$8 - (($F20 - Current_Fiscal_Year)+$G20*INT(((AC$8 - ($F20 - Current_Fiscal_Year)) / $G20))))/((($D20 - $E20)/($E20-1))+1)), (AC$8 - (($F20 - Current_Fiscal_Year)+$G20*INT(((AC$8 - ($F20 - Current_Fiscal_Year)) / $G20)))) <$D20),IF(secondaryInflationYear- Current_Fiscal_Year >=AC$8,ROUND($L20* $R20*$S20*((1 + AC$7)^AC$8),1),ROUND($L20* $R20*$S20*(((1+secondaryInflation)^(secondaryInflationYear-Current_Fiscal_Year)) * ((1+AC$7)^(AC$8-(secondaryInflationYear - Current_Fiscal_Year)))),1)),"")),"") | AD20: =IFERROR(IF(OR(AD$8 = ($F20 - Current_Fiscal_Year),AND(MOD($F20-AD$9,$G20)=0,AD$9>$F20)),IF(secondaryInflationYear- Current_Fiscal_Year >=AD$8,ROUND($L20* $R20*$S20*((1 + AD$7)^AD$8),1),ROUND($L20* $R20*$S20*(((1+secondaryInflation)^(secondaryInflationYear-Current_Fiscal_Year)) * ((1+AD$7)^(AD$8-(secondaryInflationYear - Current_Fiscal_Year)))),1)),IF(AND($D20<>1,AD$8 > ($F20 - Current_Fiscal_Year),(AD$8 - (($F20 - Current_Fiscal_Year)+$G20*INT(((AD$8 - ($F20 - Current_Fiscal_Year)) / $G20))))/((($D20 - $E20)/($E20-1))+1) = INT((AD$8 - (($F20 - Current_Fiscal_Year)+$G20*INT(((AD$8 - ($F20 - Current_Fiscal_Year)) / $G20))))/((($D20 - $E20)/($E20-1))+1)), (AD$8 - (($F20 - Current_Fiscal_Year)+$G20*INT(((AD$8 - ($F20 - Current_Fiscal_Year)) / $G20)))) <$D20),IF(secondaryInflationYear- Current_Fiscal_Year >=AD$8,ROUND($L20* $R20*$S20*((1 + AD$7)^AD$8),1),ROUND($L20* $R20*$S20*(((1+secondaryInflation)^(secondaryInflationYear-Current_Fiscal_Year)) * ((1+AD$7)^(AD$8-(secondaryInflationYear - Current_Fiscal_Year)))),1)),"")),"") | AE20: =IFERROR(IF(OR(AE$8 = ($F20 - Current_Fiscal_Year),AND(MOD($F20-AE$9,$G20)=0,AE$9>$F20)),IF(secondaryInflationYear- Current_Fiscal_Year >=AE$8,ROUND($L20* $R20*$S20*((1 + AE$7)^AE$8),1),ROUND($L20* $R20*$S20*(((1+secondaryInflation)^(secondaryInflationYear-Current_Fiscal_Year)) * ((1+AE$7)^(AE$8-(secondaryInflationYear - Current_Fiscal_Year)))),1)),IF(AND($D20<>1,AE$8 > ($F20 - Current_Fiscal_Year),(AE$8 - (($F20 - Current_Fiscal_Year)+$G20*INT(((AE$8 - ($F20 - Current_Fiscal_Year)) / $G20))))/((($D20 - $E20)/($E20-1))+1) = INT((AE$8 - (($F20 - Current_Fiscal_Year)+$G20*INT(((AE$8 - ($F20 - Current_Fiscal_Year)) / $G20))))/((($D20 - $E20)/($E20-1))+1)), (AE$8 - (($F20 - Current_Fiscal_Year)+$G20*INT(((AE$8 - ($F20 - Current_Fiscal_Year)) / $G20)))) <$D20),IF(secondaryInflationYear- Current_Fiscal_Year >=AE$8,ROUND($L20* $R20*$S20*((1 + AE$7)^AE$8),1),ROUND($L20* $R20*$S20*(((1+secondaryInflation)^(secondaryInflationYear-Current_Fiscal_Year)) * ((1+AE$7)^(AE$8-(secondaryInflationYear - Current_Fiscal_Year)))),1)),"")),"") | ... BB20: =IFERROR(IF(OR(BB$8 = ($F20 - Current_Fiscal_Year),AND(MOD($F20-BB$9,$G20)=0,BB$9>$F20)),IF(secondaryInflationYear- Current_Fiscal_Year >=BB$8,ROUND($L20* $R20*$S20*((1 + BB$7)^BB$8),1),ROUND($L20* $R20*$S20*(((1+secondaryInflation)^(secondaryInflationYear-Current_Fiscal_Year)) * ((1+BB$7)^(BB$8-(secondaryInflationYear - Current_Fiscal_Year)))),1)),IF(AND($D20<>1,BB$8 > ($F20 - Current_Fiscal_Year),(BB$8 - (($F20 - Current_Fiscal_Year)+$G20*INT(((BB$8 - ($F20 - Current_Fiscal_Year)) / $G20))))/((($D20 - $E20)/($E20-1))+1) = INT((BB$8 - (($F20 - Current_Fiscal_Year)+$G20*INT(((BB$8 - ($F20 - Current_Fiscal_Year)) / $G20))))/((($D20 - $E20)/($E20-1))+1)), (BB$8 - (($F20 - Current_Fiscal_Year)+$G20*INT(((BB$8 - ($F20 - Current_Fiscal_Year)) / $G20)))) <$D20),IF(secondaryInflationYear- Current_Fiscal_Year >=BB$8,ROUND($L20* $R20*$S20*((1 + BB$7)^BB$8),1),ROUND($L20* $R20*$S20*(((1+secondaryInflation)^(secondaryInflationYear-Current_Fiscal_Year)) * ((1+BB$7)^(BB$8-(secondaryInflationYear - Current_Fiscal_Year)))),1)),"")),"")
B21: - | C21: - | D21: - | E21: - | F21: - | G21: - | J21: - | K21: - | L21: - | M21: - | N21: - | O21: - | Q21: - | R21: - | S21: - | T21: - | V21: - | W21: - | X21: - | Y21: - | Z21: - | AA21: - | AB21: - | AC21: - | AD21: - | AE21: - | AF21: - | AG21: - | AH21: - | AI21: - | AJ21: - | AK21: - | AL21: - | AM21: - | AN21: - | AO21: - | AP21: - | AQ21: - | AR21: - | AS21: - | AT21: - | AU21: - | AV21: - | AW21: - | AX21: - | AY21: - | AZ21: - | BA21: -
N22: ="Anticipated Expenditures, By Year ("&Currency_Symbol&TEXT($V$22,"#,##0")&" over "&Study_Length&" years)" -> Anticipated Expenditures, By Year ($802,301 over 30 years) | V22: =SUM(OFFSET(X22,,,1,Study_Length+1)) -> 802300.55 | X22: =SUM(X10:X21) -> 0 | Y22: =SUM(Y10:Y21) -> 0 | Z22: =SUM(Z10:Z21) -> 20874.5 | AA22: =SUM(AA10:AA21) -> 26983.05 | AB22: =SUM(AB10:AB21) -> 0 | AC22: =SUM(AC10:AC21) -> 14749.2 | AD22: =SUM(AD10:AD21) -> 0 | AE22: =SUM(AE10:AE21) -> 0 | ... BB22: =SUM(BB10:BB21) -> 32416.2
A2008: =IF(OFFSET($B2008,IF(AND($K2008=0,NOT(ISBLANK($K2008))),-4,-3),-1)=0,1,0) -> 1
A2009: =IF(OFFSET($B2009,IF(AND($K2009=0,NOT(ISBLANK($K2009))),-4,-3),-1)=0,1,0) -> 1 | D2009: =(($E2009-1)*$C2009)+1 -> 1 | L2009: =IF(M2009="Allowance",1,ROUND(K2009*B2009/E2009/H2009,0)*H2009) -> #DIV/0! | O2009: =IF($F2009>$BB$9,$F2009,Current_Fiscal_Year+MATCH(TRUE,INDEX($X2009:$BB2009<>"",0),0)-1) -> #N/A | Q2009: =$O2009-Current_Fiscal_Year&IF($B2009<1," to "&Study_Length&"+",IF( $E2009>1," to "&IF($O2009-Current_Fiscal_Year+$D2009-1>Study_Length,Study_Length&"+",$O2009-Current_Fiscal_Year+$D2009-1),"")) -> #N/A | T2009: =$L2009*$R2009*$S2009 -> #DIV/0! | U2009: =$K2009*$R2009*$S2009 -> 0 | V2009: =SUM(OFFSET($X2009,,,1,Study_Length+1)) -> 0 | W2009: =$V2009/Total_Study_Expenditures -> 0 | X2009: =IFERROR(IF(OR(X$8 = ($F2009 - Current_Fiscal_Year),AND(MOD($F2009-X$9,$G2009)=0,X$9>$F2009)),IF(secondaryInflationYear- Current_Fiscal_Year >=X$8,ROUND($L2009* $R2009*$S2009*((1 + X$7)^X$8),1),ROUND($L2009* $R2009*$S2009*(((1+secondaryInflation)^(secondaryInflationYear-Current_Fiscal_Year)) * ((1+X$7)^(X$8-(secondaryInflationYear - Current_Fiscal_Year)))),1)),IF(AND($D2009<>1,X$8 > ($F2009 - Current_Fiscal_Year),(X$8 - (($F2009 - Current_Fiscal_Year)+$G2009*INT(((X$8 - ($F2009 - Current_Fiscal_Year)) / $G2009))))/((($D2009 - $E2009)/($E2009-1))+1) = INT((X$8 - (($F2009 - Current_Fiscal_Year)+$G2009*INT(((X$8 - ($F2009 - Current_Fiscal_Year)) / $G2009))))/((($D2009 - $E2009)/($E2009-1))+1)), (X$8 - (($F2009 - Current_Fiscal_Year)+$G2009*INT(((X$8 - ($F2009 - Current_Fiscal_Year)) / $G2009)))) <$D2009),IF(secondaryInflationYear- Current_Fiscal_Year >=X$8,ROUND($L2009* $R2009*$S2009*((1 + X$7)^X$8),1),ROUND($L2009* $R2009*$S2009*(((1+secondaryInflation)^(secondaryInflationYear-Current_Fiscal_Year)) * ((1+X$7)^(X$8-(secondaryInflationYear - Current_Fiscal_Year)))),1)),"")),"") | Y2009: =IFERROR(IF(OR(Y$8 = ($F2009 - Current_Fiscal_Year),AND(MOD($F2009-Y$9,$G2009)=0,Y$9>$F2009)),IF(secondaryInflationYear- Current_Fiscal_Year >=Y$8,ROUND($L2009* $R2009*$S2009*((1 + Y$7)^Y$8),1),ROUND($L2009* $R2009*$S2009*(((1+secondaryInflation)^(secondaryInflationYear-Current_Fiscal_Year)) * ((1+Y$7)^(Y$8-(secondaryInflationYear - Current_Fiscal_Year)))),1)),IF(AND($D2009<>1,Y$8 > ($F2009 - Current_Fiscal_Year),(Y$8 - (($F2009 - Current_Fiscal_Year)+$G2009*INT(((Y$8 - ($F2009 - Current_Fiscal_Year)) / $G2009))))/((($D2009 - $E2009)/($E2009-1))+1) = INT((Y$8 - (($F2009 - Current_Fiscal_Year)+$G2009*INT(((Y$8 - ($F2009 - Current_Fiscal_Year)) / $G2009))))/((($D2009 - $E2009)/($E2009-1))+1)), (Y$8 - (($F2009 - Current_Fiscal_Year)+$G2009*INT(((Y$8 - ($F2009 - Current_Fiscal_Year)) / $G2009)))) <$D2009),IF(secondaryInflationYear- Current_Fiscal_Year >=Y$8,ROUND($L2009* $R2009*$S2009*((1 + Y$7)^Y$8),1),ROUND($L2009* $R2009*$S2009*(((1+secondaryInflation)^(secondaryInflationYear-Current_Fiscal_Year)) * ((1+Y$7)^(Y$8-(secondaryInflationYear - Current_Fiscal_Year)))),1)),"")),"") | Z2009: =IFERROR(IF(OR(Z$8 = ($F2009 - Current_Fiscal_Year),AND(MOD($F2009-Z$9,$G2009)=0,Z$9>$F2009)),IF(secondaryInflationYear- Current_Fiscal_Year >=Z$8,ROUND($L2009* $R2009*$S2009*((1 + Z$7)^Z$8),1),ROUND($L2009* $R2009*$S2009*(((1+secondaryInflation)^(secondaryInflationYear-Current_Fiscal_Year)) * ((1+Z$7)^(Z$8-(secondaryInflationYear - Current_Fiscal_Year)))),1)),IF(AND($D2009<>1,Z$8 > ($F2009 - Current_Fiscal_Year),(Z$8 - (($F2009 - Current_Fiscal_Year)+$G2009*INT(((Z$8 - ($F2009 - Current_Fiscal_Year)) / $G2009))))/((($D2009 - $E2009)/($E2009-1))+1) = INT((Z$8 - (($F2009 - Current_Fiscal_Year)+$G2009*INT(((Z$8 - ($F2009 - Current_Fiscal_Year)) / $G2009))))/((($D2009 - $E2009)/($E2009-1))+1)), (Z$8 - (($F2009 - Current_Fiscal_Year)+$G2009*INT(((Z$8 - ($F2009 - Current_Fiscal_Year)) / $G2009)))) <$D2009),IF(secondaryInflationYear- Current_Fiscal_Year >=Z$8,ROUND($L2009* $R2009*$S2009*((1 + Z$7)^Z$8),1),ROUND($L2009* $R2009*$S2009*(((1+secondaryInflation)^(secondaryInflationYear-Current_Fiscal_Year)) * ((1+Z$7)^(Z$8-(secondaryInflationYear - Current_Fiscal_Year)))),1)),"")),"") | AA2009: =IFERROR(IF(OR(AA$8 = ($F2009 - Current_Fiscal_Year),AND(MOD($F2009-AA$9,$G2009)=0,AA$9>$F2009)),IF(secondaryInflationYear- Current_Fiscal_Year >=AA$8,ROUND($L2009* $R2009*$S2009*((1 + AA$7)^AA$8),1),ROUND($L2009* $R2009*$S2009*(((1+secondaryInflation)^(secondaryInflationYear-Current_Fiscal_Year)) * ((1+AA$7)^(AA$8-(secondaryInflationYear - Current_Fiscal_Year)))),1)),IF(AND($D2009<>1,AA$8 > ($F2009 - Current_Fiscal_Year),(AA$8 - (($F2009 - Current_Fiscal_Year)+$G2009*INT(((AA$8 - ($F2009 - Current_Fiscal_Year)) / $G2009))))/((($D2009 - $E2009)/($E2009-1))+1) = INT((AA$8 - (($F2009 - Current_Fiscal_Year)+$G2009*INT(((AA$8 - ($F2009 - Current_Fiscal_Year)) / $G2009))))/((($D2009 - $E2009)/($E2009-1))+1)), (AA$8 - (($F2009 - Current_Fiscal_Year)+$G2009*INT(((AA$8 - ($F2009 - Current_Fiscal_Year)) / $G2009)))) <$D2009),IF(secondaryInflationYear- Current_Fiscal_Year >=AA$8,ROUND($L2009* $R2009*$S2009*((1 + AA$7)^AA$8),1),ROUND($L2009* $R2009*$S2009*(((1+secondaryInflation)^(secondaryInflationYear-Current_Fiscal_Year)) * ((1+AA$7)^(AA$8-(secondaryInflationYear - Current_Fiscal_Year)))),1)),"")),"") | AB2009: =IFERROR(IF(OR(AB$8 = ($F2009 - Current_Fiscal_Year),AND(MOD($F2009-AB$9,$G2009)=0,AB$9>$F2009)),IF(secondaryInflationYear- Current_Fiscal_Year >=AB$8,ROUND($L2009* $R2009*$S2009*((1 + AB$7)^AB$8),1),ROUND($L2009* $R2009*$S2009*(((1+secondaryInflation)^(secondaryInflationYear-Current_Fiscal_Year)) * ((1+AB$7)^(AB$8-(secondaryInflationYear - Current_Fiscal_Year)))),1)),IF(AND($D2009<>1,AB$8 > ($F2009 - Current_Fiscal_Year),(AB$8 - (($F2009 - Current_Fiscal_Year)+$G2009*INT(((AB$8 - ($F2009 - Current_Fiscal_Year)) / $G2009))))/((($D2009 - $E2009)/($E2009-1))+1) = INT((AB$8 - (($F2009 - Current_Fiscal_Year)+$G2009*INT(((AB$8 - ($F2009 - Current_Fiscal_Year)) / $G2009))))/((($D2009 - $E2009)/($E2009-1))+1)), (AB$8 - (($F2009 - Current_Fiscal_Year)+$G2009*INT(((AB$8 - ($F2009 - Current_Fiscal_Year)) / $G2009)))) <$D2009),IF(secondaryInflationYear- Current_Fiscal_Year >=AB$8,ROUND($L2009* $R2009*$S2009*((1 + AB$7)^AB$8),1),ROUND($L2009* $R2009*$S2009*(((1+secondaryInflation)^(secondaryInflationYear-Current_Fiscal_Year)) * ((1+AB$7)^(AB$8-(secondaryInflationYear - Current_Fiscal_Year)))),1)),"")),"") | AC2009: =IFERROR(IF(OR(AC$8 = ($F2009 - Current_Fiscal_Year),AND(MOD($F2009-AC$9,$G2009)=0,AC$9>$F2009)),IF(secondaryInflationYear- Current_Fiscal_Year >=AC$8,ROUND($L2009* $R2009*$S2009*((1 + AC$7)^AC$8),1),ROUND($L2009* $R2009*$S2009*(((1+secondaryInflation)^(secondaryInflationYear-Current_Fiscal_Year)) * ((1+AC$7)^(AC$8-(secondaryInflationYear - Current_Fiscal_Year)))),1)),IF(AND($D2009<>1,AC$8 > ($F2009 - Current_Fiscal_Year),(AC$8 - (($F2009 - Current_Fiscal_Year)+$G2009*INT(((AC$8 - ($F2009 - Current_Fiscal_Year)) / $G2009))))/((($D2009 - $E2009)/($E2009-1))+1) = INT((AC$8 - (($F2009 - Current_Fiscal_Year)+$G2009*INT(((AC$8 - ($F2009 - Current_Fiscal_Year)) / $G2009))))/((($D2009 - $E2009)/($E2009-1))+1)), (AC$8 - (($F2009 - Current_Fiscal_Year)+$G2009*INT(((AC$8 - ($F2009 - Current_Fiscal_Year)) / $G2009)))) <$D2009),IF(secondaryInflationYear- Current_Fiscal_Year >=AC$8,ROUND($L2009* $R2009*$S2009*((1 + AC$7)^AC$8),1),ROUND($L2009* $R2009*$S2009*(((1+secondaryInflation)^(secondaryInflationYear-Current_Fiscal_Year)) * ((1+AC$7)^(AC$8-(secondaryInflationYear - Current_Fiscal_Year)))),1)),"")),"") | AD2009: =IFERROR(IF(OR(AD$8 = ($F2009 - Current_Fiscal_Year),AND(MOD($F2009-AD$9,$G2009)=0,AD$9>$F2009)),IF(secondaryInflationYear- Current_Fiscal_Year >=AD$8,ROUND($L2009* $R2009*$S2009*((1 + AD$7)^AD$8),1),ROUND($L2009* $R2009*$S2009*(((1+secondaryInflation)^(secondaryInflationYear-Current_Fiscal_Year)) * ((1+AD$7)^(AD$8-(secondaryInflationYear - Current_Fiscal_Year)))),1)),IF(AND($D2009<>1,AD$8 > ($F2009 - Current_Fiscal_Year),(AD$8 - (($F2009 - Current_Fiscal_Year)+$G2009*INT(((AD$8 - ($F2009 - Current_Fiscal_Year)) / $G2009))))/((($D2009 - $E2009)/($E2009-1))+1) = INT((AD$8 - (($F2009 - Current_Fiscal_Year)+$G2009*INT(((AD$8 - ($F2009 - Current_Fiscal_Year)) / $G2009))))/((($D2009 - $E2009)/($E2009-1))+1)), (AD$8 - (($F2009 - Current_Fiscal_Year)+$G2009*INT(((AD$8 - ($F2009 - Current_Fiscal_Year)) / $G2009)))) <$D2009),IF(secondaryInflationYear- Current_Fiscal_Year >=AD$8,ROUND($L2009* $R2009*$S2009*((1 + AD$7)^AD$8),1),ROUND($L2009* $R2009*$S2009*(((1+secondaryInflation)^(secondaryInflationYear-Current_Fiscal_Year)) * ((1+AD$7)^(AD$8-(secondaryInflationYear - Current_Fiscal_Year)))),1)),"")),"") | AE2009: =IFERROR(IF(OR(AE$8 = ($F2009 - Current_Fiscal_Year),AND(MOD($F2009-AE$9,$G2009)=0,AE$9>$F2009)),IF(secondaryInflationYear- Current_Fiscal_Year >=AE$8,ROUND($L2009* $R2009*$S2009*((1 + AE$7)^AE$8),1),ROUND($L2009* $R2009*$S2009*(((1+secondaryInflation)^(secondaryInflationYear-Current_Fiscal_Year)) * ((1+AE$7)^(AE$8-(secondaryInflationYear - Current_Fiscal_Year)))),1)),IF(AND($D2009<>1,AE$8 > ($F2009 - Current_Fiscal_Year),(AE$8 - (($F2009 - Current_Fiscal_Year)+$G2009*INT(((AE$8 - ($F2009 - Current_Fiscal_Year)) / $G2009))))/((($D2009 - $E2009)/($E2009-1))+1) = INT((AE$8 - (($F2009 - Current_Fiscal_Year)+$G2009*INT(((AE$8 - ($F2009 - Current_Fiscal_Year)) / $G2009))))/((($D2009 - $E2009)/($E2009-1))+1)), (AE$8 - (($F2009 - Current_Fiscal_Year)+$G2009*INT(((AE$8 - ($F2009 - Current_Fiscal_Year)) / $G2009)))) <$D2009),IF(secondaryInflationYear- Current_Fiscal_Year >=AE$8,ROUND($L2009* $R2009*$S2009*((1 + AE$7)^AE$8),1),ROUND($L2009* $R2009*$S2009*(((1+secondaryInflation)^(secondaryInflationYear-Current_Fiscal_Year)) * ((1+AE$7)^(AE$8-(secondaryInflationYear - Current_Fiscal_Year)))),1)),"")),"") | ... BB2009: =IFERROR(IF(OR(BB$8 = ($F2009 - Current_Fiscal_Year),AND(MOD($F2009-BB$9,$G2009)=0,BB$9>$F2009)),IF(secondaryInflationYear- Current_Fiscal_Year >=BB$8,ROUND($L2009* $R2009*$S2009*((1 + BB$7)^BB$8),1),ROUND($L2009* $R2009*$S2009*(((1+secondaryInflation)^(secondaryInflationYear-Current_Fiscal_Year)) * ((1+BB$7)^(BB$8-(secondaryInflationYear - Current_Fiscal_Year)))),1)),IF(AND($D2009<>1,BB$8 > ($F2009 - Current_Fiscal_Year),(BB$8 - (($F2009 - Current_Fiscal_Year)+$G2009*INT(((BB$8 - ($F2009 - Current_Fiscal_Year)) / $G2009))))/((($D2009 - $E2009)/($E2009-1))+1) = INT((BB$8 - (($F2009 - Current_Fiscal_Year)+$G2009*INT(((BB$8 - ($F2009 - Current_Fiscal_Year)) / $G2009))))/((($D2009 - $E2009)/($E2009-1))+1)), (BB$8 - (($F2009 - Current_Fiscal_Year)+$G2009*INT(((BB$8 - ($F2009 - Current_Fiscal_Year)) / $G2009)))) <$D2009),IF(secondaryInflationYear- Current_Fiscal_Year >=BB$8,ROUND($L2009* $R2009*$S2009*((1 + BB$7)^BB$8),1),ROUND($L2009* $R2009*$S2009*(((1+secondaryInflation)^(secondaryInflationYear-Current_Fiscal_Year)) * ((1+BB$7)^(BB$8-(secondaryInflationYear - Current_Fiscal_Year)))),1)),"")),"")

Sheet Funding Plan
C1: RESERVE FUNDING PLAN
C3: CASH FLOW ANALYSIS
C4: The Villas at Amarra Drive
A5: Unit | C5: Condominium Community, Inc. | F5: Individual Reserve Budgets & Cash Flows for the Next 30 Years
C6: Austin, TX | E6: =Current_Fiscal_Year -> 2026 | F6: =Current_Fiscal_Year+1 -> 2027 | G6: =F6+1 -> 2028 | H6: =G6+1 -> 2029 | I6: =H6+1 -> 2030 | J6: =I6+1 -> 2031 | K6: =J6+1 -> 2032 | L6: =K6+1 -> 2033 | M6: =L6+1 -> 2034 | N6: =M6+1 -> 2035 | ... T6: =S6+1 -> 2041
B7: Reserves at Beginning of Year | D7: (Note 1) | E7: =IF(Y56="Yes","N/A",Y54) -> 52679 | F7: =E16 -> 64313 | G7: =F16 -> 84789 | H7: =G16 -> 85197.5 | I7: =H16 -> 80050.45 | J7: =I16 -> 102659.45 | K7: =J16 -> 111531.25 | L7: =K16 -> 136184.25 | M7: =L16 -> 162037.25 | ... T7: =S16 -> 185113.05
C8: Recommended Reserve Contributions | E8: =Y60/Frequency_of_Contributions_Number*Funding_Current_Contributions -> 10571 | F8: =IF($Y$53-1=F6,$Y$58,ROUND(IF(AND(NOT(ISBLANK($R$22)),NOT(ISBLANK($R$21)),F6=$R$22),$R$21,IF(AND(NOT(ISBLANK($T$22)),NOT(ISBLANK($T$21)),F6=$T$22),$T$21,IF(AND(NOT(ISBLANK($J$21)),$Y$53=F6),$J$21,IF(AND(NOT(ISBLANK($L$22)),NOT(ISBLANK($L$21)),F6<$Y$53+$L$22),$L$21+INDIRECT("contributions_year"&F6-1-$Y$52)+IF(F6-1-$Y$52=0,(1-($Y$60/$Y$61))*$Y$57,0),IF(AND(NOT(ISBLANK($N$21)),NOT(ISBLANK($N$22)),NOT(ISBLANK($N$23)),$N$22<=F6,F6<=$N$23),$N$21,IF(AND(NOT(ISBLANK($P$21)),NOT(ISBLANK($P$22)),NOT(ISBLANK($P$23)),$P$22<=F6,F6<=$P$23),$P$21,(INDIRECT("contributions_year"&F6-1-$Y$52)+IF(F6-1-$Y$52=0,(1-($Y$60/$Y$61))*$Y$57,0))*(1+$Y$59)))))))/$Y$62,0)*$Y$62) -> 19000 | G8: =IF($Y$53-1=G6,$Y$58,ROUND(IF(AND(NOT(ISBLANK($R$22)),NOT(ISBLANK($R$21)),G6=$R$22),$R$21,IF(AND(NOT(ISBLANK($T$22)),NOT(ISBLANK($T$21)),G6=$T$22),$T$21,IF(AND(NOT(ISBLANK($J$21)),$Y$53=G6),$J$21,IF(AND(NOT(ISBLANK($L$22)),NOT(ISBLANK($L$21)),G6<$Y$53+$L$22),$L$21+INDIRECT("contributions_year"&G6-1-$Y$52)+IF(G6-1-$Y$52=0,(1-($Y$60/$Y$61))*$Y$57,0),IF(AND(NOT(ISBLANK($N$21)),NOT(ISBLANK($N$22)),NOT(ISBLANK($N$23)),$N$22<=G6,G6<=$N$23),$N$21,IF(AND(NOT(ISBLANK($P$21)),NOT(ISBLANK($P$22)),NOT(ISBLANK($P$23)),$P$22<=G6,G6<=$P$23),$P$21,(INDIRECT("contributions_year"&G6-1-$Y$52)+IF(G6-1-$Y$52=0,(1-($Y$60/$Y$61))*$Y$57,0))*(1+$Y$59)))))))/$Y$62,0)*$Y$62) -> 19600 | H8: =IF($Y$53-1=H6,$Y$58,ROUND(IF(AND(NOT(ISBLANK($R$22)),NOT(ISBLANK($R$21)),H6=$R$22),$R$21,IF(AND(NOT(ISBLANK($T$22)),NOT(ISBLANK($T$21)),H6=$T$22),$T$21,IF(AND(NOT(ISBLANK($J$21)),$Y$53=H6),$J$21,IF(AND(NOT(ISBLANK($L$22)),NOT(ISBLANK($L$21)),H6<$Y$53+$L$22),$L$21+INDIRECT("contributions_year"&H6-1-$Y$52)+IF(H6-1-$Y$52=0,(1-($Y$60/$Y$61))*$Y$57,0),IF(AND(NOT(ISBLANK($N$21)),NOT(ISBLANK($N$22)),NOT(ISBLANK($N$23)),$N$22<=H6,H6<=$N$23),$N$21,IF(AND(NOT(ISBLANK($P$21)),NOT(ISBLANK($P$22)),NOT(ISBLANK($P$23)),$P$22<=H6,H6<=$P$23),$P$21,(INDIRECT("contributions_year"&H6-1-$Y$52)+IF(H6-1-$Y$52=0,(1-($Y$60/$Y$61))*$Y$57,0))*(1+$Y$59)))))))/$Y$62,0)*$Y$62) -> 20200 | I8: =IF($Y$53-1=I6,$Y$58,ROUND(IF(AND(NOT(ISBLANK($R$22)),NOT(ISBLANK($R$21)),I6=$R$22),$R$21,IF(AND(NOT(ISBLANK($T$22)),NOT(ISBLANK($T$21)),I6=$T$22),$T$21,IF(AND(NOT(ISBLANK($J$21)),$Y$53=I6),$J$21,IF(AND(NOT(ISBLANK($L$22)),NOT(ISBLANK($L$21)),I6<$Y$53+$L$22),$L$21+INDIRECT("contributions_year"&I6-1-$Y$52)+IF(I6-1-$Y$52=0,(1-($Y$60/$Y$61))*$Y$57,0),IF(AND(NOT(ISBLANK($N$21)),NOT(ISBLANK($N$22)),NOT(ISBLANK($N$23)),$N$22<=I6,I6<=$N$23),$N$21,IF(AND(NOT(ISBLANK($P$21)),NOT(ISBLANK($P$22)),NOT(ISBLANK($P$23)),$P$22<=I6,I6<=$P$23),$P$21,(INDIRECT("contributions_year"&I6-1-$Y$52)+IF(I6-1-$Y$52=0,(1-($Y$60/$Y$61))*$Y$57,0))*(1+$Y$59)))))))/$Y$62,0)*$Y$62) -> 20800 | J8: =IF($Y$53-1=J6,$Y$58,ROUND(IF(AND(NOT(ISBLANK($R$22)),NOT(ISBLANK($R$21)),J6=$R$22),$R$21,IF(AND(NOT(ISBLANK($T$22)),NOT(ISBLANK($T$21)),J6=$T$22),$T$21,IF(AND(NOT(ISBLANK($J$21)),$Y$53=J6),$J$21,IF(AND(NOT(ISBLANK($L$22)),NOT(ISBLANK($L$21)),J6<$Y$53+$L$22),$L$21+INDIRECT("contributions_year"&J6-1-$Y$52)+IF(J6-1-$Y$52=0,(1-($Y$60/$Y$61))*$Y$57,0),IF(AND(NOT(ISBLANK($N$21)),NOT(ISBLANK($N$22)),NOT(ISBLANK($N$23)),$N$22<=J6,J6<=$N$23),$N$21,IF(AND(NOT(ISBLANK($P$21)),NOT(ISBLANK($P$22)),NOT(ISBLANK($P$23)),$P$22<=J6,J6<=$P$23),$P$21,(INDIRECT("contributions_year"&J6-1-$Y$52)+IF(J6-1-$Y$52=0,(1-($Y$60/$Y$61))*$Y$57,0))*(1+$Y$59)))))))/$Y$62,0)*$Y$62) -> 21500 | K8: =IF($Y$53-1=K6,$Y$58,ROUND(IF(AND(NOT(ISBLANK($R$22)),NOT(ISBLANK($R$21)),K6=$R$22),$R$21,IF(AND(NOT(ISBLANK($T$22)),NOT(ISBLANK($T$21)),K6=$T$22),$T$21,IF(AND(NOT(ISBLANK($J$21)),$Y$53=K6),$J$21,IF(AND(NOT(ISBLANK($L$22)),NOT(ISBLANK($L$21)),K6<$Y$53+$L$22),$L$21+INDIRECT("contributions_year"&K6-1-$Y$52)+IF(K6-1-$Y$52=0,(1-($Y$60/$Y$61))*$Y$57,0),IF(AND(NOT(ISBLANK($N$21)),NOT(ISBLANK($N$22)),NOT(ISBLANK($N$23)),$N$22<=K6,K6<=$N$23),$N$21,IF(AND(NOT(ISBLANK($P$21)),NOT(ISBLANK($P$22)),NOT(ISBLANK($P$23)),$P$22<=K6,K6<=$P$23),$P$21,(INDIRECT("contributions_year"&K6-1-$Y$52)+IF(K6-1-$Y$52=0,(1-($Y$60/$Y$61))*$Y$57,0))*(1+$Y$59)))))))/$Y$62,0)*$Y$62) -> 22200 | L8: =IF($Y$53-1=L6,$Y$58,ROUND(IF(AND(NOT(ISBLANK($R$22)),NOT(ISBLANK($R$21)),L6=$R$22),$R$21,IF(AND(NOT(ISBLANK($T$22)),NOT(ISBLANK($T$21)),L6=$T$22),$T$21,IF(AND(NOT(ISBLANK($J$21)),$Y$53=L6),$J$21,IF(AND(NOT(ISBLANK($L$22)),NOT(ISBLANK($L$21)),L6<$Y$53+$L$22),$L$21+INDIRECT("contributions_year"&L6-1-$Y$52)+IF(L6-1-$Y$52=0,(1-($Y$60/$Y$61))*$Y$57,0),IF(AND(NOT(ISBLANK($N$21)),NOT(ISBLANK($N$22)),NOT(ISBLANK($N$23)),$N$22<=L6,L6<=$N$23),$N$21,IF(AND(NOT(ISBLANK($P$21)),NOT(ISBLANK($P$22)),NOT(ISBLANK($P$23)),$P$22<=L6,L6<=$P$23),$P$21,(INDIRECT("contributions_year"&L6-1-$Y$52)+IF(L6-1-$Y$52=0,(1-($Y$60/$Y$61))*$Y$57,0))*(1+$Y$59)))))))/$Y$62,0)*$Y$62) -> 22900 | M8: =IF($Y$53-1=M6,$Y$58,ROUND(IF(AND(NOT(ISBLANK($R$22)),NOT(ISBLANK($R$21)),M6=$R$22),$R$21,IF(AND(NOT(ISBLANK($T$22)),NOT(ISBLANK($T$21)),M6=$T$22),$T$21,IF(AND(NOT(ISBLANK($J$21)),$Y$53=M6),$J$21,IF(AND(NOT(ISBLANK($L$22)),NOT(ISBLANK($L$21)),M6<$Y$53+$L$22),$L$21+INDIRECT("contributions_year"&M6-1-$Y$52)+IF(M6-1-$Y$52=0,(1-($Y$60/$Y$61))*$Y$57,0),IF(AND(NOT(ISBLANK($N$21)),NOT(ISBLANK($N$22)),NOT(ISBLANK($N$23)),$N$22<=M6,M6<=$N$23),$N$21,IF(AND(NOT(ISBLANK($P$21)),NOT(ISBLANK($P$22)),NOT(ISBLANK($P$23)),$P$22<=M6,M6<=$P$23),$P$21,(INDIRECT("contributions_year"&M6-1-$Y$52)+IF(M6-1-$Y$52=0,(1-($Y$60/$Y$61))*$Y$57,0))*(1+$Y$59)))))))/$Y$62,0)*$Y$62) -> 23600 | ... T8: =IF($Y$53-1=T6,$Y$58,ROUND(IF(AND(NOT(ISBLANK($R$22)),NOT(ISBLANK($R$21)),T6=$R$22),$R$21,IF(AND(NOT(ISBLANK($T$22)),NOT(ISBLANK($T$21)),T6=$T$22),$T$21,IF(AND(NOT(ISBLANK($J$21)),$Y$53=T6),$J$21,IF(AND(NOT(ISBLANK($L$22)),NOT(ISBLANK($L$21)),T6<$Y$53+$L$22),$L$21+INDIRECT("contributions_year"&T6-1-$Y$52)+IF(T6-1-$Y$52=0,(1-($Y$60/$Y$61))*$Y$57,0),IF(AND(NOT(ISBLANK($N$21)),NOT(ISBLANK($N$22)),NOT(ISBLANK($N$23)),$N$22<=T6,T6<=$N$23),$N$21,IF(AND(NOT(ISBLANK($P$21)),NOT(ISBLANK($P$22)),NOT(ISBLANK($P$23)),$P$22<=T6,T6<=$P$23),$P$21,(INDIRECT("contributions_year"&T6-1-$Y$52)+IF(T6-1-$Y$52=0,(1-($Y$60/$Y$61))*$Y$57,0))*(1+$Y$59)))))))/$Y$62,0)*$Y$62) -> 29500
C9: Additional Reserve Contributions
C10: Additional Assessment
B11: Total Recommended Reserve Contributions | D11: (Note 2) | E11: =IF(Y56="Yes","N/A",SUM(E8,E9,E10)) -> 10571 | F11: =SUM(F8,F9,F10) -> 19000 | G11: =SUM(G8,G9,G10) -> 19600 | H11: =SUM(H8,H9,H10) -> 20200 | I11: =SUM(I8,I9,I10) -> 20800 | J11: =SUM(J8,J9,J10) -> 21500 | K11: =SUM(K8,K9,K10) -> 22200 | L11: =SUM(L8,L9,L10) -> 22900 | M11: =SUM(M8,M9,M10) -> 23600 | ... T11: =SUM(T8,T9,T10) -> 29500
B12: Anticipated Interest Rate | E12: =IF(Y56="Yes","N/A",'Property Info'!$B$20) -> 0.02 | F12: ='Property Info'!$B$20 -> 0.02 | G12: ='Property Info'!$B$20 -> 0.02 | H12: ='Property Info'!$B$20 -> 0.02 | I12: ='Property Info'!$B$20 -> 0.02 | J12: ='Property Info'!$B$20 -> 0.02 | K12: ='Property Info'!$B$20 -> 0.02 | L12: ='Property Info'!$B$20 -> 0.02 | M12: ='Property Info'!$B$20 -> 0.02 | ... T12: ='Property Info'!$B$20 -> 0.02
B13: Estimated Interest Earned, During Year | D13: (Note 3) | E13: =IF($Y$56="Yes","N/A",ROUND((E7+E14/2+E11/2)*(E12*('Property Info'!$B$14/12)),0)) -> 1063 | F13: =ROUND(F12*(F7+F14/2+F11/2),0) -> 1476 | G13: =ROUND(G12*(G7+G14/2+G11/2),0) -> 1683 | H13: =ROUND(H12*(H7+H14/2+H11/2),0) -> 1636 | I13: =ROUND(I12*(I7+I14/2+I11/2),0) -> 1809 | J13: =ROUND(J12*(J7+J14/2+J11/2),0) -> 2121 | K13: =ROUND(K12*(K7+K14/2+K11/2),0) -> 2453 | L13: =ROUND(L12*(L7+L14/2+L11/2),0) -> 2953 | M13: =ROUND(M12*(M7+M14/2+M11/2),0) -> 3384 | ... T13: =ROUND(T12*(T7+T14/2+T11/2),0) -> 2034
B14: Anticipated Expenditures, By Year | E14: =IF(Y56="Yes","N/A",ExpenseTable303[[#Totals],[0]]) -> 0 | F14: =ExpenseTable303[[#Totals],[1]] -> 0 | G14: =ExpenseTable303[[#Totals],[2]] -> -20874.5 | H14: =ExpenseTable303[[#Totals],[3]] -> -26983.05 | I14: =ExpenseTable303[[#Totals],[4]] -> 0 | J14: =ExpenseTable303[[#Totals],[5]] -> -14749.2 | K14: =ExpenseTable303[[#Totals],[6]] -> 0 | L14: =ExpenseTable303[[#Totals],[7]] -> 0 | M14: =ExpenseTable303[[#Totals],[8]] -> -9263.4 | N14: =ExpenseTable303[[#Totals],[9]] -> 0 | O14: =ExpenseTable303[[#Totals],[10]] -> -70635.9 | P14: =ExpenseTable303[[#Totals],[11]] -> 0 | Q14: =ExpenseTable303[[#Totals],[12]] -> -74134.5 | R14: =ExpenseTable303[[#Totals],[13]] -> -29518.4 | S14: =ExpenseTable303[[#Totals],[14]] -> 0 | T14: =ExpenseTable303[[#Totals],[15]] -> -196325.5
E15: - | F15: - | G15: - | H15: - | I15: - | J15: - | K15: - | L15: - | M15: - | N15: - | O15: - | P15: - | Q15: - | R15: - | S15: - | T15: -
B16: Anticipated Reserves at Year End | E16: =IF(Y56="Yes",Funding_Balance,SUM(E7,E11,E13,E14)) -> 64313 | F16: =SUM(F7,F11,F13,F14) -> 84789 | G16: =SUM(G7,G11,G13,G14) -> 85197.5 | H16: =SUM(H7,H11,H13,H14) -> 80050.45 | I16: =SUM(I7,I11,I13,I14) -> 102659.45 | J16: =SUM(J7,J11,J13,J14) -> 111531.25 | K16: =SUM(K7,K11,K13,K14) -> 136184.25 | L16: =SUM(L7,L11,L13,L14) -> 162037.25 | M16: =SUM(M7,M11,M13,M14) -> 179757.85 | ... T16: =SUM(T7,T11,T13,T14) -> 20321.55
E17: =IFERROR(IF(-E16/E14<($Y$63+$AI$1004),"(NOTE 5)",""),"") | F17: =IFERROR(IF(-F16/F14<($Y$63+$AI$1004),"(NOTE 5)",""),"") | G17: =IFERROR(IF(-G16/G14<($Y$63+$AI$1004),"(NOTE 5)",""),"") | H17: =IFERROR(IF(-H16/H14<($Y$63+$AI$1004),"(NOTE 5)",""),"") | I17: =IFERROR(IF(-I16/I14<($Y$63+$AI$1004),"(NOTE 5)",""),"") | J17: =IFERROR(IF(-J16/J14<($Y$63+$AI$1004),"(NOTE 5)",""),"") | K17: =IFERROR(IF(-K16/K14<($Y$63+$AI$1004),"(NOTE 5)",""),"") | L17: =IFERROR(IF(-L16/L14<($Y$63+$AI$1004),"(NOTE 5)",""),"") | ... T17: =IFERROR(IF(-T16/T14<($Y$63+$AI$1004),"(NOTE 5)",""),"") -> (NOTE 5)
I20: Single Increase | K20: Phased Increases | M20: Flatline | O20: 2nd Flatline | Q20: Decrease | S20: 2nd Decrease
I21: Amount: | J21: 19000 | K21: Increase: | M21: Amount: | N21: 29500 | O21: Amount: | Q21: Amount: | S21: Amount:
K22: # Years: | M22: Begin Year: | N22: 2042 | O22: Begin Year: | Q22: Year: | S22: Year:
M23: End Year: | N23: 2047 | O23: End Year:
C26: (continued) | F26: Individual Reserve Budgets & Cash Flows for the Next 30 Years, Continued
F27: =T6+1 -> 2042 | G27: =F27+1 -> 2043 | H27: =G27+1 -> 2044 | I27: =H27+1 -> 2045 | J27: =I27+1 -> 2046 | K27: =J27+1 -> 2047 | L27: =K27+1 -> 2048 | M27: =L27+1 -> 2049 | N27: =M27+1 -> 2050 | ... T27: =S27+1 -> 2056
B28: Reserves at Beginning of Year | F28: =T16 -> 20321.55 | G28: =F37 -> 50522.55 | H28: =G37 -> 72787.65 | I28: =H37 -> 104038.65 | J28: =I37 -> 135914.65 | K28: =J37 -> 144534.35 | L28: =K37 -> 177220.35 | M28: =L37 -> 171883.25 | N28: =M37 -> 166182.95 | ... T28: =S37 -> 173512.65
C29: Recommended Reserve Contributions | F29: =IF($Y$53-1=F27,$Y$58,ROUND(IF(AND(NOT(ISBLANK($R$22)),NOT(ISBLANK($R$21)),F27=$R$22),$R$21,IF(AND(NOT(ISBLANK($T$22)),NOT(ISBLANK($T$21)),F27=$T$22),$T$21,IF(AND(NOT(ISBLANK($J$21)),$Y$53=F27),$J$21,IF(AND(NOT(ISBLANK($L$22)),NOT(ISBLANK($L$21)),F27<$Y$53+$L$22),$L$21+INDIRECT("contributions_year"&F27-1-$Y$52)+IF(F27-1-$Y$52=0,(1-($Y$60/$Y$61))*$Y$57,0),IF(AND(NOT(ISBLANK($N$21)),NOT(ISBLANK($N$22)),NOT(ISBLANK($N$23)),$N$22<=F27,F27<=$N$23),$N$21,IF(AND(NOT(ISBLANK($P$21)),NOT(ISBLANK($P$22)),NOT(ISBLANK($P$23)),$P$22<=F27,F27<=$P$23),$P$21,(INDIRECT("contributions_year"&F27-1-$Y$52)+IF(F27-1-$Y$52=0,(1-($Y$60/$Y$61))*$Y$57,0))*(1+$Y$59)))))))/$Y$62,0)*$Y$62) -> 29500 | G29: =IF($Y$53-1=G27,$Y$58,ROUND(IF(AND(NOT(ISBLANK($R$22)),NOT(ISBLANK($R$21)),G27=$R$22),$R$21,IF(AND(NOT(ISBLANK($T$22)),NOT(ISBLANK($T$21)),G27=$T$22),$T$21,IF(AND(NOT(ISBLANK($J$21)),$Y$53=G27),$J$21,IF(AND(NOT(ISBLANK($L$22)),NOT(ISBLANK($L$21)),G27<$Y$53+$L$22),$L$21+INDIRECT("contributions_year"&G27-1-$Y$52)+IF(G27-1-$Y$52=0,(1-($Y$60/$Y$61))*$Y$57,0),IF(AND(NOT(ISBLANK($N$21)),NOT(ISBLANK($N$22)),NOT(ISBLANK($N$23)),$N$22<=G27,G27<=$N$23),$N$21,IF(AND(NOT(ISBLANK($P$21)),NOT(ISBLANK($P$22)),NOT(ISBLANK($P$23)),$P$22<=G27,G27<=$P$23),$P$21,(INDIRECT("contributions_year"&G27-1-$Y$52)+IF(G27-1-$Y$52=0,(1-($Y$60/$Y$61))*$Y$57,0))*(1+$Y$59)))))))/$Y$62,0)*$Y$62) -> 29500 | H29: =IF($Y$53-1=H27,$Y$58,ROUND(IF(AND(NOT(ISBLANK($R$22)),NOT(ISBLANK($R$21)),H27=$R$22),$R$21,IF(AND(NOT(ISBLANK($T$22)),NOT(ISBLANK($T$21)),H27=$T$22),$T$21,IF(AND(NOT(ISBLANK($J$21)),$Y$53=H27),$J$21,IF(AND(NOT(ISBLANK($L$22)),NOT(ISBLANK($L$21)),H27<$Y$53+$L$22),$L$21+INDIRECT("contributions_year"&H27-1-$Y$52)+IF(H27-1-$Y$52=0,(1-($Y$60/$Y$61))*$Y$57,0),IF(AND(NOT(ISBLANK($N$21)),NOT(ISBLANK($N$22)),NOT(ISBLANK($N$23)),$N$22<=H27,H27<=$N$23),$N$21,IF(AND(NOT(ISBLANK($P$21)),NOT(ISBLANK($P$22)),NOT(ISBLANK($P$23)),$P$22<=H27,H27<=$P$23),$P$21,(INDIRECT("contributions_year"&H27-1-$Y$52)+IF(H27-1-$Y$52=0,(1-($Y$60/$Y$61))*$Y$57,0))*(1+$Y$59)))))))/$Y$62,0)*$Y$62) -> 29500 | I29: =IF($Y$53-1=I27,$Y$58,ROUND(IF(AND(NOT(ISBLANK($R$22)),NOT(ISBLANK($R$21)),I27=$R$22),$R$21,IF(AND(NOT(ISBLANK($T$22)),NOT(ISBLANK($T$21)),I27=$T$22),$T$21,IF(AND(NOT(ISBLANK($J$21)),$Y$53=I27),$J$21,IF(AND(NOT(ISBLANK($L$22)),NOT(ISBLANK($L$21)),I27<$Y$53+$L$22),$L$21+INDIRECT("contributions_year"&I27-1-$Y$52)+IF(I27-1-$Y$52=0,(1-($Y$60/$Y$61))*$Y$57,0),IF(AND(NOT(ISBLANK($N$21)),NOT(ISBLANK($N$22)),NOT(ISBLANK($N$23)),$N$22<=I27,I27<=$N$23),$N$21,IF(AND(NOT(ISBLANK($P$21)),NOT(ISBLANK($P$22)),NOT(ISBLANK($P$23)),$P$22<=I27,I27<=$P$23),$P$21,(INDIRECT("contributions_year"&I27-1-$Y$52)+IF(I27-1-$Y$52=0,(1-($Y$60/$Y$61))*$Y$57,0))*(1+$Y$59)))))))/$Y$62,0)*$Y$62) -> 29500 | J29: =IF($Y$53-1=J27,$Y$58,ROUND(IF(AND(NOT(ISBLANK($R$22)),NOT(ISBLANK($R$21)),J27=$R$22),$R$21,IF(AND(NOT(ISBLANK($T$22)),NOT(ISBLANK($T$21)),J27=$T$22),$T$21,IF(AND(NOT(ISBLANK($J$21)),$Y$53=J27),$J$21,IF(AND(NOT(ISBLANK($L$22)),NOT(ISBLANK($L$21)),J27<$Y$53+$L$22),$L$21+INDIRECT("contributions_year"&J27-1-$Y$52)+IF(J27-1-$Y$52=0,(1-($Y$60/$Y$61))*$Y$57,0),IF(AND(NOT(ISBLANK($N$21)),NOT(ISBLANK($N$22)),NOT(ISBLANK($N$23)),$N$22<=J27,J27<=$N$23),$N$21,IF(AND(NOT(ISBLANK($P$21)),NOT(ISBLANK($P$22)),NOT(ISBLANK($P$23)),$P$22<=J27,J27<=$P$23),$P$21,(INDIRECT("contributions_year"&J27-1-$Y$52)+IF(J27-1-$Y$52=0,(1-($Y$60/$Y$61))*$Y$57,0))*(1+$Y$59)))))))/$Y$62,0)*$Y$62) -> 29500 | K29: =IF($Y$53-1=K27,$Y$58,ROUND(IF(AND(NOT(ISBLANK($R$22)),NOT(ISBLANK($R$21)),K27=$R$22),$R$21,IF(AND(NOT(ISBLANK($T$22)),NOT(ISBLANK($T$21)),K27=$T$22),$T$21,IF(AND(NOT(ISBLANK($J$21)),$Y$53=K27),$J$21,IF(AND(NOT(ISBLANK($L$22)),NOT(ISBLANK($L$21)),K27<$Y$53+$L$22),$L$21+INDIRECT("contributions_year"&K27-1-$Y$52)+IF(K27-1-$Y$52=0,(1-($Y$60/$Y$61))*$Y$57,0),IF(AND(NOT(ISBLANK($N$21)),NOT(ISBLANK($N$22)),NOT(ISBLANK($N$23)),$N$22<=K27,K27<=$N$23),$N$21,IF(AND(NOT(ISBLANK($P$21)),NOT(ISBLANK($P$22)),NOT(ISBLANK($P$23)),$P$22<=K27,K27<=$P$23),$P$21,(INDIRECT("contributions_year"&K27-1-$Y$52)+IF(K27-1-$Y$52=0,(1-($Y$60/$Y$61))*$Y$57,0))*(1+$Y$59)))))))/$Y$62,0)*$Y$62) -> 29500 | L29: =IF($Y$53-1=L27,$Y$58,ROUND(IF(AND(NOT(ISBLANK($R$22)),NOT(ISBLANK($R$21)),L27=$R$22),$R$21,IF(AND(NOT(ISBLANK($T$22)),NOT(ISBLANK($T$21)),L27=$T$22),$T$21,IF(AND(NOT(ISBLANK($J$21)),$Y$53=L27),$J$21,IF(AND(NOT(ISBLANK($L$22)),NOT(ISBLANK($L$21)),L27<$Y$53+$L$22),$L$21+INDIRECT("contributions_year"&L27-1-$Y$52)+IF(L27-1-$Y$52=0,(1-($Y$60/$Y$61))*$Y$57,0),IF(AND(NOT(ISBLANK($N$21)),NOT(ISBLANK($N$22)),NOT(ISBLANK($N$23)),$N$22<=L27,L27<=$N$23),$N$21,IF(AND(NOT(ISBLANK($P$21)),NOT(ISBLANK($P$22)),NOT(ISBLANK($P$23)),$P$22<=L27,L27<=$P$23),$P$21,(INDIRECT("contributions_year"&L27-1-$Y$52)+IF(L27-1-$Y$52=0,(1-($Y$60/$Y$61))*$Y$57,0))*(1+$Y$59)))))))/$Y$62,0)*$Y$62) -> 30400 | M29: =IF($Y$53-1=M27,$Y$58,ROUND(IF(AND(NOT(ISBLANK($R$22)),NOT(ISBLANK($R$21)),M27=$R$22),$R$21,IF(AND(NOT(ISBLANK($T$22)),NOT(ISBLANK($T$21)),M27=$T$22),$T$21,IF(AND(NOT(ISBLANK($J$21)),$Y$53=M27),$J$21,IF(AND(NOT(ISBLANK($L$22)),NOT(ISBLANK($L$21)),M27<$Y$53+$L$22),$L$21+INDIRECT("contributions_year"&M27-1-$Y$52)+IF(M27-1-$Y$52=0,(1-($Y$60/$Y$61))*$Y$57,0),IF(AND(NOT(ISBLANK($N$21)),NOT(ISBLANK($N$22)),NOT(ISBLANK($N$23)),$N$22<=M27,M27<=$N$23),$N$21,IF(AND(NOT(ISBLANK($P$21)),NOT(ISBLANK($P$22)),NOT(ISBLANK($P$23)),$P$22<=M27,M27<=$P$23),$P$21,(INDIRECT("contributions_year"&M27-1-$Y$52)+IF(M27-1-$Y$52=0,(1-($Y$60/$Y$61))*$Y$57,0))*(1+$Y$59)))))))/$Y$62,0)*$Y$62) -> 31400 | ... T29: =IF($Y$53-1=T27,$Y$58,ROUND(IF(AND(NOT(ISBLANK($R$22)),NOT(ISBLANK($R$21)),T27=$R$22),$R$21,IF(AND(NOT(ISBLANK($T$22)),NOT(ISBLANK($T$21)),T27=$T$22),$T$21,IF(AND(NOT(ISBLANK($J$21)),$Y$53=T27),$J$21,IF(AND(NOT(ISBLANK($L$22)),NOT(ISBLANK($L$21)),T27<$Y$53+$L$22),$L$21+INDIRECT("contributions_year"&T27-1-$Y$52)+IF(T27-1-$Y$52=0,(1-($Y$60/$Y$61))*$Y$57,0),IF(AND(NOT(ISBLANK($N$21)),NOT(ISBLANK($N$22)),NOT(ISBLANK($N$23)),$N$22<=T27,T27<=$N$23),$N$21,IF(AND(NOT(ISBLANK($P$21)),NOT(ISBLANK($P$22)),NOT(ISBLANK($P$23)),$P$22<=T27,T27<=$P$23),$P$21,(INDIRECT("contributions_year"&T27-1-$Y$52)+IF(T27-1-$Y$52=0,(1-($Y$60/$Y$61))*$Y$57,0))*(1+$Y$59)))))))/$Y$62,0)*$Y$62) -> 39100
C30: Additional Reserve Contributions
C31: Additional Assessment
B32: Total Recommended Reserve Contributions | F32: =SUM(F29,F30,F31) -> 29500 | G32: =SUM(G29,G30,G31) -> 29500 | H32: =SUM(H29,H30,H31) -> 29500 | I32: =SUM(I29,I30,I31) -> 29500 | J32: =SUM(J29,J30,J31) -> 29500 | K32: =SUM(K29,K30,K31) -> 29500 | L32: =SUM(L29,L30,L31) -> 30400 | M32: =SUM(M29,M30,M31) -> 31400 | ... T32: =SUM(T29,T30,T31) -> 39100
B33: Anticipated Interest Rate | F33: ='Property Info'!$B$20 -> 0.02 | G33: ='Property Info'!$B$20 -> 0.02 | H33: ='Property Info'!$B$20 -> 0.02 | I33: ='Property Info'!$B$20 -> 0.02 | J33: ='Property Info'!$B$20 -> 0.02 | K33: ='Property Info'!$B$20 -> 0.02 | L33: ='Property Info'!$B$20 -> 0.02 | M33: ='Property Info'!$B$20 -> 0.02 | ... T33: ='Property Info'!$B$20 -> 0.02
B34: Estimated Interest Earned, During Year | F34: =ROUND(F33*(F28+F35/2+F32/2),0) -> 701 | G34: =ROUND(G33*(G28+G35/2+G32/2),0) -> 1221 | H34: =ROUND(H33*(H28+H35/2+H32/2),0) -> 1751 | I34: =ROUND(I33*(I28+I35/2+I32/2),0) -> 2376 | J34: =ROUND(J33*(J28+J35/2+J32/2),0) -> 2777 | K34: =ROUND(K33*(K28+K35/2+K32/2),0) -> 3186 | L34: =ROUND(L33*(L28+L35/2+L32/2),0) -> 3456 | M34: =ROUND(M33*(M28+M35/2+M32/2),0) -> 3347 | ... T34: =ROUND(T33*(T28+T35/2+T32/2),0) -> 3537
B35: Anticipated Expenditures, By Year | F35: =ExpenseTable303[[#Totals],[16]] -> 0 | G35: =ExpenseTable303[[#Totals],[17]] -> -8455.9 | H35: =ExpenseTable303[[#Totals],[18]] -> 0 | I35: =ExpenseTable303[[#Totals],[19]] -> 0 | J35: =ExpenseTable303[[#Totals],[20]] -> -23657.3 | K35: =ExpenseTable303[[#Totals],[21]] -> 0 | L35: =ExpenseTable303[[#Totals],[22]] -> -39193.1 | M35: =ExpenseTable303[[#Totals],[23]] -> -40447.3 | N35: =ExpenseTable303[[#Totals],[24]] -> -95835.2 | O35: =ExpenseTable303[[#Totals],[25]] -> -102418.5 | P35: =ExpenseTable303[[#Totals],[26]] -> 0 | Q35: =ExpenseTable303[[#Totals],[27]] -> 0 | R35: =ExpenseTable303[[#Totals],[28]] -> -17392.6 | S35: =ExpenseTable303[[#Totals],[29]] -> 0 | T35: =ExpenseTable303[[#Totals],[30]] -> -32416.2
F36: - | G36: - | H36: - | I36: - | J36: - | K36: - | L36: - | M36: - | N36: - | O36: - | P36: - | Q36: - | R36: - | S36: - | T36: -
B37: Anticipated Reserves at Year End | F37: =SUM(F28,F32,F34,F35) -> 50522.55 | G37: =SUM(G28,G32,G34,G35) -> 72787.65 | H37: =SUM(H28,H32,H34,H35) -> 104038.65 | I37: =SUM(I28,I32,I34,I35) -> 135914.65 | J37: =SUM(J28,J32,J34,J35) -> 144534.35 | K37: =SUM(K28,K32,K34,K35) -> 177220.35 | L37: =SUM(L28,L32,L34,L35) -> 171883.25 | M37: =SUM(M28,M32,M34,M35) -> 166182.95 | ... T37: =SUM(T28,T32,T34,T35) -> 183733.45
F38: =IFERROR(IF(-F37/F35<($Y$63+$AI$1004),"(NOTE 5)",""),"") | G38: =IFERROR(IF(-G37/G35<($Y$63+$AI$1004),"(NOTE 5)",""),"") | H38: =IFERROR(IF(-H37/H35<($Y$63+$AI$1004),"(NOTE 5)",""),"") | I38: =IFERROR(IF(-I37/I35<($Y$63+$AI$1004),"(NOTE 5)",""),"") | J38: =IFERROR(IF(-J37/J35<($Y$63+$AI$1004),"(NOTE 5)",""),"") | K38: =IFERROR(IF(-K37/K35<($Y$63+$AI$1004),"(NOTE 5)",""),"") | L38: =IFERROR(IF(-L37/L35<($Y$63+$AI$1004),"(NOTE 5)",""),"") | M38: =IFERROR(IF(-M37/M35<($Y$63+$AI$1004),"(NOTE 5)",""),"") | ... S38: =IFERROR(IF(-S37/S35<($Y$63+$AI$1004),"(NOTE 5)",""),"") | T38: =IFERROR(IF(-T37/T35<($Y$63+$AI$1004),"(NOTES 4&5)","(NOTE 4)"),"") -> (NOTE 4)
B43: Explanatory Notes:
A44: 1) | B44: Year 2026 starting reserves are as of January 31, 2026; FY2026 starts January 1, 2026 and ends December 31, 2026.
A45: 2) | B45: =IF(Remaining_Budgeted_Months=0,"",IF(Remaining_Budgeted_Months/Frequency_of_Contributions_Number=1,"Reserve Contributions for "&Current_Fiscal_Year&" are budgeted; ","Reserve Contributions for "&Current_Fiscal_Year&" are the remaining budgeted; "))&IF(First_Year_of_Recommendation=Current_Fiscal_Year+1,First_Year_of_Recommendation&" is the first year of recommended contributions.",Current_Fiscal_Year+1&" contributions are budgeted; "&First_Year_of_Recommendation&" is the first year of recommended contributions.") -> Reserve Contributions for 2026 are the remaining budgeted; 2027 is the first year of recommended contributions.
A46: 3) | B46: =[0]!Interest -> 0.02 | C46: ="is the estimated annual rate of return on invested reserves"&IF(Remaining_Budgeted_Months<12,CONCATENATE("; ",Current_Fiscal_Year," is a partial year of interest earned."),".") -> is the estimated annual rate of return on invested reserves; 2026 is a partial year of interest earned.
A47: 4) | B47: Accumulated year 2056 ending reserves consider the need to fund for subsequent repaving of the asphalt streets shortly after 2056, and the age, size, overall condition and complexity of the property.
A48: =IF(OR(COUNTIF(A1:T40,"(NOTE 5)")>0,COUNTIF(A1:T40,"(NOTES 4&5)")>0),"5)","") -> 5) | B48: =IF(OR(COUNTIF(A1:T40,"(NOTE 5)")>0,COUNTIF(A1:T40,"(NOTES 4&5)")>0),"Threshold Funding Year (reserve balance at critical point).","") -> Threshold Funding Year (reserve balance at critical point).
K51: Recommended Reserve Funding Table | V51: Funding Plan Settings
V52: Current Fiscal Year: | Y52: ='Property Info'!B10 -> 2026
V53: First Non-Budgeted Year: | Y53: ='Property Info'!$B$12 -> 2027
K54: Year | L54: Reserve Contributions | M54: Reserve Balances | N54: Year | O54: Reserve Contributions | P54: Reserve Balances | Q54: Year | R54: Reserve Contributions | S54: Reserve Balances | V54: Reserve Balance ($): | Y54: 52679
V55: Reserve Balance Date: | Y55: ='Property Info'!$B$15 -> 46053
V56: Reserve Balance Projected: | Y56: ='Property Info'!$B$16 -> No
K57: =Current_Fiscal_Year+1 -> 2027 | L57: =F11 -> 19000 | M57: =F16 -> 84789 | N57: =K57+10 -> 2037 | O57: =P11 -> 26000 | P57: =P16 -> 195851.95 | Q57: =N57+10 -> 2047 | R57: =K32 -> 29500 | S57: =K37 -> 177220.35 | V57: Current Year Contributions ($): | Y57: 11532
V58: Next Year Contributions ($): | Y58: 0
K59: =K57+1 -> 2028 | L59: =G11 -> 19600 | M59: =G16 -> 85197.5 | N59: =N57+1 -> 2038 | O59: =Q11 -> 26800 | P59: =Q16 -> 151961.45 | Q59: =Q57+1 -> 2048 | R59: =L32 -> 30400 | S59: =L37 -> 171883.25 | V59: Inflation Rate: | Y59: ='Property Info'!$B$19 -> 0.032
V60: Remaining Budgeted Periods: | Y60: ='Property Info'!$B$13 -> 11
K61: =K59+1 -> 2029 | L61: =H11 -> 20200 | M61: =H16 -> 80050.45 | N61: =N59+1 -> 2039 | O61: =R11 -> 27700 | P61: =R16 -> 153164.05 | Q61: =Q59+1 -> 2049 | R61: =M32 -> 31400 | S61: =M37 -> 166182.95 | V61: Total Budgeted Periods: | Y61: ='Property Info'!$B$21 -> 12
V62: Round Funding To ($): | Y62: ='Property Info'!$B$23 -> 100
K63: =K61+1 -> 2030 | L63: =I11 -> 20800 | M63: =I16 -> 102659.45 | N63: =N61+1 -> 2040 | O63: =S11 -> 28600 | P63: =S16 -> 185113.05 | Q63: =Q61+1 -> 2050 | R63: =N32 -> 32400 | S63: =N37 -> 105436.75 | V63: % Above Min For Threshold: | Y63: 0.1
K65: =K63+1 -> 2031 | L65: =J11 -> 21500 | M65: =J16 -> 111531.25 | N65: =N63+1 -> 2041 | O65: =T11 -> 29500 | P65: =T16 -> 20321.55 | Q65: =Q63+1 -> 2051 | R65: =O32 -> 33400 | S65: =O37 -> 37837.25
K67: =K65+1 -> 2032 | L67: =K11 -> 22200 | M67: =K16 -> 136184.25 | N67: =N65+1 -> 2042 | O67: =F32 -> 29500 | P67: =F37 -> 50522.55 | Q67: =Q65+1 -> 2052 | R67: =P32 -> 34500 | S67: =P37 -> 73439.25
K69: =K67+1 -> 2033 | L69: =L11 -> 22900 | M69: =L16 -> 162037.25 | N69: =N67+1 -> 2043 | O69: =G32 -> 29500 | P69: =G37 -> 72787.65 | Q69: =Q67+1 -> 2053 | R69: =Q32 -> 35600 | S69: =Q37 -> 110864.25
K71: =K69+1 -> 2034 | L71: =M11 -> 23600 | M71: =M16 -> 179757.85 | N71: =N69+1 -> 2044 | O71: =H32 -> 29500 | P71: =H37 -> 104038.65 | Q71: =Q69+1 -> 2054 | R71: =R32 -> 36700 | S71: =R37 -> 132581.65
K73: =K71+1 -> 2035 | L73: =N11 -> 24400 | M73: =N16 -> 207996.85 | N73: =N71+1 -> 2045 | O73: =I32 -> 29500 | P73: =I37 -> 135914.65 | Q73: =Q71+1 -> 2055 | R73: =S32 -> 37900 | S73: =S37 -> 173512.65
K75: =K73+1 -> 2036 | L75: =O11 -> 25200 | M75: =O16 -> 166266.95 | N75: =N73+1 -> 2046 | O75: =J32 -> 29500 | P75: =J37 -> 144534.35 | Q75: =Q73+1 -> 2056 | R75: =T32 -> 39100 | S75: =T37 -> 183733.45
C992: Year | D992: =Y52 -> 2026 | E992: =D992+1 -> 2027 | F992: =E992+1 -> 2028 | G992: =F992+1 -> 2029 | H992: =G992+1 -> 2030 | I992: =H992+1 -> 2031 | J992: =I992+1 -> 2032 | K992: =J992+1 -> 2033 | L992: =K992+1 -> 2034 | ... AH992: =AG992+1 -> 2056
C993: Reserve Contributions | D993: =E8 -> 10571 | E993: =F8 -> 19000 | F993: =G8 -> 19600 | G993: =H8 -> 20200 | H993: =I8 -> 20800 | I993: =J8 -> 21500 | J993: =K8 -> 22200 | K993: =L8 -> 22900 | ... S993: =T8 -> 29500 | T993: =F29 -> 29500 | U993: =G29 -> 29500 | V993: =H29 -> 29500 | W993: =I29 -> 29500 | X993: =J29 -> 29500 | Y993: =K29 -> 29500 | Z993: =L29 -> 30400 | AA993: =M29 -> 31400 | ... AH993: =T29 -> 39100
C994: Additional Assessments | D994: =E9 | E994: =F9 | F994: =G9 | G994: =H9 | H994: =I9 | I994: =J9 | J994: =K9 | K994: =L9 | ... S994: =T9 | T994: =F30 | U994: =G30 | V994: =H30 | W994: =I30 | X994: =J30 | Y994: =K30 | Z994: =L30 | AA994: =M30 | ... AH994: =T30
C995: Additional Reserve Contributions | D995: =E10 | E995: =F10 | F995: =G10 | G995: =H10 | H995: =I10 | I995: =J10 | J995: =K10 | K995: =L10 | ... S995: =T10 | T995: =F31 | U995: =G31 | V995: =H31 | W995: =I31 | X995: =J31 | Y995: =K31 | Z995: =L31 | AA995: =M31 | ... AH995: =T31
C996: Reserve Balance | D996: =E16 -> 64313 | E996: =F16 -> 84789 | F996: =G16 -> 85197.5 | G996: =H16 -> 80050.45 | H996: =I16 -> 102659.45 | I996: =J16 -> 111531.25 | J996: =K16 -> 136184.25 | K996: =L16 -> 162037.25 | ... S996: =T16 -> 20321.55 | T996: =F37 -> 50522.55 | U996: =G37 -> 72787.65 | V996: =H37 -> 104038.65 | W996: =I37 -> 135914.65 | X996: =J37 -> 144534.35 | Y996: =K37 -> 177220.35 | Z996: =L37 -> 171883.25 | AA996: =M37 -> 166182.95 | ... AH996: =T37 -> 183733.45
C1000: Reference Expenditure Sheets | D1000: 0 | E1000: 1 | F1000: 2 | G1000: 3 | H1000: 4 | I1000: 5 | J1000: 6 | K1000: 7 | L1000: 8 | M1000: 9 | N1000: 10 | O1000: 11 | P1000: 12 | Q1000: 13 | R1000: 14 | S1000: 15 | T1000: 16 | U1000: 17 | V1000: 18 | W1000: 19 | X1000: 20 | Y1000: 21 | Z1000: 22 | AA1000: 23 | AB1000: 24 | AC1000: 25 | AD1000: 26 | AE1000: 27 | AF1000: 28 | AG1000: 29 | AH1000: 30
C1001: Expenditures | D1001: =-IF($C1001="",0,INDIRECT("'"& $C1001 & "'!" & "expenditures" & ExpenseTable303[[#Headers],[0]])) -> 0 | E1001: =-IF($C1001="",0,INDIRECT("'"& $C1001 & "'!" & "expenditures" & ExpenseTable303[[#Headers],[1]])) -> 0 | F1001: =-IF($C1001="",0,INDIRECT("'"& $C1001 & "'!" & "expenditures" & ExpenseTable303[[#Headers],[2]])) -> -20874.5 | G1001: =-IF($C1001="",0,INDIRECT("'"& $C1001 & "'!" & "expenditures" & ExpenseTable303[[#Headers],[3]])) -> -26983.05 | H1001: =-IF($C1001="",0,INDIRECT("'"& $C1001 & "'!" & "expenditures" & ExpenseTable303[[#Headers],[4]])) -> 0 | I1001: =-IF($C1001="",0,INDIRECT("'"& $C1001 & "'!" & "expenditures" & ExpenseTable303[[#Headers],[5]])) -> -14749.2 | J1001: =-IF($C1001="",0,INDIRECT("'"& $C1001 & "'!" & "expenditures" & ExpenseTable303[[#Headers],[6]])) -> 0 | K1001: =-IF($C1001="",0,INDIRECT("'"& $C1001 & "'!" & "expenditures" & ExpenseTable303[[#Headers],[7]])) -> 0 | L1001: =-IF($C1001="",0,INDIRECT("'"& $C1001 & "'!" & "expenditures" & ExpenseTable303[[#Headers],[8]])) -> -9263.4 | M1001: =-IF($C1001="",0,INDIRECT("'"& $C1001 & "'!" & "expenditures" & ExpenseTable303[[#Headers],[9]])) -> 0 | N1001: =-IF($C1001="",0,INDIRECT("'"& $C1001 & "'!" & "expenditures" & ExpenseTable303[[#Headers],[10]])) -> -70635.9 | O1001: =-IF($C1001="",0,INDIRECT("'"& $C1001 & "'!" & "expenditures" & ExpenseTable303[[#Headers],[11]])) -> 0 | P1001: =-IF($C1001="",0,INDIRECT("'"& $C1001 & "'!" & "expenditures" & ExpenseTable303[[#Headers],[12]])) -> -74134.5 | Q1001: =-IF($C1001="",0,INDIRECT("'"& $C1001 & "'!" & "expenditures" & ExpenseTable303[[#Headers],[13]])) -> -29518.4 | R1001: =-IF($C1001="",0,INDIRECT("'"& $C1001 & "'!" & "expenditures" & ExpenseTable303[[#Headers],[14]])) -> 0 | S1001: =-IF($C1001="",0,INDIRECT("'"& $C1001 & "'!" & "expenditures" & ExpenseTable303[[#Headers],[15]])) -> -196325.5 | T1001: =-IF($C1001="",0,INDIRECT("'"& $C1001 & "'!" & "expenditures" & ExpenseTable303[[#Headers],[16]])) -> 0 | U1001: =-IF($C1001="",0,INDIRECT("'"& $C1001 & "'!" & "expenditures" & ExpenseTable303[[#Headers],[17]])) -> -8455.9 | V1001: =-IF($C1001="",0,INDIRECT("'"& $C1001 & "'!" & "expenditures" & ExpenseTable303[[#Headers],[18]])) -> 0 | W1001: =-IF($C1001="",0,INDIRECT("'"& $C1001 & "'!" & "expenditures" & ExpenseTable303[[#Headers],[19]])) -> 0 | X1001: =-IF($C1001="",0,INDIRECT("'"& $C1001 & "'!" & "expenditures" & ExpenseTable303[[#Headers],[20]])) -> -23657.3 | Y1001: =-IF($C1001="",0,INDIRECT("'"& $C1001 & "'!" & "expenditures" & ExpenseTable303[[#Headers],[21]])) -> 0 | Z1001: =-IF($C1001="",0,INDIRECT("'"& $C1001 & "'!" & "expenditures" & ExpenseTable303[[#Headers],[22]])) -> -39193.1 | AA1001: =-IF($C1001="",0,INDIRECT("'"& $C1001 & "'!" & "expenditures" & ExpenseTable303[[#Headers],[23]])) -> -40447.3 | AB1001: =-IF($C1001="",0,INDIRECT("'"& $C1001 & "'!" & "expenditures" & ExpenseTable303[[#Headers],[24]])) -> -95835.2 | AC1001: =-IF($C1001="",0,INDIRECT("'"& $C1001 & "'!" & "expenditures" & ExpenseTable303[[#Headers],[25]])) -> -102418.5 | AD1001: =-IF($C1001="",0,INDIRECT("'"& $C1001 & "'!" & "expenditures" & ExpenseTable303[[#Headers],[26]])) -> 0 | AE1001: =-IF($C1001="",0,INDIRECT("'"& $C1001 & "'!" & "expenditures" & ExpenseTable303[[#Headers],[27]])) -> 0 | AF1001: =-IF($C1001="",0,INDIRECT("'"& $C1001 & "'!" & "expenditures" & ExpenseTable303[[#Headers],[28]])) -> -17392.6 | AG1001: =-IF($C1001="",0,INDIRECT("'"& $C1001 & "'!" & "expenditures" & ExpenseTable303[[#Headers],[29]])) -> 0 | AH1001: =-IF($C1001="",0,INDIRECT("'"& $C1001 & "'!" & "expenditures" & ExpenseTable303[[#Headers],[30]])) -> -32416.2
D1002: =-IF($C1002="",0,INDIRECT("'"& $C1002 & "'!" & "expenditures" & ExpenseTable303[[#Headers],[0]])) -> 0 | E1002: =-IF($C1002="",0,INDIRECT("'"& $C1002 & "'!" & "expenditures" & ExpenseTable303[[#Headers],[1]])) -> 0 | F1002: =-IF($C1002="",0,INDIRECT("'"& $C1002 & "'!" & "expenditures" & ExpenseTable303[[#Headers],[2]])) -> 0 | G1002: =-IF($C1002="",0,INDIRECT("'"& $C1002 & "'!" & "expenditures" & ExpenseTable303[[#Headers],[3]])) -> 0 | H1002: =-IF($C1002="",0,INDIRECT("'"& $C1002 & "'!" & "expenditures" & ExpenseTable303[[#Headers],[4]])) -> 0 | I1002: =-IF($C1002="",0,INDIRECT("'"& $C1002 & "'!" & "expenditures" & ExpenseTable303[[#Headers],[5]])) -> 0 | J1002: =-IF($C1002="",0,INDIRECT("'"& $C1002 & "'!" & "expenditures" & ExpenseTable303[[#Headers],[6]])) -> 0 | K1002: =-IF($C1002="",0,INDIRECT("'"& $C1002 & "'!" & "expenditures" & ExpenseTable303[[#Headers],[7]])) -> 0 | L1002: =-IF($C1002="",0,INDIRECT("'"& $C1002 & "'!" & "expenditures" & ExpenseTable303[[#Headers],[8]])) -> 0 | M1002: =-IF($C1002="",0,INDIRECT("'"& $C1002 & "'!" & "expenditures" & ExpenseTable303[[#Headers],[9]])) -> 0 | N1002: =-IF($C1002="",0,INDIRECT("'"& $C1002 & "'!" & "expenditures" & ExpenseTable303[[#Headers],[10]])) -> 0 | O1002: =-IF($C1002="",0,INDIRECT("'"& $C1002 & "'!" & "expenditures" & ExpenseTable303[[#Headers],[11]])) -> 0 | P1002: =-IF($C1002="",0,INDIRECT("'"& $C1002 & "'!" & "expenditures" & ExpenseTable303[[#Headers],[12]])) -> 0 | Q1002: =-IF($C1002="",0,INDIRECT("'"& $C1002 & "'!" & "expenditures" & ExpenseTable303[[#Headers],[13]])) -> 0 | R1002: =-IF($C1002="",0,INDIRECT("'"& $C1002 & "'!" & "expenditures" & ExpenseTable303[[#Headers],[14]])) -> 0 | S1002: =-IF($C1002="",0,INDIRECT("'"& $C1002 & "'!" & "expenditures" & ExpenseTable303[[#Headers],[15]])) -> 0 | T1002: =-IF($C1002="",0,INDIRECT("'"& $C1002 & "'!" & "expenditures" & ExpenseTable303[[#Headers],[16]])) -> 0 | U1002: =-IF($C1002="",0,INDIRECT("'"& $C1002 & "'!" & "expenditures" & ExpenseTable303[[#Headers],[17]])) -> 0 | V1002: =-IF($C1002="",0,INDIRECT("'"& $C1002 & "'!" & "expenditures" & ExpenseTable303[[#Headers],[18]])) -> 0 | W1002: =-IF($C1002="",0,INDIRECT("'"& $C1002 & "'!" & "expenditures" & ExpenseTable303[[#Headers],[19]])) -> 0 | X1002: =-IF($C1002="",0,INDIRECT("'"& $C1002 & "'!" & "expenditures" & ExpenseTable303[[#Headers],[20]])) -> 0 | Y1002: =-IF($C1002="",0,INDIRECT("'"& $C1002 & "'!" & "expenditures" & ExpenseTable303[[#Headers],[21]])) -> 0 | Z1002: =-IF($C1002="",0,INDIRECT("'"& $C1002 & "'!" & "expenditures" & ExpenseTable303[[#Headers],[22]])) -> 0 | AA1002: =-IF($C1002="",0,INDIRECT("'"& $C1002 & "'!" & "expenditures" & ExpenseTable303[[#Headers],[23]])) -> 0 | AB1002: =-IF($C1002="",0,INDIRECT("'"& $C1002 & "'!" & "expenditures" & ExpenseTable303[[#Headers],[24]])) -> 0 | AC1002: =-IF($C1002="",0,INDIRECT("'"& $C1002 & "'!" & "expenditures" & ExpenseTable303[[#Headers],[25]])) -> 0 | AD1002: =-IF($C1002="",0,INDIRECT("'"& $C1002 & "'!" & "expenditures" & ExpenseTable303[[#Headers],[26]])) -> 0 | AE1002: =-IF($C1002="",0,INDIRECT("'"& $C1002 & "'!" & "expenditures" & ExpenseTable303[[#Headers],[27]])) -> 0 | AF1002: =-IF($C1002="",0,INDIRECT("'"& $C1002 & "'!" & "expenditures" & ExpenseTable303[[#Headers],[28]])) -> 0 | AG1002: =-IF($C1002="",0,INDIRECT("'"& $C1002 & "'!" & "expenditures" & ExpenseTable303[[#Headers],[29]])) -> 0 | AH1002: =-IF($C1002="",0,INDIRECT("'"& $C1002 & "'!" & "expenditures" & ExpenseTable303[[#Headers],[30]])) -> 0
C1003: Total | D1003: =SUBTOTAL(109,ExpenseTable303[0]) -> 0 | E1003: =SUBTOTAL(109,ExpenseTable303[1]) -> 0 | F1003: =SUBTOTAL(109,ExpenseTable303[2]) -> -20874.5 | G1003: =SUBTOTAL(109,ExpenseTable303[3]) -> -26983.05 | H1003: =SUBTOTAL(109,ExpenseTable303[4]) -> 0 | I1003: =SUBTOTAL(109,ExpenseTable303[5]) -> -14749.2 | J1003: =SUBTOTAL(109,ExpenseTable303[6]) -> 0 | K1003: =SUBTOTAL(109,ExpenseTable303[7]) -> 0 | L1003: =SUBTOTAL(109,ExpenseTable303[8]) -> -9263.4 | M1003: =SUBTOTAL(109,ExpenseTable303[9]) -> 0 | N1003: =SUBTOTAL(109,ExpenseTable303[10]) -> -70635.9 | O1003: =SUBTOTAL(109,ExpenseTable303[11]) -> 0 | P1003: =SUBTOTAL(109,ExpenseTable303[12]) -> -74134.5 | Q1003: =SUBTOTAL(109,ExpenseTable303[13]) -> -29518.4 | R1003: =SUBTOTAL(109,ExpenseTable303[14]) -> 0 | S1003: =SUBTOTAL(109,ExpenseTable303[15]) -> -196325.5 | T1003: =SUBTOTAL(109,ExpenseTable303[16]) -> 0 | U1003: =SUBTOTAL(109,ExpenseTable303[17]) -> -8455.9 | V1003: =SUBTOTAL(109,ExpenseTable303[18]) -> 0 | W1003: =SUBTOTAL(109,ExpenseTable303[19]) -> 0 | X1003: =SUBTOTAL(109,ExpenseTable303[20]) -> -23657.3 | Y1003: =SUBTOTAL(109,ExpenseTable303[21]) -> 0 | Z1003: =SUBTOTAL(109,ExpenseTable303[22]) -> -39193.1 | AA1003: =SUBTOTAL(109,ExpenseTable303[23]) -> -40447.3 | AB1003: =SUBTOTAL(109,ExpenseTable303[24]) -> -95835.2 | AC1003: =SUBTOTAL(109,ExpenseTable303[25]) -> -102418.5 | AD1003: =SUBTOTAL(109,ExpenseTable303[26]) -> 0 | AE1003: =SUBTOTAL(109,ExpenseTable303[27]) -> 0 | AF1003: =SUBTOTAL(109,ExpenseTable303[28]) -> -17392.6 | AG1003: =SUBTOTAL(109,ExpenseTable303[29]) -> 0 | AH1003: =SUBTOTAL(109,ExpenseTable303[30]) -> -32416.2
AI1004: =MIN(D1005:AH1005) -> 0.10350948
D1005: =IFERROR(IF(ExpenseTable303[[#Totals],[0]]<>0,-D996/ExpenseTable303[[#Totals],[0]],""),"") | E1005: =IFERROR(IF(ExpenseTable303[[#Totals],[1]]<>0,-E996/ExpenseTable303[[#Totals],[1]],""),"") | F1005: =IFERROR(IF(ExpenseTable303[[#Totals],[2]]<>0,-F996/ExpenseTable303[[#Totals],[2]],""),"") -> 4.0814151 | G1005: =IFERROR(IF(ExpenseTable303[[#Totals],[3]]<>0,-G996/ExpenseTable303[[#Totals],[3]],""),"") -> 2.9666939 | H1005: =IFERROR(IF(ExpenseTable303[[#Totals],[4]]<>0,-H996/ExpenseTable303[[#Totals],[4]],""),"") | I1005: =IFERROR(IF(ExpenseTable303[[#Totals],[5]]<>0,-I996/ExpenseTable303[[#Totals],[5]],""),"") -> 7.5618508 | J1005: =IFERROR(IF(ExpenseTable303[[#Totals],[6]]<>0,-J996/ExpenseTable303[[#Totals],[6]],""),"") | K1005: =IFERROR(IF(ExpenseTable303[[#Totals],[7]]<>0,-K996/ExpenseTable303[[#Totals],[7]],""),"") | L1005: =IFERROR(IF(ExpenseTable303[[#Totals],[8]]<>0,-L996/ExpenseTable303[[#Totals],[8]],""),"") -> 19.40517 | M1005: =IFERROR(IF(ExpenseTable303[[#Totals],[9]]<>0,-M996/ExpenseTable303[[#Totals],[9]],""),"") | N1005: =IFERROR(IF(ExpenseTable303[[#Totals],[10]]<>0,-N996/ExpenseTable303[[#Totals],[10]],""),"") -> 2.353859 | O1005: =IFERROR(IF(ExpenseTable303[[#Totals],[11]]<>0,-O996/ExpenseTable303[[#Totals],[11]],""),"") | P1005: =IFERROR(IF(ExpenseTable303[[#Totals],[12]]<>0,-P996/ExpenseTable303[[#Totals],[12]],""),"") -> 2.0498074 | Q1005: =IFERROR(IF(ExpenseTable303[[#Totals],[13]]<>0,-Q996/ExpenseTable303[[#Totals],[13]],""),"") -> 5.1887653 | R1005: =IFERROR(IF(ExpenseTable303[[#Totals],[14]]<>0,-R996/ExpenseTable303[[#Totals],[14]],""),"") | S1005: =IFERROR(IF(ExpenseTable303[[#Totals],[15]]<>0,-S996/ExpenseTable303[[#Totals],[15]],""),"") -> 0.10350948 | T1005: =IFERROR(IF(ExpenseTable303[[#Totals],[16]]<>0,-T996/ExpenseTable303[[#Totals],[16]],""),"") | U1005: =IFERROR(IF(ExpenseTable303[[#Totals],[17]]<>0,-U996/ExpenseTable303[[#Totals],[17]],""),"") -> 8.6079128 | V1005: =IFERROR(IF(ExpenseTable303[[#Totals],[18]]<>0,-V996/ExpenseTable303[[#Totals],[18]],""),"") | W1005: =IFERROR(IF(ExpenseTable303[[#Totals],[19]]<>0,-W996/ExpenseTable303[[#Totals],[19]],""),"") | X1005: =IFERROR(IF(ExpenseTable303[[#Totals],[20]]<>0,-X996/ExpenseTable303[[#Totals],[20]],""),"") -> 6.1095032 | Y1005: =IFERROR(IF(ExpenseTable303[[#Totals],[21]]<>0,-Y996/ExpenseTable303[[#Totals],[21]],""),"") | Z1005: =IFERROR(IF(ExpenseTable303[[#Totals],[22]]<>0,-Z996/ExpenseTable303[[#Totals],[22]],""),"") -> 4.3855487 | AA1005: =IFERROR(IF(ExpenseTable303[[#Totals],[23]]<>0,-AA996/ExpenseTable303[[#Totals],[23]],""),"") -> 4.108629 | AB1005: =IFERROR(IF(ExpenseTable303[[#Totals],[24]]<>0,-AB996/ExpenseTable303[[#Totals],[24]],""),"") -> 1.1001881 | AC1005: =IFERROR(IF(ExpenseTable303[[#Totals],[25]]<>0,-AC996/ExpenseTable303[[#Totals],[25]],""),"") -> 0.36943765 | AD1005: =IFERROR(IF(ExpenseTable303[[#Totals],[26]]<>0,-AD996/ExpenseTable303[[#Totals],[26]],""),"") | AE1005: =IFERROR(IF(ExpenseTable303[[#Totals],[27]]<>0,-AE996/ExpenseTable303[[#Totals],[27]],""),"") | AF1005: =IFERROR(IF(ExpenseTable303[[#Totals],[28]]<>0,-AF996/ExpenseTable303[[#Totals],[28]],""),"") -> 7.622877 | AG1005: =IFERROR(IF(ExpenseTable303[[#Totals],[29]]<>0,-AG996/ExpenseTable303[[#Totals],[29]],""),"") | AH1005: =IFERROR(IF(ExpenseTable303[[#Totals],[30]]<>0,-AH996/ExpenseTable303[[#Totals],[30]],""),"") -> 5.6679515
